Workbook
Name ___INDEX_SHEET___ASAP_Utilities: #REF!
Name ___INDEX_SHEET___ASAP_Utilities: #REF!
Name AccountType: #REF!
Name AccountType: #REF!
Name CountryCode: "OFFSET($B$1,0,0,COUNT($B:$B),1)"

Sheet Store P&L - Summary
B2: Stores P&L - YTD Apr 2025
B3: (SAR'000')
I4: Sales | Q4: Product Margin | Y4: Commercial Margin | AG4: Stock Loss | AO4: Supply Chain Expenses | AW4: Gross Profit | BE4: Staff Expense | BM4: Operating Expenses | BU4: Rent Expense | CC4: EBITDA | CK4: Depreciation & Interest | CS4: Net Income / (Loss)
B5: Region | C5: District | D5: Location | E5: Loc Name | F5: Format | G5: Status | I5: Actual | J5: Budget | K5: LY | L5: Var Vs. Bud | M5: Var vs. LY | N5: Var vs. Bud % | O5: Var vs. LY % | Q5: Actual | R5: Budget | S5: LY | T5: Var Vs. Bud | U5: Var vs. LY | V5: Var vs. Bud % | W5: Var vs. LY % | Y5: Actual | Z5: Budget | AA5: LY | AB5: Var Vs. Bud | AC5: Var vs. LY | AD5: Var vs. Bud % | AE5: Var vs. LY % | AG5: Actual | AH5: Budget | AI5: LY | AJ5: Var Vs. Bud | AK5: Var vs. LY | AL5: Var vs. Bud % | AM5: Var vs. LY % | AO5: Actual | AP5: Budget | AQ5: LY | AR5: Var Vs. Bud | AS5: Var vs. LY | AT5: Var vs. Bud % | AU5: Var vs. LY % | AW5: Actual | AX5: Budget | AY5: LY | AZ5: Var Vs. Bud | BA5: Var vs. LY | BB5: Var vs. Bud % | BC5: Var vs. LY % | BE5: Actual | BF5: Budget | BG5: LY | BH5: Var Vs. Bud | BI5: Var vs. LY | BJ5: Var vs. Bud % | BK5: Var vs. LY % | BM5: Actual | BN5: Budget | BO5: LY | BP5: Var Vs. Bud | BQ5: Var vs. LY | BR5: Var vs. Bud % | BS5: Var vs. LY % | BU5: Actual | BV5: Budget | BW5: LY | BX5: Var Vs. Bud | BY5: Var vs. LY | BZ5: Var vs. Bud % | CA5: Var vs. LY % | CC5: Actual | CD5: Budget | CE5: LY | CF5: Var Vs. Bud | CG5: Var vs. LY | CH5: Var vs. Bud % | CI5: Var vs. LY % | CK5: Actual | CL5: Budget | CM5: LY | CN5: Var Vs. Bud | CO5: Var vs. LY | CP5: Var vs. Bud % | CQ5: Var vs. LY % | CS5: Actual | CT5: Budget | CU5: LY | CV5: Var Vs. Bud | CW5: Var vs. LY | CX5: Var vs. Bud % | CY5: Var vs. LY %
B6: Central | C6: Riyadh - Crescent | D6: 110 | E6: Al Quds-Re Opened | F6: Super | G6: LFL | I6: =SUMIFS('P&L Data'!$N:$N,'P&L Data'!$B:$B,$D6,'P&L Data'!$C:$C,$I$4) -> 27870.318 | J6: =SUMIFS('P&L Data'!$P:$P,'P&L Data'!$B:$B,$D6,'P&L Data'!$C:$C,$I$4) -> 27368.313 | K6: =SUMIFS('P&L Data'!$T:$T,'P&L Data'!$B:$B,$D6,'P&L Data'!$C:$C,$I$4) -> 26172.75 | L6: =I6-J6 -> 502.0054 | M6: =I6-K6 -> 1697.5675 | N6: =IFERROR((I6-J6)/ABS(J6),0) -> 0.018342578 | O6: =IFERROR((I6-K6)/ABS(K6),0) -> 0.064860113 | Q6: =SUMIFS('P&L Data'!$N:$N,'P&L Data'!$B:$B,$D6,'P&L Data'!$C:$C,$Q$4) -> 2321.9001 | R6: =SUMIFS('P&L Data'!$P:$P,'P&L Data'!$B:$B,$D6,'P&L Data'!$C:$C,$Q$4) -> 2116.8049 | S6: =SUMIFS('P&L Data'!$T:$T,'P&L Data'!$B:$B,$D6,'P&L Data'!$C:$C,$Q$4) -> 2527.3581 | T6: =Q6-R6 -> 205.0952 | U6: =Q6-S6 -> -205.45799 | V6: =IFERROR((Q6-R6)/ABS(R6),0) -> 0.096889041 | W6: =IFERROR((Q6-S6)/ABS(S6),0) -> -0.081293582 | Y6: =SUMIFS('P&L Data'!$N:$N,'P&L Data'!$B:$B,$D6,'P&L Data'!$C:$C,$Y$4) -> 7660.7427 | Z6: =SUMIFS('P&L Data'!$P:$P,'P&L Data'!$B:$B,$D6,'P&L Data'!$C:$C,$Y$4) -> 7189.9922 | AA6: =SUMIFS('P&L Data'!$T:$T,'P&L Data'!$B:$B,$D6,'P&L Data'!$C:$C,$Y$4) -> 7029.3761 | AB6: =Y6-Z6 -> 470.75055 | AC6: =Y6-AA6 -> 631.36658 | AD6: =IFERROR((Y6-Z6)/ABS(Z6),0) -> 0.065473027 | AE6: =IFERROR((Y6-AA6)/ABS(AA6),0) -> 0.089818296 | AG6: =SUMIFS('P&L Data'!$N:$N,'P&L Data'!$B:$B,$D6,'P&L Data'!$C:$C,$AG$4) -> -130.1943 | AH6: =SUMIFS('P&L Data'!$P:$P,'P&L Data'!$B:$B,$D6,'P&L Data'!$C:$C,$AG$4) -> -149.21151 | AI6: =SUMIFS('P&L Data'!$T:$T,'P&L Data'!$B:$B,$D6,'P&L Data'!$C:$C,$AG$4) -> -125.05086 | AJ6: =AG6-AH6 -> 19.01721 | AK6: =AG6-AI6 -> -5.14344 | AL6: =IFERROR((AG6-AH6)/ABS(AH6),0) -> 0.12745136 | AM6: =IFERROR((AG6-AI6)/ABS(AI6),0) -> -0.041130785 | AO6: =SUMIFS('P&L Data'!$N:$N,'P&L Data'!$B:$B,$D6,'P&L Data'!$C:$C,$AO$4) -> -473.35512 | AP6: =SUMIFS('P&L Data'!$P:$P,'P&L Data'!$B:$B,$D6,'P&L Data'!$C:$C,$AO$4) -> -505.86612 | AQ6: =SUMIFS('P&L Data'!$T:$T,'P&L Data'!$B:$B,$D6,'P&L Data'!$C:$C,$AO$4) -> -401.52716 | AR6: =AO6-AP6 -> 32.511 | AS6: =AO6-AQ6 -> -71.827956 | AT6: =IFERROR((AO6-AP6)/ABS(AP6),0) -> 0.064267992 | AU6: =IFERROR((AO6-AQ6)/ABS(AQ6),0) -> -0.17888692 | AW6: =SUMIFS('P&L Data'!$N:$N,'P&L Data'!$B:$B,$D6,'P&L Data'!$C:$C,$AW$4) -> 7057.1933 | AX6: =SUMIFS('P&L Data'!$P:$P,'P&L Data'!$B:$B,$D6,'P&L Data'!$C:$C,$AW$4) -> 6534.9145 | AY6: =SUMIFS('P&L Data'!$T:$T,'P&L Data'!$B:$B,$D6,'P&L Data'!$C:$C,$AW$4) -> 6502.7981 | AZ6: =AW6-AX6 -> 522.27876 | BA6: =AW6-AY6 -> 554.39519 | BB6: =IFERROR((AW6-AX6)/ABS(AX6),0) -> 0.079921284 | BC6: =IFERROR((AW6-AY6)/ABS(AY6),0) -> 0.085254867 | BE6: =SUMIFS('P&L Data'!$N:$N,'P&L Data'!$B:$B,$D6,'P&L Data'!$C:$C,$BE$4) -> -1860.5426 | BF6: =SUMIFS('P&L Data'!$P:$P,'P&L Data'!$B:$B,$D6,'P&L Data'!$C:$C,$BE$4) -> -1796.469 | BG6: =SUMIFS('P&L Data'!$T:$T,'P&L Data'!$B:$B,$D6,'P&L Data'!$C:$C,$BE$4) -> -1761.5087 | BH6: =BE6-BF6 -> -64.07361 | BI6: =BE6-BG6 -> -99.0339 | BJ6: =IFERROR((BE6-BF6)/ABS(BF6),0) -> -0.035666415 | BK6: =IFERROR((BE6-BG6)/ABS(BG6),0) -> -0.056221067 | BM6: =SUMIFS('P&L Data'!$N:$N,'P&L Data'!$B:$B,$D6,'P&L Data'!$C:$C,$BM$4) -> -645.63852 | BN6: =SUMIFS('P&L Data'!$P:$P,'P&L Data'!$B:$B,$D6,'P&L Data'!$C:$C,$BM$4) -> -668.14439 | BO6: =SUMIFS('P&L Data'!$T:$T,'P&L Data'!$B:$B,$D6,'P&L Data'!$C:$C,$BM$4) -> -646.61741 | BP6: =BM6-BN6 -> 22.50587 | BQ6: =BM6-BO6 -> 0.97889 | BR6: =IFERROR((BM6-BN6)/ABS(BN6),0) -> 0.033684141 | BS6: =IFERROR((BM6-BO6)/ABS(BO6),0) -> 0.0015138627 | BU6: =SUMIFS('P&L Data'!$N:$N,'P&L Data'!$B:$B,$D6,'P&L Data'!$C:$C,$BU$4) -> -902.48856 | BV6: =SUMIFS('P&L Data'!$P:$P,'P&L Data'!$B:$B,$D6,'P&L Data'!$C:$C,$BU$4) -> -902.48856 | BW6: =SUMIFS('P&L Data'!$T:$T,'P&L Data'!$B:$B,$D6,'P&L Data'!$C:$C,$BU$4) -> -902.48856 | BX6: =BU6-BV6 -> 0 | BY6: =BU6-BW6 -> 0 | BZ6: =IFERROR((BU6-BV6)/ABS(BV6),0) -> 0 | CA6: =IFERROR((BU6-BW6)/ABS(BW6),0) -> 0 | CC6: =SUMIFS('P&L Data'!$N:$N,'P&L Data'!$B:$B,$D6,'P&L Data'!$C:$C,$CC$4) -> 3648.5236 | CD6: =SUMIFS('P&L Data'!$P:$P,'P&L Data'!$B:$B,$D6,'P&L Data'!$C:$C,$CC$4) -> 3167.8126 | CE6: =SUMIFS('P&L Data'!$T:$T,'P&L Data'!$B:$B,$D6,'P&L Data'!$C:$C,$CC$4) -> 3192.1834 | CF6: =CC6-CD6 -> 480.71102 | CG6: =CC6-CE6 -> 456.34018 | CH6: =IFERROR((CC6-CD6)/ABS(CD6),0) -> 0.15174857 | CI6: =IFERROR((CC6-CE6)/ABS(CE6),0) -> 0.1429555 | CK6: =SUMIFS('P&L Data'!$N:$N,'P&L Data'!$B:$B,$D6,'P&L Data'!$C:$C,$CK$4) -> -835.3406 | CL6: =SUMIFS('P&L Data'!$P:$P,'P&L Data'!$B:$B,$D6,'P&L Data'!$C:$C,$CK$4) -> -836.24459 | CM6: =SUMIFS('P&L Data'!$T:$T,'P&L Data'!$B:$B,$D6,'P&L Data'!$C:$C,$CK$4) -> -912.70721 | CN6: =CK6-CL6 -> 0.90399 | CO6: =CK6-CM6 -> 77.36661 | CP6: =IFERROR((CK6-CL6)/ABS(CL6),0) -> 0.0010810115 | CQ6: =IFERROR((CK6-CM6)/ABS(CM6),0) -> 0.084766077 | CS6: =SUMIFS('P&L Data'!$N:$N,'P&L Data'!$B:$B,$D6,'P&L Data'!$C:$C,$CS$4) -> 2813.183 | CT6: =SUMIFS('P&L Data'!$P:$P,'P&L Data'!$B:$B,$D6,'P&L Data'!$C:$C,$CS$4) -> 2331.568 | CU6: =SUMIFS('P&L Data'!$T:$T,'P&L Data'!$B:$B,$D6,'P&L Data'!$C:$C,$CS$4) -> 2279.4762 | CV6: =CS6-CT6 -> 481.61501 | CW6: =CS6-CU6 -> 533.70679 | CX6: =IFERROR((CS6-CT6)/ABS(CT6),0) -> 0.20656271 | CY6: =IFERROR((CS6-CU6)/ABS(CU6),0) -> 0.23413571
B7: Central | C7: Riyadh - Crescent | D7: 10002 | E7: Rimal Mall | F7: Hyper | G7: LFL | I7: =SUMIFS('P&L Data'!$N:$N,'P&L Data'!$B:$B,$D7,'P&L Data'!$C:$C,$I$4) -> 22333.226 | J7: =SUMIFS('P&L Data'!$P:$P,'P&L Data'!$B:$B,$D7,'P&L Data'!$C:$C,$I$4) -> 19298.603 | K7: =SUMIFS('P&L Data'!$T:$T,'P&L Data'!$B:$B,$D7,'P&L Data'!$C:$C,$I$4) -> 22005.441 | L7: =I7-J7 -> 3034.6223 | M7: =I7-K7 -> 327.78493 | N7: =IFERROR((I7-J7)/ABS(J7),0) -> 0.1572457 | O7: =IFERROR((I7-K7)/ABS(K7),0) -> 0.014895631 | Q7: =SUMIFS('P&L Data'!$N:$N,'P&L Data'!$B:$B,$D7,'P&L Data'!$C:$C,$Q$4) -> 83.63492 | R7: =SUMIFS('P&L Data'!$P:$P,'P&L Data'!$B:$B,$D7,'P&L Data'!$C:$C,$Q$4) -> 758.14798 | S7: =SUMIFS('P&L Data'!$T:$T,'P&L Data'!$B:$B,$D7,'P&L Data'!$C:$C,$Q$4) -> 264.96195 | T7: =Q7-R7 -> -674.51306 | U7: =Q7-S7 -> -181.32703 | V7: =IFERROR((Q7-R7)/ABS(R7),0) -> -0.88968523 | W7: =IFERROR((Q7-S7)/ABS(S7),0) -> -0.68435121 | Y7: =SUMIFS('P&L Data'!$N:$N,'P&L Data'!$B:$B,$D7,'P&L Data'!$C:$C,$Y$4) -> 4679.696 | Z7: =SUMIFS('P&L Data'!$P:$P,'P&L Data'!$B:$B,$D7,'P&L Data'!$C:$C,$Y$4) -> 4649.7724 | AA7: =SUMIFS('P&L Data'!$T:$T,'P&L Data'!$B:$B,$D7,'P&L Data'!$C:$C,$Y$4) -> 4442.2341 | AB7: =Y7-Z7 -> 29.92362 | AC7: =Y7-AA7 -> 237.4619 | AD7: =IFERROR((Y7-Z7)/ABS(Z7),0) -> 0.0064355021 | AE7: =IFERROR((Y7-AA7)/ABS(AA7),0) -> 0.053455511 | AG7: =SUMIFS('P&L Data'!$N:$N,'P&L Data'!$B:$B,$D7,'P&L Data'!$C:$C,$AG$4) -> -78.40686 | AH7: =SUMIFS('P&L Data'!$P:$P,'P&L Data'!$B:$B,$D7,'P&L Data'!$C:$C,$AG$4) -> -128.90878 | AI7: =SUMIFS('P&L Data'!$T:$T,'P&L Data'!$B:$B,$D7,'P&L Data'!$C:$C,$AG$4) -> -131.65797 | AJ7: =AG7-AH7 -> 50.50192 | AK7: =AG7-AI7 -> 53.25111 | AL7: =IFERROR((AG7-AH7)/ABS(AH7),0) -> 0.39176478 | AM7: =IFERROR((AG7-AI7)/ABS(AI7),0) -> 0.40446553 | AO7: =SUMIFS('P&L Data'!$N:$N,'P&L Data'!$B:$B,$D7,'P&L Data'!$C:$C,$AO$4) -> -363.2698 | AP7: =SUMIFS('P&L Data'!$P:$P,'P&L Data'!$B:$B,$D7,'P&L Data'!$C:$C,$AO$4) -> -366.80482 | AQ7: =SUMIFS('P&L Data'!$T:$T,'P&L Data'!$B:$B,$D7,'P&L Data'!$C:$C,$AO$4) -> -332.60495 | AR7: =AO7-AP7 -> 3.53502 | AS7: =AO7-AQ7 -> -30.664848 | AT7: =IFERROR((AO7-AP7)/ABS(AP7),0) -> 0.0096373325 | AU7: =IFERROR((AO7-AQ7)/ABS(AQ7),0) -> -0.092196007 | AW7: =SUMIFS('P&L Data'!$N:$N,'P&L Data'!$B:$B,$D7,'P&L Data'!$C:$C,$AW$4) -> 4238.0194 | AX7: =SUMIFS('P&L Data'!$P:$P,'P&L Data'!$B:$B,$D7,'P&L Data'!$C:$C,$AW$4) -> 4154.0588 | AY7: =SUMIFS('P&L Data'!$T:$T,'P&L Data'!$B:$B,$D7,'P&L Data'!$C:$C,$AW$4) -> 3977.9712 | AZ7: =AW7-AX7 -> 83.96056 | BA7: =AW7-AY7 -> 260.04816 | BB7: =IFERROR((AW7-AX7)/ABS(AX7),0) -> 0.020211693 | BC7: =IFERROR((AW7-AY7)/ABS(AY7),0) -> 0.065372057 | BE7: =SUMIFS('P&L Data'!$N:$N,'P&L Data'!$B:$B,$D7,'P&L Data'!$C:$C,$BE$4) -> -1905.4051 | BF7: =SUMIFS('P&L Data'!$P:$P,'P&L Data'!$B:$B,$D7,'P&L Data'!$C:$C,$BE$4) -> -1677.6926 | BG7: =SUMIFS('P&L Data'!$T:$T,'P&L Data'!$B:$B,$D7,'P&L Data'!$C:$C,$BE$4) -> -2013.0302 | BH7: =BE7-BF7 -> -227.71245 | BI7: =BE7-BG7 -> 107.62508 | BJ7: =IFERROR((BE7-BF7)/ABS(BF7),0) -> -0.13572954 | BK7: =IFERROR((BE7-BG7)/ABS(BG7),0) -> 0.053464216 | BM7: =SUMIFS('P&L Data'!$N:$N,'P&L Data'!$B:$B,$D7,'P&L Data'!$C:$C,$BM$4) -> -1162.8406 | BN7: =SUMIFS('P&L Data'!$P:$P,'P&L Data'!$B:$B,$D7,'P&L Data'!$C:$C,$BM$4) -> -1170.7327 | BO7: =SUMIFS('P&L Data'!$T:$T,'P&L Data'!$B:$B,$D7,'P&L Data'!$C:$C,$BM$4) -> -1233.3777 | BP7: =BM7-BN7 -> 7.8921 | BQ7: =BM7-BO7 -> 70.53715 | BR7: =IFERROR((BM7-BN7)/ABS(BN7),0) -> 0.0067411631 | BS7: =IFERROR((BM7-BO7)/ABS(BO7),0) -> 0.057190225 | BU7: =SUMIFS('P&L Data'!$N:$N,'P&L Data'!$B:$B,$D7,'P&L Data'!$C:$C,$BU$4) -> -1290.9067 | BV7: =SUMIFS('P&L Data'!$P:$P,'P&L Data'!$B:$B,$D7,'P&L Data'!$C:$C,$BU$4) -> -897.84528 | BW7: =SUMIFS('P&L Data'!$T:$T,'P&L Data'!$B:$B,$D7,'P&L Data'!$C:$C,$BU$4) -> -1288.7741 | BX7: =BU7-BV7 -> -393.06144 | BY7: =BU7-BW7 -> -2.13258 | BZ7: =IFERROR((BU7-BV7)/ABS(BV7),0) -> -0.43778304 | CA7: =IFERROR((BU7-BW7)/ABS(BW7),0) -> -0.0016547353 | CC7: =SUMIFS('P&L Data'!$N:$N,'P&L Data'!$B:$B,$D7,'P&L Data'!$C:$C,$CC$4) -> -121.13301 | CD7: =SUMIFS('P&L Data'!$P:$P,'P&L Data'!$B:$B,$D7,'P&L Data'!$C:$C,$CC$4) -> 407.78822 | CE7: =SUMIFS('P&L Data'!$T:$T,'P&L Data'!$B:$B,$D7,'P&L Data'!$C:$C,$CC$4) -> -557.21082 | CF7: =CC7-CD7 -> -528.92123 | CG7: =CC7-CE7 -> 436.07781 | CH7: =IFERROR((CC7-CD7)/ABS(CD7),0) -> -1.2970488 | CI7: =IFERROR((CC7-CE7)/ABS(CE7),0) -> 0.7826083 | CK7: =SUMIFS('P&L Data'!$N:$N,'P&L Data'!$B:$B,$D7,'P&L Data'!$C:$C,$CK$4) -> -361.59676 | CL7: =SUMIFS('P&L Data'!$P:$P,'P&L Data'!$B:$B,$D7,'P&L Data'!$C:$C,$CK$4) -> -345.63358 | CM7: =SUMIFS('P&L Data'!$T:$T,'P&L Data'!$B:$B,$D7,'P&L Data'!$C:$C,$CK$4) -> -431.18724 | CN7: =CK7-CL7 -> -15.96318 | CO7: =CK7-CM7 -> 69.59048 | CP7: =IFERROR((CK7-CL7)/ABS(CL7),0) -> -0.046185269 | CQ7: =IFERROR((CK7-CM7)/ABS(CM7),0) -> 0.16139272 | CS7: =SUMIFS('P&L Data'!$N:$N,'P&L Data'!$B:$B,$D7,'P&L Data'!$C:$C,$CS$4) -> -482.72977 | CT7: =SUMIFS('P&L Data'!$P:$P,'P&L Data'!$B:$B,$D7,'P&L Data'!$C:$C,$CS$4) -> 62.15464 | CU7: =SUMIFS('P&L Data'!$T:$T,'P&L Data'!$B:$B,$D7,'P&L Data'!$C:$C,$CS$4) -> -988.39806 | CV7: =CS7-CT7 -> -544.88441 | CW7: =CS7-CU7 -> 505.66829 | CX7: =IFERROR((CS7-CT7)/ABS(CT7),0) -> -8.7665926 | CY7: =IFERROR((CS7-CU7)/ABS(CU7),0) -> 0.51160389
B8: Central | C8: Riyadh - Crescent Total | I8: =SUBTOTAL(9,I6:I7) -> 50203.544 | J8: =SUBTOTAL(9,J6:J7) -> 46666.916 | K8: =SUBTOTAL(9,K6:K7) -> 48178.191 | L8: =I8-J8 -> 3536.6277 | M8: =I8-K8 -> 2025.3525 | N8: =IFERROR((I8-J8)/ABS(J8),0) -> 0.075784475 | O8: =IFERROR((I8-K8)/ABS(K8),0) -> 0.042038782 | Q8: =SUBTOTAL(9,Q6:Q7) -> 2405.5351 | R8: =SUBTOTAL(9,R6:R7) -> 2874.9529 | S8: =SUBTOTAL(9,S6:S7) -> 2792.3201 | T8: =Q8-R8 -> -469.41786 | U8: =Q8-S8 -> -386.78503 | V8: =IFERROR((Q8-R8)/ABS(R8),0) -> -0.16327845 | W8: =IFERROR((Q8-S8)/ABS(S8),0) -> -0.13851744 | Y8: =SUBTOTAL(9,Y6:Y7) -> 12340.439 | Z8: =SUBTOTAL(9,Z6:Z7) -> 11839.765 | AA8: =SUBTOTAL(9,AA6:AA7) -> 11471.61 | AB8: =Y8-Z8 -> 500.67417 | AC8: =Y8-AA8 -> 868.82848 | AD8: =IFERROR((Y8-Z8)/ABS(Z8),0) -> 0.042287511 | AE8: =IFERROR((Y8-AA8)/ABS(AA8),0) -> 0.075737273 | AG8: =SUBTOTAL(9,AG6:AG7) -> -208.60116 | AH8: =SUBTOTAL(9,AH6:AH7) -> -278.12029 | AI8: =SUBTOTAL(9,AI6:AI7) -> -256.70883 | AJ8: =AG8-AH8 -> 69.51913 | AK8: =AG8-AI8 -> 48.10767 | AL8: =IFERROR((AG8-AH8)/ABS(AH8),0) -> 0.24996066 | AM8: =IFERROR((AG8-AI8)/ABS(AI8),0) -> 0.1874017 | AO8: =SUBTOTAL(9,AO6:AO7) -> -836.62492 | AP8: =SUBTOTAL(9,AP6:AP7) -> -872.67094 | AQ8: =SUBTOTAL(9,AQ6:AQ7) -> -734.13212 | AR8: =AO8-AP8 -> 36.04602 | AS8: =AO8-AQ8 -> -102.4928 | AT8: =IFERROR((AO8-AP8)/ABS(AP8),0) -> 0.041305397 | AU8: =IFERROR((AO8-AQ8)/ABS(AQ8),0) -> -0.13961084 | AW8: =SUBTOTAL(9,AW6:AW7) -> 11295.213 | AX8: =SUBTOTAL(9,AX6:AX7) -> 10688.973 | AY8: =SUBTOTAL(9,AY6:AY7) -> 10480.769 | AZ8: =AW8-AX8 -> 606.23932 | BA8: =AW8-AY8 -> 814.44335 | BB8: =IFERROR((AW8-AX8)/ABS(AX8),0) -> 0.056716328 | BC8: =IFERROR((AW8-AY8)/ABS(AY8),0) -> 0.077708355 | BE8: =SUBTOTAL(9,BE6:BE7) -> -3765.9477 | BF8: =SUBTOTAL(9,BF6:BF7) -> -3474.1617 | BG8: =SUBTOTAL(9,BG6:BG7) -> -3774.5389 | BH8: =BE8-BF8 -> -291.78606 | BI8: =BE8-BG8 -> 8.59118 | BJ8: =IFERROR((BE8-BF8)/ABS(BF8),0) -> -0.083987474 | BK8: =IFERROR((BE8-BG8)/ABS(BG8),0) -> 0.0022760873 | BM8: =SUBTOTAL(9,BM6:BM7) -> -1808.4791 | BN8: =SUBTOTAL(9,BN6:BN7) -> -1838.8771 | BO8: =SUBTOTAL(9,BO6:BO7) -> -1879.9951 | BP8: =BM8-BN8 -> 30.39797 | BQ8: =BM8-BO8 -> 71.51604 | BR8: =IFERROR((BM8-BN8)/ABS(BN8),0) -> 0.016530724 | BS8: =IFERROR((BM8-BO8)/ABS(BO8),0) -> 0.038040545 | BU8: =SUBTOTAL(9,BU6:BU7) -> -2193.3953 | BV8: =SUBTOTAL(9,BV6:BV7) -> -1800.3338 | BW8: =SUBTOTAL(9,BW6:BW7) -> -2191.2627 | BX8: =BU8-BV8 -> -393.06144 | BY8: =BU8-BW8 -> -2.13258 | BZ8: =IFERROR((BU8-BV8)/ABS(BV8),0) -> -0.21832697 | CA8: =IFERROR((BU8-BW8)/ABS(BW8),0) -> -0.00097321969 | CC8: =SUBTOTAL(9,CC6:CC7) -> 3527.3906 | CD8: =SUBTOTAL(9,CD6:CD7) -> 3575.6008 | CE8: =SUBTOTAL(9,CE6:CE7) -> 2634.9726 | CF8: =CC8-CD8 -> -48.21021 | CG8: =CC8-CE8 -> 892.41799 | CH8: =IFERROR((CC8-CD8)/ABS(CD8),0) -> -0.013483108 | CI8: =IFERROR((CC8-CE8)/ABS(CE8),0) -> 0.33868208 | CK8: =SUBTOTAL(9,CK6:CK7) -> -1196.9374 | CL8: =SUBTOTAL(9,CL6:CL7) -> -1181.8782 | CM8: =SUBTOTAL(9,CM6:CM7) -> -1343.8944 | CN8: =CK8-CL8 -> -15.05919 | CO8: =CK8-CM8 -> 146.95709 | CP8: =IFERROR((CK8-CL8)/ABS(CL8),0) -> -0.012741745 | CQ8: =IFERROR((CK8-CM8)/ABS(CM8),0) -> 0.10935166 | CS8: =SUBTOTAL(9,CS6:CS7) -> 2330.4532 | CT8: =SUBTOTAL(9,CT6:CT7) -> 2393.7226 | CU8: =SUBTOTAL(9,CU6:CU7) -> 1291.0781 | CV8: =SUBTOTAL(9,CV6:CV7) -> -63.2694 | CW8: =SUBTOTAL(9,CW6:CW7) -> 1039.3751 | CX8: =IFERROR((CS8-CT8)/ABS(CT8),0) -> -0.026431383 | CY8: =IFERROR((CS8-CU8)/ABS(CU8),0) -> 0.80504428
B9: Central | C9: Riyadh - Nucleus | D9: 10003 | E9: Alia Mall Abo Baker (Takassosi) | F9: Hyper | G9: LFL | I9: =SUMIFS('P&L Data'!$N:$N,'P&L Data'!$B:$B,$D9,'P&L Data'!$C:$C,$I$4) -> 34145.193 | J9: =SUMIFS('P&L Data'!$P:$P,'P&L Data'!$B:$B,$D9,'P&L Data'!$C:$C,$I$4) -> 34354.519 | K9: =SUMIFS('P&L Data'!$T:$T,'P&L Data'!$B:$B,$D9,'P&L Data'!$C:$C,$I$4) -> 31998.823 | L9: =I9-J9 -> -209.32589 | M9: =I9-K9 -> 2146.3701 | N9: =IFERROR((I9-J9)/ABS(J9),0) -> -0.0060931107 | O9: =IFERROR((I9-K9)/ABS(K9),0) -> 0.067076533 | Q9: =SUMIFS('P&L Data'!$N:$N,'P&L Data'!$B:$B,$D9,'P&L Data'!$C:$C,$Q$4) -> 3240.5851 | R9: =SUMIFS('P&L Data'!$P:$P,'P&L Data'!$B:$B,$D9,'P&L Data'!$C:$C,$Q$4) -> 2739.9401 | S9: =SUMIFS('P&L Data'!$T:$T,'P&L Data'!$B:$B,$D9,'P&L Data'!$C:$C,$Q$4) -> 2925.3352 | T9: =Q9-R9 -> 500.64503 | U9: =Q9-S9 -> 315.24988 | V9: =IFERROR((Q9-R9)/ABS(R9),0) -> 0.18272116 | W9: =IFERROR((Q9-S9)/ABS(S9),0) -> 0.10776539 | Y9: =SUMIFS('P&L Data'!$N:$N,'P&L Data'!$B:$B,$D9,'P&L Data'!$C:$C,$Y$4) -> 10062.44 | Z9: =SUMIFS('P&L Data'!$P:$P,'P&L Data'!$B:$B,$D9,'P&L Data'!$C:$C,$Y$4) -> 9378.7189 | AA9: =SUMIFS('P&L Data'!$T:$T,'P&L Data'!$B:$B,$D9,'P&L Data'!$C:$C,$Y$4) -> 8827.104 | AB9: =Y9-Z9 -> 683.72109 | AC9: =Y9-AA9 -> 1235.336 | AD9: =IFERROR((Y9-Z9)/ABS(Z9),0) -> 0.072901331 | AE9: =IFERROR((Y9-AA9)/ABS(AA9),0) -> 0.13994805 | AG9: =SUMIFS('P&L Data'!$N:$N,'P&L Data'!$B:$B,$D9,'P&L Data'!$C:$C,$AG$4) -> -116.60088 | AH9: =SUMIFS('P&L Data'!$P:$P,'P&L Data'!$B:$B,$D9,'P&L Data'!$C:$C,$AG$4) -> -213.42851 | AI9: =SUMIFS('P&L Data'!$T:$T,'P&L Data'!$B:$B,$D9,'P&L Data'!$C:$C,$AG$4) -> -182.12539 | AJ9: =AG9-AH9 -> 96.82763 | AK9: =AG9-AI9 -> 65.52451 | AL9: =IFERROR((AG9-AH9)/ABS(AH9),0) -> 0.45367711 | AM9: =IFERROR((AG9-AI9)/ABS(AI9),0) -> 0.35977691 | AO9: =SUMIFS('P&L Data'!$N:$N,'P&L Data'!$B:$B,$D9,'P&L Data'!$C:$C,$AO$4) -> -585.98803 | AP9: =SUMIFS('P&L Data'!$P:$P,'P&L Data'!$B:$B,$D9,'P&L Data'!$C:$C,$AO$4) -> -642.59945 | AQ9: =SUMIFS('P&L Data'!$T:$T,'P&L Data'!$B:$B,$D9,'P&L Data'!$C:$C,$AO$4) -> -527.19259 | AR9: =AO9-AP9 -> 56.61142 | AS9: =AO9-AQ9 -> -58.795442 | AT9: =IFERROR((AO9-AP9)/ABS(AP9),0) -> 0.088097523 | AU9: =IFERROR((AO9-AQ9)/ABS(AQ9),0) -> -0.11152555 | AW9: =SUMIFS('P&L Data'!$N:$N,'P&L Data'!$B:$B,$D9,'P&L Data'!$C:$C,$AW$4) -> 9359.8511 | AX9: =SUMIFS('P&L Data'!$P:$P,'P&L Data'!$B:$B,$D9,'P&L Data'!$C:$C,$AW$4) -> 8522.691 | AY9: =SUMIFS('P&L Data'!$T:$T,'P&L Data'!$B:$B,$D9,'P&L Data'!$C:$C,$AW$4) -> 8117.786 | AZ9: =AW9-AX9 -> 837.16014 | BA9: =AW9-AY9 -> 1242.0651 | BB9: =IFERROR((AW9-AX9)/ABS(AX9),0) -> 0.098227208 | BC9: =IFERROR((AW9-AY9)/ABS(AY9),0) -> 0.1530054 | BE9: =SUMIFS('P&L Data'!$N:$N,'P&L Data'!$B:$B,$D9,'P&L Data'!$C:$C,$BE$4) -> -2290.0799 | BF9: =SUMIFS('P&L Data'!$P:$P,'P&L Data'!$B:$B,$D9,'P&L Data'!$C:$C,$BE$4) -> -2526.8343 | BG9: =SUMIFS('P&L Data'!$T:$T,'P&L Data'!$B:$B,$D9,'P&L Data'!$C:$C,$BE$4) -> -2193.1746 | BH9: =BE9-BF9 -> 236.75443 | BI9: =BE9-BG9 -> -96.9053 | BJ9: =IFERROR((BE9-BF9)/ABS(BF9),0) -> 0.093696064 | BK9: =IFERROR((BE9-BG9)/ABS(BG9),0) -> -0.044184945 | BM9: =SUMIFS('P&L Data'!$N:$N,'P&L Data'!$B:$B,$D9,'P&L Data'!$C:$C,$BM$4) -> -1038.9385 | BN9: =SUMIFS('P&L Data'!$P:$P,'P&L Data'!$B:$B,$D9,'P&L Data'!$C:$C,$BM$4) -> -1035.2243 | BO9: =SUMIFS('P&L Data'!$T:$T,'P&L Data'!$B:$B,$D9,'P&L Data'!$C:$C,$BM$4) -> -1121.4782 | BP9: =BM9-BN9 -> -3.71424 | BQ9: =BM9-BO9 -> 82.53972 | BR9: =IFERROR((BM9-BN9)/ABS(BN9),0) -> -0.0035878602 | BS9: =IFERROR((BM9-BO9)/ABS(BO9),0) -> 0.073599038 | BU9: =SUMIFS('P&L Data'!$N:$N,'P&L Data'!$B:$B,$D9,'P&L Data'!$C:$C,$BU$4) -> -2279.4567 | BV9: =SUMIFS('P&L Data'!$P:$P,'P&L Data'!$B:$B,$D9,'P&L Data'!$C:$C,$BU$4) -> -2279.4567 | BW9: =SUMIFS('P&L Data'!$T:$T,'P&L Data'!$B:$B,$D9,'P&L Data'!$C:$C,$BU$4) -> -2279.4567 | BX9: =BU9-BV9 -> 0 | BY9: =BU9-BW9 -> 0 | BZ9: =IFERROR((BU9-BV9)/ABS(BV9),0) -> 0 | CA9: =IFERROR((BU9-BW9)/ABS(BW9),0) -> 0 | CC9: =SUMIFS('P&L Data'!$N:$N,'P&L Data'!$B:$B,$D9,'P&L Data'!$C:$C,$CC$4) -> 3751.376 | CD9: =SUMIFS('P&L Data'!$P:$P,'P&L Data'!$B:$B,$D9,'P&L Data'!$C:$C,$CC$4) -> 2681.1757 | CE9: =SUMIFS('P&L Data'!$T:$T,'P&L Data'!$B:$B,$D9,'P&L Data'!$C:$C,$CC$4) -> 2523.6765 | CF9: =CC9-CD9 -> 1070.2003 | CG9: =CC9-CE9 -> 1227.6995 | CH9: =IFERROR((CC9-CD9)/ABS(CD9),0) -> 0.39915338 | CI9: =IFERROR((CC9-CE9)/ABS(CE9),0) -> 0.48647262 | CK9: =SUMIFS('P&L Data'!$N:$N,'P&L Data'!$B:$B,$D9,'P&L Data'!$C:$C,$CK$4) -> -1342.0394 | CL9: =SUMIFS('P&L Data'!$P:$P,'P&L Data'!$B:$B,$D9,'P&L Data'!$C:$C,$CK$4) -> -951.3892 | CM9: =SUMIFS('P&L Data'!$T:$T,'P&L Data'!$B:$B,$D9,'P&L Data'!$C:$C,$CK$4) -> -1133.7776 | CN9: =CK9-CL9 -> -390.65016 | CO9: =CK9-CM9 -> -208.26174 | CP9: =IFERROR((CK9-CL9)/ABS(CL9),0) -> -0.41061025 | CQ9: =IFERROR((CK9-CM9)/ABS(CM9),0) -> -0.18368835 | CS9: =SUMIFS('P&L Data'!$N:$N,'P&L Data'!$B:$B,$D9,'P&L Data'!$C:$C,$CS$4) -> 2409.3367 | CT9: =SUMIFS('P&L Data'!$P:$P,'P&L Data'!$B:$B,$D9,'P&L Data'!$C:$C,$CS$4) -> 1729.7865 | CU9: =SUMIFS('P&L Data'!$T:$T,'P&L Data'!$B:$B,$D9,'P&L Data'!$C:$C,$CS$4) -> 1389.8989 | CV9: =CS9-CT9 -> 679.55017 | CW9: =CS9-CU9 -> 1019.4378 | CX9: =IFERROR((CS9-CT9)/ABS(CT9),0) -> 0.39285205 | CY9: =IFERROR((CS9-CU9)/ABS(CU9),0) -> 0.73346183
B10: Central | C10: Riyadh - Nucleus Total | I10: =SUBTOTAL(9,I9:I9) -> 34145.193 | J10: =SUBTOTAL(9,J9:J9) -> 34354.519 | K10: =SUBTOTAL(9,K9:K9) -> 31998.823 | L10: =I10-J10 -> -209.32589 | M10: =I10-K10 -> 2146.3701 | N10: =IFERROR((I10-J10)/ABS(J10),0) -> -0.0060931107 | O10: =IFERROR((I10-K10)/ABS(K10),0) -> 0.067076533 | Q10: =SUBTOTAL(9,Q9:Q9) -> 3240.5851 | R10: =SUBTOTAL(9,R9:R9) -> 2739.9401 | S10: =SUBTOTAL(9,S9:S9) -> 2925.3352 | T10: =Q10-R10 -> 500.64503 | U10: =Q10-S10 -> 315.24988 | V10: =IFERROR((Q10-R10)/ABS(R10),0) -> 0.18272116 | W10: =IFERROR((Q10-S10)/ABS(S10),0) -> 0.10776539 | Y10: =SUBTOTAL(9,Y9:Y9) -> 10062.44 | Z10: =SUBTOTAL(9,Z9:Z9) -> 9378.7189 | AA10: =SUBTOTAL(9,AA9:AA9) -> 8827.104 | AB10: =Y10-Z10 -> 683.72109 | AC10: =Y10-AA10 -> 1235.336 | AD10: =IFERROR((Y10-Z10)/ABS(Z10),0) -> 0.072901331 | AE10: =IFERROR((Y10-AA10)/ABS(AA10),0) -> 0.13994805 | AG10: =SUBTOTAL(9,AG9:AG9) -> -116.60088 | AH10: =SUBTOTAL(9,AH9:AH9) -> -213.42851 | AI10: =SUBTOTAL(9,AI9:AI9) -> -182.12539 | AJ10: =AG10-AH10 -> 96.82763 | AK10: =AG10-AI10 -> 65.52451 | AL10: =IFERROR((AG10-AH10)/ABS(AH10),0) -> 0.45367711 | AM10: =IFERROR((AG10-AI10)/ABS(AI10),0) -> 0.35977691 | AO10: =SUBTOTAL(9,AO9:AO9) -> -585.98803 | AP10: =SUBTOTAL(9,AP9:AP9) -> -642.59945 | AQ10: =SUBTOTAL(9,AQ9:AQ9) -> -527.19259 | AR10: =AO10-AP10 -> 56.61142 | AS10: =AO10-AQ10 -> -58.795442 | AT10: =IFERROR((AO10-AP10)/ABS(AP10),0) -> 0.088097523 | AU10: =IFERROR((AO10-AQ10)/ABS(AQ10),0) -> -0.11152555 | AW10: =SUBTOTAL(9,AW9:AW9) -> 9359.8511 | AX10: =SUBTOTAL(9,AX9:AX9) -> 8522.691 | AY10: =SUBTOTAL(9,AY9:AY9) -> 8117.786 | AZ10: =AW10-AX10 -> 837.16014 | BA10: =AW10-AY10 -> 1242.0651 | BB10: =IFERROR((AW10-AX10)/ABS(AX10),0) -> 0.098227208 | BC10: =IFERROR((AW10-AY10)/ABS(AY10),0) -> 0.1530054 | BE10: =SUBTOTAL(9,BE9:BE9) -> -2290.0799 | BF10: =SUBTOTAL(9,BF9:BF9) -> -2526.8343 | BG10: =SUBTOTAL(9,BG9:BG9) -> -2193.1746 | BH10: =BE10-BF10 -> 236.75443 | BI10: =BE10-BG10 -> -96.9053 | BJ10: =IFERROR((BE10-BF10)/ABS(BF10),0) -> 0.093696064 | BK10: =IFERROR((BE10-BG10)/ABS(BG10),0) -> -0.044184945 | BM10: =SUBTOTAL(9,BM9:BM9) -> -1038.9385 | BN10: =SUBTOTAL(9,BN9:BN9) -> -1035.2243 | BO10: =SUBTOTAL(9,BO9:BO9) -> -1121.4782 | BP10: =BM10-BN10 -> -3.71424 | BQ10: =BM10-BO10 -> 82.53972 | BR10: =IFERROR((BM10-BN10)/ABS(BN10),0) -> -0.0035878602 | BS10: =IFERROR((BM10-BO10)/ABS(BO10),0) -> 0.073599038 | BU10: =SUBTOTAL(9,BU9:BU9) -> -2279.4567 | BV10: =SUBTOTAL(9,BV9:BV9) -> -2279.4567 | BW10: =SUBTOTAL(9,BW9:BW9) -> -2279.4567 | BX10: =BU10-BV10 -> 0 | BY10: =BU10-BW10 -> 0 | BZ10: =IFERROR((BU10-BV10)/ABS(BV10),0) -> 0 | CA10: =IFERROR((BU10-BW10)/ABS(BW10),0) -> 0 | CC10: =SUBTOTAL(9,CC9:CC9) -> 3751.376 | CD10: =SUBTOTAL(9,CD9:CD9) -> 2681.1757 | CE10: =SUBTOTAL(9,CE9:CE9) -> 2523.6765 | CF10: =CC10-CD10 -> 1070.2003 | CG10: =CC10-CE10 -> 1227.6995 | CH10: =IFERROR((CC10-CD10)/ABS(CD10),0) -> 0.39915338 | CI10: =IFERROR((CC10-CE10)/ABS(CE10),0) -> 0.48647262 | CK10: =SUBTOTAL(9,CK9:CK9) -> -1342.0394 | CL10: =SUBTOTAL(9,CL9:CL9) -> -951.3892 | CM10: =SUBTOTAL(9,CM9:CM9) -> -1133.7776 | CN10: =CK10-CL10 -> -390.65016 | CO10: =CK10-CM10 -> -208.26174 | CP10: =IFERROR((CK10-CL10)/ABS(CL10),0) -> -0.41061025 | CQ10: =IFERROR((CK10-CM10)/ABS(CM10),0) -> -0.18368835 | CS10: =SUBTOTAL(9,CS9:CS9) -> 2409.3367 | CT10: =SUBTOTAL(9,CT9:CT9) -> 1729.7865 | CU10: =SUBTOTAL(9,CU9:CU9) -> 1389.8989 | CV10: =SUBTOTAL(9,CV9:CV9) -> 679.55017 | CW10: =SUBTOTAL(9,CW9:CW9) -> 1019.4378 | CX10: =IFERROR((CS10-CT10)/ABS(CT10),0) -> 0.39285205 | CY10: =IFERROR((CS10-CU10)/ABS(CU10),0) -> 0.73346183
B11: Central | C11: Riyadh - South | D11: 102 | E11: Al Tarmathi | F11: Super | G11: LFL | I11: =SUMIFS('P&L Data'!$N:$N,'P&L Data'!$B:$B,$D11,'P&L Data'!$C:$C,$I$4) -> 10993.125 | J11: =SUMIFS('P&L Data'!$P:$P,'P&L Data'!$B:$B,$D11,'P&L Data'!$C:$C,$I$4) -> 11612.472 | K11: =SUMIFS('P&L Data'!$T:$T,'P&L Data'!$B:$B,$D11,'P&L Data'!$C:$C,$I$4) -> 11815.73 | L11: =I11-J11 -> -619.34621 | M11: =I11-K11 -> -822.60448 | N11: =IFERROR((I11-J11)/ABS(J11),0) -> -0.053334572 | O11: =IFERROR((I11-K11)/ABS(K11),0) -> -0.069619438 | Q11: =SUMIFS('P&L Data'!$N:$N,'P&L Data'!$B:$B,$D11,'P&L Data'!$C:$C,$Q$4) -> 395.85014 | R11: =SUMIFS('P&L Data'!$P:$P,'P&L Data'!$B:$B,$D11,'P&L Data'!$C:$C,$Q$4) -> 551.63802 | S11: =SUMIFS('P&L Data'!$T:$T,'P&L Data'!$B:$B,$D11,'P&L Data'!$C:$C,$Q$4) -> 661.04016 | T11: =Q11-R11 -> -155.78788 | U11: =Q11-S11 -> -265.19002 | V11: =IFERROR((Q11-R11)/ABS(R11),0) -> -0.28240961 | W11: =IFERROR((Q11-S11)/ABS(S11),0) -> -0.40117082 | Y11: =SUMIFS('P&L Data'!$N:$N,'P&L Data'!$B:$B,$D11,'P&L Data'!$C:$C,$Y$4) -> 2655.0971 | Z11: =SUMIFS('P&L Data'!$P:$P,'P&L Data'!$B:$B,$D11,'P&L Data'!$C:$C,$Y$4) -> 2773.7705 | AA11: =SUMIFS('P&L Data'!$T:$T,'P&L Data'!$B:$B,$D11,'P&L Data'!$C:$C,$Y$4) -> 2784.314 | AB11: =Y11-Z11 -> -118.67342 | AC11: =Y11-AA11 -> -129.21693 | AD11: =IFERROR((Y11-Z11)/ABS(Z11),0) -> -0.042784152 | AE11: =IFERROR((Y11-AA11)/ABS(AA11),0) -> -0.046408894 | AG11: =SUMIFS('P&L Data'!$N:$N,'P&L Data'!$B:$B,$D11,'P&L Data'!$C:$C,$AG$4) -> -5.22213 | AH11: =SUMIFS('P&L Data'!$P:$P,'P&L Data'!$B:$B,$D11,'P&L Data'!$C:$C,$AG$4) -> -70.92856 | AI11: =SUMIFS('P&L Data'!$T:$T,'P&L Data'!$B:$B,$D11,'P&L Data'!$C:$C,$AG$4) -> -52.02357 | AJ11: =AG11-AH11 -> 65.70643 | AK11: =AG11-AI11 -> 46.80144 | AL11: =IFERROR((AG11-AH11)/ABS(AH11),0) -> 0.92637479 | AM11: =IFERROR((AG11-AI11)/ABS(AI11),0) -> 0.89961992 | AO11: =SUMIFS('P&L Data'!$N:$N,'P&L Data'!$B:$B,$D11,'P&L Data'!$C:$C,$AO$4) -> -195.52834 | AP11: =SUMIFS('P&L Data'!$P:$P,'P&L Data'!$B:$B,$D11,'P&L Data'!$C:$C,$AO$4) -> -212.42066 | AQ11: =SUMIFS('P&L Data'!$T:$T,'P&L Data'!$B:$B,$D11,'P&L Data'!$C:$C,$AO$4) -> -190.27486 | AR11: =AO11-AP11 -> 16.89232 | AS11: =AO11-AQ11 -> -5.25348 | AT11: =IFERROR((AO11-AP11)/ABS(AP11),0) -> 0.079522962 | AU11: =IFERROR((AO11-AQ11)/ABS(AQ11),0) -> -0.027609953 | AW11: =SUMIFS('P&L Data'!$N:$N,'P&L Data'!$B:$B,$D11,'P&L Data'!$C:$C,$AW$4) -> 2454.3466 | AX11: =SUMIFS('P&L Data'!$P:$P,'P&L Data'!$B:$B,$D11,'P&L Data'!$C:$C,$AW$4) -> 2490.4213 | AY11: =SUMIFS('P&L Data'!$T:$T,'P&L Data'!$B:$B,$D11,'P&L Data'!$C:$C,$AW$4) -> 2542.0156 | AZ11: =AW11-AX11 -> -36.07467 | BA11: =AW11-AY11 -> -87.668973 | BB11: =IFERROR((AW11-AX11)/ABS(AX11),0) -> -0.014485368 | BC11: =IFERROR((AW11-AY11)/ABS(AY11),0) -> -0.034487976 | BE11: =SUMIFS('P&L Data'!$N:$N,'P&L Data'!$B:$B,$D11,'P&L Data'!$C:$C,$BE$4) -> -903.23325 | BF11: =SUMIFS('P&L Data'!$P:$P,'P&L Data'!$B:$B,$D11,'P&L Data'!$C:$C,$BE$4) -> -796.75625 | BG11: =SUMIFS('P&L Data'!$T:$T,'P&L Data'!$B:$B,$D11,'P&L Data'!$C:$C,$BE$4) -> -798.84041 | BH11: =BE11-BF11 -> -106.477 | BI11: =BE11-BG11 -> -104.39284 | BJ11: =IFERROR((BE11-BF11)/ABS(BF11),0) -> -0.13363811 | BK11: =IFERROR((BE11-BG11)/ABS(BG11),0) -> -0.13068047 | BM11: =SUMIFS('P&L Data'!$N:$N,'P&L Data'!$B:$B,$D11,'P&L Data'!$C:$C,$BM$4) -> -238.59393 | BN11: =SUMIFS('P&L Data'!$P:$P,'P&L Data'!$B:$B,$D11,'P&L Data'!$C:$C,$BM$4) -> -260.27438 | BO11: =SUMIFS('P&L Data'!$T:$T,'P&L Data'!$B:$B,$D11,'P&L Data'!$C:$C,$BM$4) -> -240.64897 | BP11: =BM11-BN11 -> 21.68045 | BQ11: =BM11-BO11 -> 2.05504 | BR11: =IFERROR((BM11-BN11)/ABS(BN11),0) -> 0.083298441 | BS11: =IFERROR((BM11-BO11)/ABS(BO11),0) -> 0.0085395753 | BU11: =SUMIFS('P&L Data'!$N:$N,'P&L Data'!$B:$B,$D11,'P&L Data'!$C:$C,$BU$4) -> -827.4336 | BV11: =SUMIFS('P&L Data'!$P:$P,'P&L Data'!$B:$B,$D11,'P&L Data'!$C:$C,$BU$4) -> -827.4336 | BW11: =SUMIFS('P&L Data'!$T:$T,'P&L Data'!$B:$B,$D11,'P&L Data'!$C:$C,$BU$4) -> -827.4336 | BX11: =BU11-BV11 -> 0 | BY11: =BU11-BW11 -> 0 | BZ11: =IFERROR((BU11-BV11)/ABS(BV11),0) -> 0 | CA11: =IFERROR((BU11-BW11)/ABS(BW11),0) -> 0 | CC11: =SUMIFS('P&L Data'!$N:$N,'P&L Data'!$B:$B,$D11,'P&L Data'!$C:$C,$CC$4) -> 485.08585 | CD11: =SUMIFS('P&L Data'!$P:$P,'P&L Data'!$B:$B,$D11,'P&L Data'!$C:$C,$CC$4) -> 605.95707 | CE11: =SUMIFS('P&L Data'!$T:$T,'P&L Data'!$B:$B,$D11,'P&L Data'!$C:$C,$CC$4) -> 675.09262 | CF11: =CC11-CD11 -> -120.87122 | CG11: =CC11-CE11 -> -190.00677 | CH11: =IFERROR((CC11-CD11)/ABS(CD11),0) -> -0.19947159 | CI11: =IFERROR((CC11-CE11)/ABS(CE11),0) -> -0.2814529 | CK11: =SUMIFS('P&L Data'!$N:$N,'P&L Data'!$B:$B,$D11,'P&L Data'!$C:$C,$CK$4) -> -88.80584 | CL11: =SUMIFS('P&L Data'!$P:$P,'P&L Data'!$B:$B,$D11,'P&L Data'!$C:$C,$CK$4) -> -292.64342 | CM11: =SUMIFS('P&L Data'!$T:$T,'P&L Data'!$B:$B,$D11,'P&L Data'!$C:$C,$CK$4) -> -63.60393 | CN11: =CK11-CL11 -> 203.83758 | CO11: =CK11-CM11 -> -25.20191 | CP11: =IFERROR((CK11-CL11)/ABS(CL11),0) -> 0.69653909 | CQ11: =IFERROR((CK11-CM11)/ABS(CM11),0) -> -0.39623196 | CS11: =SUMIFS('P&L Data'!$N:$N,'P&L Data'!$B:$B,$D11,'P&L Data'!$C:$C,$CS$4) -> 396.28001 | CT11: =SUMIFS('P&L Data'!$P:$P,'P&L Data'!$B:$B,$D11,'P&L Data'!$C:$C,$CS$4) -> 313.31365 | CU11: =SUMIFS('P&L Data'!$T:$T,'P&L Data'!$B:$B,$D11,'P&L Data'!$C:$C,$CS$4) -> 611.48869 | CV11: =CS11-CT11 -> 82.96636 | CW11: =CS11-CU11 -> -215.20868 | CX11: =IFERROR((CS11-CT11)/ABS(CT11),0) -> 0.26480289 | CY11: =IFERROR((CS11-CU11)/ABS(CU11),0) -> -0.35194221
B12: Central | C12: Riyadh - South | D12: 10006 | E12: Gs Riyadh Bilal Abn Rabah | F12: Hyper | G12: LFL | I12: =SUMIFS('P&L Data'!$N:$N,'P&L Data'!$B:$B,$D12,'P&L Data'!$C:$C,$I$4) -> 30028.574 | J12: =SUMIFS('P&L Data'!$P:$P,'P&L Data'!$B:$B,$D12,'P&L Data'!$C:$C,$I$4) -> 29761.367 | K12: =SUMIFS('P&L Data'!$T:$T,'P&L Data'!$B:$B,$D12,'P&L Data'!$C:$C,$I$4) -> 26778.883 | L12: =I12-J12 -> 267.20704 | M12: =I12-K12 -> 3249.6911 | N12: =IFERROR((I12-J12)/ABS(J12),0) -> 0.0089783187 | O12: =IFERROR((I12-K12)/ABS(K12),0) -> 0.12135275 | Q12: =SUMIFS('P&L Data'!$N:$N,'P&L Data'!$B:$B,$D12,'P&L Data'!$C:$C,$Q$4) -> 1738.5654 | R12: =SUMIFS('P&L Data'!$P:$P,'P&L Data'!$B:$B,$D12,'P&L Data'!$C:$C,$Q$4) -> 2048.3363 | S12: =SUMIFS('P&L Data'!$T:$T,'P&L Data'!$B:$B,$D12,'P&L Data'!$C:$C,$Q$4) -> 1408.0058 | T12: =Q12-R12 -> -309.77083 | U12: =Q12-S12 -> 330.55965 | V12: =IFERROR((Q12-R12)/ABS(R12),0) -> -0.15123046 | W12: =IFERROR((Q12-S12)/ABS(S12),0) -> 0.23477151 | Y12: =SUMIFS('P&L Data'!$N:$N,'P&L Data'!$B:$B,$D12,'P&L Data'!$C:$C,$Y$4) -> 7752.3435 | Z12: =SUMIFS('P&L Data'!$P:$P,'P&L Data'!$B:$B,$D12,'P&L Data'!$C:$C,$Y$4) -> 7845.5533 | AA12: =SUMIFS('P&L Data'!$T:$T,'P&L Data'!$B:$B,$D12,'P&L Data'!$C:$C,$Y$4) -> 6306.9863 | AB12: =Y12-Z12 -> -93.20983 | AC12: =Y12-AA12 -> 1445.3572 | AD12: =IFERROR((Y12-Z12)/ABS(Z12),0) -> -0.011880594 | AE12: =IFERROR((Y12-AA12)/ABS(AA12),0) -> 0.22916764 | AG12: =SUMIFS('P&L Data'!$N:$N,'P&L Data'!$B:$B,$D12,'P&L Data'!$C:$C,$AG$4) -> -142.56481 | AH12: =SUMIFS('P&L Data'!$P:$P,'P&L Data'!$B:$B,$D12,'P&L Data'!$C:$C,$AG$4) -> -179.24663 | AI12: =SUMIFS('P&L Data'!$T:$T,'P&L Data'!$B:$B,$D12,'P&L Data'!$C:$C,$AG$4) -> -216.39312 | AJ12: =AG12-AH12 -> 36.68182 | AK12: =AG12-AI12 -> 73.82831 | AL12: =IFERROR((AG12-AH12)/ABS(AH12),0) -> 0.20464441 | AM12: =IFERROR((AG12-AI12)/ABS(AI12),0) -> 0.34117679 | AO12: =SUMIFS('P&L Data'!$N:$N,'P&L Data'!$B:$B,$D12,'P&L Data'!$C:$C,$AO$4) -> -470.73721 | AP12: =SUMIFS('P&L Data'!$P:$P,'P&L Data'!$B:$B,$D12,'P&L Data'!$C:$C,$AO$4) -> -543.3718 | AQ12: =SUMIFS('P&L Data'!$T:$T,'P&L Data'!$B:$B,$D12,'P&L Data'!$C:$C,$AO$4) -> -403.45968 | AR12: =AO12-AP12 -> 72.63459 | AS12: =AO12-AQ12 -> -67.27753 | AT12: =IFERROR((AO12-AP12)/ABS(AP12),0) -> 0.13367383 | AU12: =IFERROR((AO12-AQ12)/ABS(AQ12),0) -> -0.16675156 | AW12: =SUMIFS('P&L Data'!$N:$N,'P&L Data'!$B:$B,$D12,'P&L Data'!$C:$C,$AW$4) -> 7139.0415 | AX12: =SUMIFS('P&L Data'!$P:$P,'P&L Data'!$B:$B,$D12,'P&L Data'!$C:$C,$AW$4) -> 7122.9349 | AY12: =SUMIFS('P&L Data'!$T:$T,'P&L Data'!$B:$B,$D12,'P&L Data'!$C:$C,$AW$4) -> 5687.1335 | AZ12: =AW12-AX12 -> 16.10658 | BA12: =AW12-AY12 -> 1451.908 | BB12: =IFERROR((AW12-AX12)/ABS(AX12),0) -> 0.002261228 | BC12: =IFERROR((AW12-AY12)/ABS(AY12),0) -> 0.25529697 | BE12: =SUMIFS('P&L Data'!$N:$N,'P&L Data'!$B:$B,$D12,'P&L Data'!$C:$C,$BE$4) -> -2316.1441 | BF12: =SUMIFS('P&L Data'!$P:$P,'P&L Data'!$B:$B,$D12,'P&L Data'!$C:$C,$BE$4) -> -2367.5976 | BG12: =SUMIFS('P&L Data'!$T:$T,'P&L Data'!$B:$B,$D12,'P&L Data'!$C:$C,$BE$4) -> -2336.4651 | BH12: =BE12-BF12 -> 51.45346 | BI12: =BE12-BG12 -> 20.32096 | BJ12: =IFERROR((BE12-BF12)/ABS(BF12),0) -> 0.02173235 | BK12: =IFERROR((BE12-BG12)/ABS(BG12),0) -> 0.0086973096 | BM12: =SUMIFS('P&L Data'!$N:$N,'P&L Data'!$B:$B,$D12,'P&L Data'!$C:$C,$BM$4) -> -384.97124 | BN12: =SUMIFS('P&L Data'!$P:$P,'P&L Data'!$B:$B,$D12,'P&L Data'!$C:$C,$BM$4) -> -504.2741 | BO12: =SUMIFS('P&L Data'!$T:$T,'P&L Data'!$B:$B,$D12,'P&L Data'!$C:$C,$BM$4) -> -549.56835 | BP12: =BM12-BN12 -> 119.30286 | BQ12: =BM12-BO12 -> 164.59711 | BR12: =IFERROR((BM12-BN12)/ABS(BN12),0) -> 0.23658336 | BS12: =IFERROR((BM12-BO12)/ABS(BO12),0) -> 0.29950253 | BU12: =SUMIFS('P&L Data'!$N:$N,'P&L Data'!$B:$B,$D12,'P&L Data'!$C:$C,$BU$4) -> -955.70293 | BV12: =SUMIFS('P&L Data'!$P:$P,'P&L Data'!$B:$B,$D12,'P&L Data'!$C:$C,$BU$4) -> -921.15968 | BW12: =SUMIFS('P&L Data'!$T:$T,'P&L Data'!$B:$B,$D12,'P&L Data'!$C:$C,$BU$4) -> -921.15968 | BX12: =BU12-BV12 -> -34.54325 | BY12: =BU12-BW12 -> -34.54325 | BZ12: =IFERROR((BU12-BV12)/ABS(BV12),0) -> -0.037499742 | CA12: =IFERROR((BU12-BW12)/ABS(BW12),0) -> -0.037499742 | CC12: =SUMIFS('P&L Data'!$N:$N,'P&L Data'!$B:$B,$D12,'P&L Data'!$C:$C,$CC$4) -> 3482.2232 | CD12: =SUMIFS('P&L Data'!$P:$P,'P&L Data'!$B:$B,$D12,'P&L Data'!$C:$C,$CC$4) -> 3329.9036 | CE12: =SUMIFS('P&L Data'!$T:$T,'P&L Data'!$B:$B,$D12,'P&L Data'!$C:$C,$CC$4) -> 1879.9404 | CF12: =CC12-CD12 -> 152.31965 | CG12: =CC12-CE12 -> 1602.2828 | CH12: =IFERROR((CC12-CD12)/ABS(CD12),0) -> 0.045742962 | CI12: =IFERROR((CC12-CE12)/ABS(CE12),0) -> 0.85230509 | CK12: =SUMIFS('P&L Data'!$N:$N,'P&L Data'!$B:$B,$D12,'P&L Data'!$C:$C,$CK$4) -> -1215.0372 | CL12: =SUMIFS('P&L Data'!$P:$P,'P&L Data'!$B:$B,$D12,'P&L Data'!$C:$C,$CK$4) -> -772.30307 | CM12: =SUMIFS('P&L Data'!$T:$T,'P&L Data'!$B:$B,$D12,'P&L Data'!$C:$C,$CK$4) -> -516.69898 | CN12: =CK12-CL12 -> -442.73417 | CO12: =CK12-CM12 -> -698.33826 | CP12: =IFERROR((CK12-CL12)/ABS(CL12),0) -> -0.57326481 | CQ12: =IFERROR((CK12-CM12)/ABS(CM12),0) -> -1.3515379 | CS12: =SUMIFS('P&L Data'!$N:$N,'P&L Data'!$B:$B,$D12,'P&L Data'!$C:$C,$CS$4) -> 2267.186 | CT12: =SUMIFS('P&L Data'!$P:$P,'P&L Data'!$B:$B,$D12,'P&L Data'!$C:$C,$CS$4) -> 2557.6005 | CU12: =SUMIFS('P&L Data'!$T:$T,'P&L Data'!$B:$B,$D12,'P&L Data'!$C:$C,$CS$4) -> 1363.2414 | CV12: =CS12-CT12 -> -290.41452 | CW12: =CS12-CU12 -> 903.94453 | CX12: =IFERROR((CS12-CT12)/ABS(CT12),0) -> -0.1135496 | CY12: =IFERROR((CS12-CU12)/ABS(CU12),0) -> 0.66308469
B13: Central | C13: Riyadh - South Total | I13: =SUBTOTAL(9,I11:I12) -> 41021.7 | J13: =SUBTOTAL(9,J11:J12) -> 41373.839 | K13: =SUBTOTAL(9,K11:K12) -> 38594.613 | L13: =I13-J13 -> -352.13917 | M13: =I13-K13 -> 2427.0866 | N13: =IFERROR((I13-J13)/ABS(J13),0) -> -0.0085111553 | O13: =IFERROR((I13-K13)/ABS(K13),0) -> 0.062886668 | Q13: =SUBTOTAL(9,Q11:Q12) -> 2134.4156 | R13: =SUBTOTAL(9,R11:R12) -> 2599.9743 | S13: =SUBTOTAL(9,S11:S12) -> 2069.046 | T13: =Q13-R13 -> -465.55871 | U13: =Q13-S13 -> 65.369625 | V13: =IFERROR((Q13-R13)/ABS(R13),0) -> -0.17906281 | W13: =IFERROR((Q13-S13)/ABS(S13),0) -> 0.031594091 | Y13: =SUBTOTAL(9,Y11:Y12) -> 10407.441 | Z13: =SUBTOTAL(9,Z11:Z12) -> 10619.324 | AA13: =SUBTOTAL(9,AA11:AA12) -> 9091.3003 | AB13: =Y13-Z13 -> -211.88325 | AC13: =Y13-AA13 -> 1316.1403 | AD13: =IFERROR((Y13-Z13)/ABS(Z13),0) -> -0.019952612 | AE13: =IFERROR((Y13-AA13)/ABS(AA13),0) -> 0.1447692 | AG13: =SUBTOTAL(9,AG11:AG12) -> -147.78694 | AH13: =SUBTOTAL(9,AH11:AH12) -> -250.17519 | AI13: =SUBTOTAL(9,AI11:AI12) -> -268.41669 | AJ13: =AG13-AH13 -> 102.38825 | AK13: =AG13-AI13 -> 120.62975 | AL13: =IFERROR((AG13-AH13)/ABS(AH13),0) -> 0.4092662 | AM13: =IFERROR((AG13-AI13)/ABS(AI13),0) -> 0.44941226 | AO13: =SUBTOTAL(9,AO11:AO12) -> -666.26555 | AP13: =SUBTOTAL(9,AP11:AP12) -> -755.79246 | AQ13: =SUBTOTAL(9,AQ11:AQ12) -> -593.73454 | AR13: =AO13-AP13 -> 89.52691 | AS13: =AO13-AQ13 -> -72.53101 | AT13: =IFERROR((AO13-AP13)/ABS(AP13),0) -> 0.11845436 | AU13: =IFERROR((AO13-AQ13)/ABS(AQ13),0) -> -0.12216067 | AW13: =SUBTOTAL(9,AW11:AW12) -> 9593.3881 | AX13: =SUBTOTAL(9,AX11:AX12) -> 9613.3562 | AY13: =SUBTOTAL(9,AY11:AY12) -> 8229.1491 | AZ13: =AW13-AX13 -> -19.96809 | BA13: =AW13-AY13 -> 1364.239 | BB13: =IFERROR((AW13-AX13)/ABS(AX13),0) -> -0.0020771195 | BC13: =IFERROR((AW13-AY13)/ABS(AY13),0) -> 0.16578129 | BE13: =SUBTOTAL(9,BE11:BE12) -> -3219.3773 | BF13: =SUBTOTAL(9,BF11:BF12) -> -3164.3538 | BG13: =SUBTOTAL(9,BG11:BG12) -> -3135.3055 | BH13: =BE13-BF13 -> -55.02354 | BI13: =BE13-BG13 -> -84.07188 | BJ13: =IFERROR((BE13-BF13)/ABS(BF13),0) -> -0.017388555 | BK13: =IFERROR((BE13-BG13)/ABS(BG13),0) -> -0.026814574 | BM13: =SUBTOTAL(9,BM11:BM12) -> -623.56517 | BN13: =SUBTOTAL(9,BN11:BN12) -> -764.54848 | BO13: =SUBTOTAL(9,BO11:BO12) -> -790.21732 | BP13: =BM13-BN13 -> 140.98331 | BQ13: =BM13-BO13 -> 166.65215 | BR13: =IFERROR((BM13-BN13)/ABS(BN13),0) -> 0.18440075 | BS13: =IFERROR((BM13-BO13)/ABS(BO13),0) -> 0.21089407 | BU13: =SUBTOTAL(9,BU11:BU12) -> -1783.1365 | BV13: =SUBTOTAL(9,BV11:BV12) -> -1748.5933 | BW13: =SUBTOTAL(9,BW11:BW12) -> -1748.5933 | BX13: =BU13-BV13 -> -34.54325 | BY13: =BU13-BW13 -> -34.54325 | BZ13: =IFERROR((BU13-BV13)/ABS(BV13),0) -> -0.01975488 | CA13: =IFERROR((BU13-BW13)/ABS(BW13),0) -> -0.01975488 | CC13: =SUBTOTAL(9,CC11:CC12) -> 3967.3091 | CD13: =SUBTOTAL(9,CD11:CD12) -> 3935.8606 | CE13: =SUBTOTAL(9,CE11:CE12) -> 2555.033 | CF13: =CC13-CD13 -> 31.44843 | CG13: =CC13-CE13 -> 1412.276 | CH13: =IFERROR((CC13-CD13)/ABS(CD13),0) -> 0.0079902296 | CI13: =IFERROR((CC13-CE13)/ABS(CE13),0) -> 0.55274276 | CK13: =SUBTOTAL(9,CK11:CK12) -> -1303.8431 | CL13: =SUBTOTAL(9,CL11:CL12) -> -1064.9465 | CM13: =SUBTOTAL(9,CM11:CM12) -> -580.30291 | CN13: =CK13-CL13 -> -238.89659 | CO13: =CK13-CM13 -> -723.54017 | CP13: =IFERROR((CK13-CL13)/ABS(CL13),0) -> -0.22432732 | CQ13: =IFERROR((CK13-CM13)/ABS(CM13),0) -> -1.2468319 | CS13: =SUBTOTAL(9,CS11:CS12) -> 2663.466 | CT13: =SUBTOTAL(9,CT11:CT12) -> 2870.9141 | CU13: =SUBTOTAL(9,CU11:CU12) -> 1974.7301 | CV13: =SUBTOTAL(9,CV11:CV12) -> -207.44816 | CW13: =SUBTOTAL(9,CW11:CW12) -> 688.73584 | CX13: =IFERROR((CS13-CT13)/ABS(CT13),0) -> -0.072258574 | CY13: =IFERROR((CS13-CU13)/ABS(CU13),0) -> 0.34877467
B14: Central | C14: Qassim | D14: 301 | E14: Onaizah | F14: Hyper | G14: LFL | I14: =SUMIFS('P&L Data'!$N:$N,'P&L Data'!$B:$B,$D14,'P&L Data'!$C:$C,$I$4) -> 20166.618 | J14: =SUMIFS('P&L Data'!$P:$P,'P&L Data'!$B:$B,$D14,'P&L Data'!$C:$C,$I$4) -> 20608.775 | K14: =SUMIFS('P&L Data'!$T:$T,'P&L Data'!$B:$B,$D14,'P&L Data'!$C:$C,$I$4) -> 20798.271 | L14: =I14-J14 -> -442.15676 | M14: =I14-K14 -> -631.65294 | N14: =IFERROR((I14-J14)/ABS(J14),0) -> -0.021454781 | O14: =IFERROR((I14-K14)/ABS(K14),0) -> -0.030370454 | Q14: =SUMIFS('P&L Data'!$N:$N,'P&L Data'!$B:$B,$D14,'P&L Data'!$C:$C,$Q$4) -> 142.45983 | R14: =SUMIFS('P&L Data'!$P:$P,'P&L Data'!$B:$B,$D14,'P&L Data'!$C:$C,$Q$4) -> 788.26615 | S14: =SUMIFS('P&L Data'!$T:$T,'P&L Data'!$B:$B,$D14,'P&L Data'!$C:$C,$Q$4) -> 1019.4979 | T14: =Q14-R14 -> -645.80632 | U14: =Q14-S14 -> -877.03808 | V14: =IFERROR((Q14-R14)/ABS(R14),0) -> -0.81927445 | W14: =IFERROR((Q14-S14)/ABS(S14),0) -> -0.86026472 | Y14: =SUMIFS('P&L Data'!$N:$N,'P&L Data'!$B:$B,$D14,'P&L Data'!$C:$C,$Y$4) -> 4155.4767 | Z14: =SUMIFS('P&L Data'!$P:$P,'P&L Data'!$B:$B,$D14,'P&L Data'!$C:$C,$Y$4) -> 4738.9749 | AA14: =SUMIFS('P&L Data'!$T:$T,'P&L Data'!$B:$B,$D14,'P&L Data'!$C:$C,$Y$4) -> 4786.886 | AB14: =Y14-Z14 -> -583.49819 | AC14: =Y14-AA14 -> -631.40932 | AD14: =IFERROR((Y14-Z14)/ABS(Z14),0) -> -0.12312751 | AE14: =IFERROR((Y14-AA14)/ABS(AA14),0) -> -0.13190398 | AG14: =SUMIFS('P&L Data'!$N:$N,'P&L Data'!$B:$B,$D14,'P&L Data'!$C:$C,$AG$4) -> -64.47421 | AH14: =SUMIFS('P&L Data'!$P:$P,'P&L Data'!$B:$B,$D14,'P&L Data'!$C:$C,$AG$4) -> -127.8963 | AI14: =SUMIFS('P&L Data'!$T:$T,'P&L Data'!$B:$B,$D14,'P&L Data'!$C:$C,$AG$4) -> -83.77442 | AJ14: =AG14-AH14 -> 63.42209 | AK14: =AG14-AI14 -> 19.30021 | AL14: =IFERROR((AG14-AH14)/ABS(AH14),0) -> 0.49588682 | AM14: =IFERROR((AG14-AI14)/ABS(AI14),0) -> 0.23038309 | AO14: =SUMIFS('P&L Data'!$N:$N,'P&L Data'!$B:$B,$D14,'P&L Data'!$C:$C,$AO$4) -> -345.70857 | AP14: =SUMIFS('P&L Data'!$P:$P,'P&L Data'!$B:$B,$D14,'P&L Data'!$C:$C,$AO$4) -> -383.32547 | AQ14: =SUMIFS('P&L Data'!$T:$T,'P&L Data'!$B:$B,$D14,'P&L Data'!$C:$C,$AO$4) -> -347.02352 | AR14: =AO14-AP14 -> 37.6169 | AS14: =AO14-AQ14 -> 1.31495 | AT14: =IFERROR((AO14-AP14)/ABS(AP14),0) -> 0.098133056 | AU14: =IFERROR((AO14-AQ14)/ABS(AQ14),0) -> 0.0037892244 | AW14: =SUMIFS('P&L Data'!$N:$N,'P&L Data'!$B:$B,$D14,'P&L Data'!$C:$C,$AW$4) -> 3745.2939 | AX14: =SUMIFS('P&L Data'!$P:$P,'P&L Data'!$B:$B,$D14,'P&L Data'!$C:$C,$AW$4) -> 4227.7532 | AY14: =SUMIFS('P&L Data'!$T:$T,'P&L Data'!$B:$B,$D14,'P&L Data'!$C:$C,$AW$4) -> 4356.0881 | AZ14: =AW14-AX14 -> -482.4592 | BA14: =AW14-AY14 -> -610.79416 | BB14: =IFERROR((AW14-AX14)/ABS(AX14),0) -> -0.11411716 | BC14: =IFERROR((AW14-AY14)/ABS(AY14),0) -> -0.14021621 | BE14: =SUMIFS('P&L Data'!$N:$N,'P&L Data'!$B:$B,$D14,'P&L Data'!$C:$C,$BE$4) -> -1635.6885 | BF14: =SUMIFS('P&L Data'!$P:$P,'P&L Data'!$B:$B,$D14,'P&L Data'!$C:$C,$BE$4) -> -1420.4467 | BG14: =SUMIFS('P&L Data'!$T:$T,'P&L Data'!$B:$B,$D14,'P&L Data'!$C:$C,$BE$4) -> -1572.5023 | BH14: =BE14-BF14 -> -215.24186 | BI14: =BE14-BG14 -> -63.18625 | BJ14: =IFERROR((BE14-BF14)/ABS(BF14),0) -> -0.15153111 | BK14: =IFERROR((BE14-BG14)/ABS(BG14),0) -> -0.040181977 | BM14: =SUMIFS('P&L Data'!$N:$N,'P&L Data'!$B:$B,$D14,'P&L Data'!$C:$C,$BM$4) -> -388.83962 | BN14: =SUMIFS('P&L Data'!$P:$P,'P&L Data'!$B:$B,$D14,'P&L Data'!$C:$C,$BM$4) -> -475.52009 | BO14: =SUMIFS('P&L Data'!$T:$T,'P&L Data'!$B:$B,$D14,'P&L Data'!$C:$C,$BM$4) -> -473.40409 | BP14: =BM14-BN14 -> 86.68047 | BQ14: =BM14-BO14 -> 84.56447 | BR14: =IFERROR((BM14-BN14)/ABS(BN14),0) -> 0.18228561 | BS14: =IFERROR((BM14-BO14)/ABS(BO14),0) -> 0.17863063 | BU14: =SUMIFS('P&L Data'!$N:$N,'P&L Data'!$B:$B,$D14,'P&L Data'!$C:$C,$BU$4) -> -900 | BV14: =SUMIFS('P&L Data'!$P:$P,'P&L Data'!$B:$B,$D14,'P&L Data'!$C:$C,$BU$4) -> -900 | BW14: =SUMIFS('P&L Data'!$T:$T,'P&L Data'!$B:$B,$D14,'P&L Data'!$C:$C,$BU$4) -> -900 | BX14: =BU14-BV14 -> 0 | BY14: =BU14-BW14 -> 0 | BZ14: =IFERROR((BU14-BV14)/ABS(BV14),0) -> 0 | CA14: =IFERROR((BU14-BW14)/ABS(BW14),0) -> 0 | CC14: =SUMIFS('P&L Data'!$N:$N,'P&L Data'!$B:$B,$D14,'P&L Data'!$C:$C,$CC$4) -> 820.76581 | CD14: =SUMIFS('P&L Data'!$P:$P,'P&L Data'!$B:$B,$D14,'P&L Data'!$C:$C,$CC$4) -> 1431.7864 | CE14: =SUMIFS('P&L Data'!$T:$T,'P&L Data'!$B:$B,$D14,'P&L Data'!$C:$C,$CC$4) -> 1410.1817 | CF14: =CC14-CD14 -> -611.02059 | CG14: =CC14-CE14 -> -589.41594 | CH14: =IFERROR((CC14-CD14)/ABS(CD14),0) -> -0.42675401 | CI14: =IFERROR((CC14-CE14)/ABS(CE14),0) -> -0.41797161 | CK14: =SUMIFS('P&L Data'!$N:$N,'P&L Data'!$B:$B,$D14,'P&L Data'!$C:$C,$CK$4) -> -680.79158 | CL14: =SUMIFS('P&L Data'!$P:$P,'P&L Data'!$B:$B,$D14,'P&L Data'!$C:$C,$CK$4) -> -587.51643 | CM14: =SUMIFS('P&L Data'!$T:$T,'P&L Data'!$B:$B,$D14,'P&L Data'!$C:$C,$CK$4) -> -282.33336 | CN14: =CK14-CL14 -> -93.27515 | CO14: =CK14-CM14 -> -398.45822 | CP14: =IFERROR((CK14-CL14)/ABS(CL14),0) -> -0.15876177 | CQ14: =IFERROR((CK14-CM14)/ABS(CM14),0) -> -1.4113041 | CS14: =SUMIFS('P&L Data'!$N:$N,'P&L Data'!$B:$B,$D14,'P&L Data'!$C:$C,$CS$4) -> 139.97423 | CT14: =SUMIFS('P&L Data'!$P:$P,'P&L Data'!$B:$B,$D14,'P&L Data'!$C:$C,$CS$4) -> 844.26997 | CU14: =SUMIFS('P&L Data'!$T:$T,'P&L Data'!$B:$B,$D14,'P&L Data'!$C:$C,$CS$4) -> 1127.8484 | CV14: =CS14-CT14 -> -704.29574 | CW14: =CS14-CU14 -> -987.87416 | CX14: =IFERROR((CS14-CT14)/ABS(CT14),0) -> -0.83420679 | CY14: =IFERROR((CS14-CU14)/ABS(CU14),0) -> -0.87589269
B15: Central | C15: Qassim | D15: 30001 | E15: Shahinat | F15: Hyper | G15: LFL | I15: =SUMIFS('P&L Data'!$N:$N,'P&L Data'!$B:$B,$D15,'P&L Data'!$C:$C,$I$4) -> 24579.436 | J15: =SUMIFS('P&L Data'!$P:$P,'P&L Data'!$B:$B,$D15,'P&L Data'!$C:$C,$I$4) -> 21051.442 | K15: =SUMIFS('P&L Data'!$T:$T,'P&L Data'!$B:$B,$D15,'P&L Data'!$C:$C,$I$4) -> 21915.011 | L15: =I15-J15 -> 3527.9944 | M15: =I15-K15 -> 2664.4253 | N15: =IFERROR((I15-J15)/ABS(J15),0) -> 0.16758921 | O15: =IFERROR((I15-K15)/ABS(K15),0) -> 0.12157992 | Q15: =SUMIFS('P&L Data'!$N:$N,'P&L Data'!$B:$B,$D15,'P&L Data'!$C:$C,$Q$4) -> -682.91545 | R15: =SUMIFS('P&L Data'!$P:$P,'P&L Data'!$B:$B,$D15,'P&L Data'!$C:$C,$Q$4) -> 424.78107 | S15: =SUMIFS('P&L Data'!$T:$T,'P&L Data'!$B:$B,$D15,'P&L Data'!$C:$C,$Q$4) -> 172.64294 | T15: =Q15-R15 -> -1107.6965 | U15: =Q15-S15 -> -855.55839 | V15: =IFERROR((Q15-R15)/ABS(R15),0) -> -2.607688 | W15: =IFERROR((Q15-S15)/ABS(S15),0) -> -4.9556522 | Y15: =SUMIFS('P&L Data'!$N:$N,'P&L Data'!$B:$B,$D15,'P&L Data'!$C:$C,$Y$4) -> 4328.5222 | Z15: =SUMIFS('P&L Data'!$P:$P,'P&L Data'!$B:$B,$D15,'P&L Data'!$C:$C,$Y$4) -> 4502.6572 | AA15: =SUMIFS('P&L Data'!$T:$T,'P&L Data'!$B:$B,$D15,'P&L Data'!$C:$C,$Y$4) -> 4134.3655 | AB15: =Y15-Z15 -> -174.13499 | AC15: =Y15-AA15 -> 194.15671 | AD15: =IFERROR((Y15-Z15)/ABS(Z15),0) -> -0.038673828 | AE15: =IFERROR((Y15-AA15)/ABS(AA15),0) -> 0.046961669 | AG15: =SUMIFS('P&L Data'!$N:$N,'P&L Data'!$B:$B,$D15,'P&L Data'!$C:$C,$AG$4) -> -114.11238 | AH15: =SUMIFS('P&L Data'!$P:$P,'P&L Data'!$B:$B,$D15,'P&L Data'!$C:$C,$AG$4) -> -133.42294 | AI15: =SUMIFS('P&L Data'!$T:$T,'P&L Data'!$B:$B,$D15,'P&L Data'!$C:$C,$AG$4) -> -144.53654 | AJ15: =AG15-AH15 -> 19.31056 | AK15: =AG15-AI15 -> 30.42416 | AL15: =IFERROR((AG15-AH15)/ABS(AH15),0) -> 0.14473193 | AM15: =IFERROR((AG15-AI15)/ABS(AI15),0) -> 0.21049459 | AO15: =SUMIFS('P&L Data'!$N:$N,'P&L Data'!$B:$B,$D15,'P&L Data'!$C:$C,$AO$4) -> -368.66323 | AP15: =SUMIFS('P&L Data'!$P:$P,'P&L Data'!$B:$B,$D15,'P&L Data'!$C:$C,$AO$4) -> -380.34316 | AQ15: =SUMIFS('P&L Data'!$T:$T,'P&L Data'!$B:$B,$D15,'P&L Data'!$C:$C,$AO$4) -> -334.17028 | AR15: =AO15-AP15 -> 11.67993 | AS15: =AO15-AQ15 -> -34.49295 | AT15: =IFERROR((AO15-AP15)/ABS(AP15),0) -> 0.030708926 | AU15: =IFERROR((AO15-AQ15)/ABS(AQ15),0) -> -0.10321968 | AW15: =SUMIFS('P&L Data'!$N:$N,'P&L Data'!$B:$B,$D15,'P&L Data'!$C:$C,$AW$4) -> 3845.7466 | AX15: =SUMIFS('P&L Data'!$P:$P,'P&L Data'!$B:$B,$D15,'P&L Data'!$C:$C,$AW$4) -> 3988.8911 | AY15: =SUMIFS('P&L Data'!$T:$T,'P&L Data'!$B:$B,$D15,'P&L Data'!$C:$C,$AW$4) -> 3655.6587 | AZ15: =AW15-AX15 -> -143.1445 | BA15: =AW15-AY15 -> 190.08792 | BB15: =IFERROR((AW15-AX15)/ABS(AX15),0) -> -0.035885788 | BC15: =IFERROR((AW15-AY15)/ABS(AY15),0) -> 0.051998266 | BE15: =SUMIFS('P&L Data'!$N:$N,'P&L Data'!$B:$B,$D15,'P&L Data'!$C:$C,$BE$4) -> -1663.3596 | BF15: =SUMIFS('P&L Data'!$P:$P,'P&L Data'!$B:$B,$D15,'P&L Data'!$C:$C,$BE$4) -> -1512.2225 | BG15: =SUMIFS('P&L Data'!$T:$T,'P&L Data'!$B:$B,$D15,'P&L Data'!$C:$C,$BE$4) -> -1601.4968 | BH15: =BE15-BF15 -> -151.13714 | BI15: =BE15-BG15 -> -61.86286 | BJ15: =IFERROR((BE15-BF15)/ABS(BF15),0) -> -0.09994372 | BK15: =IFERROR((BE15-BG15)/ABS(BG15),0) -> -0.038628152 | BM15: =SUMIFS('P&L Data'!$N:$N,'P&L Data'!$B:$B,$D15,'P&L Data'!$C:$C,$BM$4) -> -811.59696 | BN15: =SUMIFS('P&L Data'!$P:$P,'P&L Data'!$B:$B,$D15,'P&L Data'!$C:$C,$BM$4) -> -779.42964 | BO15: =SUMIFS('P&L Data'!$T:$T,'P&L Data'!$B:$B,$D15,'P&L Data'!$C:$C,$BM$4) -> -809.01016 | BP15: =BM15-BN15 -> -32.16732 | BQ15: =BM15-BO15 -> -2.5868 | BR15: =IFERROR((BM15-BN15)/ABS(BN15),0) -> -0.041270332 | BS15: =IFERROR((BM15-BO15)/ABS(BO15),0) -> -0.0031974877 | BU15: =SUMIFS('P&L Data'!$N:$N,'P&L Data'!$B:$B,$D15,'P&L Data'!$C:$C,$BU$4) -> -1334.5253 | BV15: =SUMIFS('P&L Data'!$P:$P,'P&L Data'!$B:$B,$D15,'P&L Data'!$C:$C,$BU$4) -> -1142.817 | BW15: =SUMIFS('P&L Data'!$T:$T,'P&L Data'!$B:$B,$D15,'P&L Data'!$C:$C,$BU$4) -> -1137.585 | BX15: =BU15-BV15 -> -191.70833 | BY15: =BU15-BW15 -> -196.94039 | BZ15: =IFERROR((BU15-BV15)/ABS(BV15),0) -> -0.16775068 | CA15: =IFERROR((BU15-BW15)/ABS(BW15),0) -> -0.17312148 | CC15: =SUMIFS('P&L Data'!$N:$N,'P&L Data'!$B:$B,$D15,'P&L Data'!$C:$C,$CC$4) -> 36.2647 | CD15: =SUMIFS('P&L Data'!$P:$P,'P&L Data'!$B:$B,$D15,'P&L Data'!$C:$C,$CC$4) -> 554.42199 | CE15: =SUMIFS('P&L Data'!$T:$T,'P&L Data'!$B:$B,$D15,'P&L Data'!$C:$C,$CC$4) -> 107.56683 | CF15: =CC15-CD15 -> -518.15729 | CG15: =CC15-CE15 -> -71.302135 | CH15: =IFERROR((CC15-CD15)/ABS(CD15),0) -> -0.93459008 | CI15: =IFERROR((CC15-CE15)/ABS(CE15),0) -> -0.66286356 | CK15: =SUMIFS('P&L Data'!$N:$N,'P&L Data'!$B:$B,$D15,'P&L Data'!$C:$C,$CK$4) -> -11.08543 | CL15: =SUMIFS('P&L Data'!$P:$P,'P&L Data'!$B:$B,$D15,'P&L Data'!$C:$C,$CK$4) -> -152.68445 | CM15: =SUMIFS('P&L Data'!$T:$T,'P&L Data'!$B:$B,$D15,'P&L Data'!$C:$C,$CK$4) -> -101.86592 | CN15: =CK15-CL15 -> 141.59902 | CO15: =CK15-CM15 -> 90.78049 | CP15: =IFERROR((CK15-CL15)/ABS(CL15),0) -> 0.92739647 | CQ15: =IFERROR((CK15-CM15)/ABS(CM15),0) -> 0.89117626 | CS15: =SUMIFS('P&L Data'!$N:$N,'P&L Data'!$B:$B,$D15,'P&L Data'!$C:$C,$CS$4) -> 25.17927 | CT15: =SUMIFS('P&L Data'!$P:$P,'P&L Data'!$B:$B,$D15,'P&L Data'!$C:$C,$CS$4) -> 401.73754 | CU15: =SUMIFS('P&L Data'!$T:$T,'P&L Data'!$B:$B,$D15,'P&L Data'!$C:$C,$CS$4) -> 5.7009149 | CV15: =CS15-CT15 -> -376.55827 | CW15: =CS15-CU15 -> 19.478355 | CX15: =IFERROR((CS15-CT15)/ABS(CT15),0) -> -0.93732408 | CY15: =IFERROR((CS15-CU15)/ABS(CU15),0) -> 3.4167069
B16: Central | C16: Qassim Total | I16: =SUBTOTAL(9,I14:I15) -> 44746.055 | J16: =SUBTOTAL(9,J14:J15) -> 41660.217 | K16: =SUBTOTAL(9,K14:K15) -> 42713.282 | L16: =I16-J16 -> 3085.8377 | M16: =I16-K16 -> 2032.7723 | N16: =IFERROR((I16-J16)/ABS(J16),0) -> 0.07407157 | O16: =IFERROR((I16-K16)/ABS(K16),0) -> 0.047591106 | Q16: =SUBTOTAL(9,Q14:Q15) -> -540.45562 | R16: =SUBTOTAL(9,R14:R15) -> 1213.0472 | S16: =SUBTOTAL(9,S14:S15) -> 1192.1409 | T16: =Q16-R16 -> -1753.5028 | U16: =Q16-S16 -> -1732.5965 | V16: =IFERROR((Q16-R16)/ABS(R16),0) -> -1.4455355 | W16: =IFERROR((Q16-S16)/ABS(S16),0) -> -1.4533488 | Y16: =SUBTOTAL(9,Y14:Y15) -> 8483.999 | Z16: =SUBTOTAL(9,Z14:Z15) -> 9241.6322 | AA16: =SUBTOTAL(9,AA14:AA15) -> 8921.2516 | AB16: =Y16-Z16 -> -757.63318 | AC16: =Y16-AA16 -> -437.25261 | AD16: =IFERROR((Y16-Z16)/ABS(Z16),0) -> -0.081980452 | AE16: =IFERROR((Y16-AA16)/ABS(AA16),0) -> -0.049012474 | AG16: =SUBTOTAL(9,AG14:AG15) -> -178.58659 | AH16: =SUBTOTAL(9,AH14:AH15) -> -261.31924 | AI16: =SUBTOTAL(9,AI14:AI15) -> -228.31096 | AJ16: =AG16-AH16 -> 82.73265 | AK16: =AG16-AI16 -> 49.72437 | AL16: =IFERROR((AG16-AH16)/ABS(AH16),0) -> 0.31659609 | AM16: =IFERROR((AG16-AI16)/ABS(AI16),0) -> 0.2177923 | AO16: =SUBTOTAL(9,AO14:AO15) -> -714.3718 | AP16: =SUBTOTAL(9,AP14:AP15) -> -763.66863 | AQ16: =SUBTOTAL(9,AQ14:AQ15) -> -681.1938 | AR16: =AO16-AP16 -> 49.29683 | AS16: =AO16-AQ16 -> -33.178 | AT16: =IFERROR((AO16-AP16)/ABS(AP16),0) -> 0.064552645 | AU16: =IFERROR((AO16-AQ16)/ABS(AQ16),0) -> -0.048705669 | AW16: =SUBTOTAL(9,AW14:AW15) -> 7591.0406 | AX16: =SUBTOTAL(9,AX14:AX15) -> 8216.6443 | AY16: =SUBTOTAL(9,AY14:AY15) -> 8011.7468 | AZ16: =AW16-AX16 -> -625.6037 | BA16: =AW16-AY16 -> -420.70624 | BB16: =IFERROR((AW16-AX16)/ABS(AX16),0) -> -0.076138589 | BC16: =IFERROR((AW16-AY16)/ABS(AY16),0) -> -0.052511175 | BE16: =SUBTOTAL(9,BE14:BE15) -> -3299.0481 | BF16: =SUBTOTAL(9,BF14:BF15) -> -2932.6691 | BG16: =SUBTOTAL(9,BG14:BG15) -> -3173.999 | BH16: =BE16-BF16 -> -366.379 | BI16: =BE16-BG16 -> -125.04911 | BJ16: =IFERROR((BE16-BF16)/ABS(BF16),0) -> -0.12493022 | BK16: =IFERROR((BE16-BG16)/ABS(BG16),0) -> -0.039397967 | BM16: =SUBTOTAL(9,BM14:BM15) -> -1200.4366 | BN16: =SUBTOTAL(9,BN14:BN15) -> -1254.9497 | BO16: =SUBTOTAL(9,BO14:BO15) -> -1282.4142 | BP16: =BM16-BN16 -> 54.51315 | BQ16: =BM16-BO16 -> 81.97767 | BR16: =IFERROR((BM16-BN16)/ABS(BN16),0) -> 0.043438513 | BS16: =IFERROR((BM16-BO16)/ABS(BO16),0) -> 0.063924485 | BU16: =SUBTOTAL(9,BU14:BU15) -> -2234.5253 | BV16: =SUBTOTAL(9,BV14:BV15) -> -2042.817 | BW16: =SUBTOTAL(9,BW14:BW15) -> -2037.585 | BX16: =BU16-BV16 -> -191.70833 | BY16: =BU16-BW16 -> -196.94039 | BZ16: =IFERROR((BU16-BV16)/ABS(BV16),0) -> -0.093845082 | CA16: =IFERROR((BU16-BW16)/ABS(BW16),0) -> -0.09665383 | CC16: =SUBTOTAL(9,CC14:CC15) -> 857.03051 | CD16: =SUBTOTAL(9,CD14:CD15) -> 1986.2084 | CE16: =SUBTOTAL(9,CE14:CE15) -> 1517.7486 | CF16: =CC16-CD16 -> -1129.1779 | CG16: =CC16-CE16 -> -660.71807 | CH16: =IFERROR((CC16-CD16)/ABS(CD16),0) -> -0.56850927 | CI16: =IFERROR((CC16-CE16)/ABS(CE16),0) -> -0.43532775 | CK16: =SUBTOTAL(9,CK14:CK15) -> -691.87701 | CL16: =SUBTOTAL(9,CL14:CL15) -> -740.20088 | CM16: =SUBTOTAL(9,CM14:CM15) -> -384.19928 | CN16: =CK16-CL16 -> 48.32387 | CO16: =CK16-CM16 -> -307.67773 | CP16: =IFERROR((CK16-CL16)/ABS(CL16),0) -> 0.065284805 | CQ16: =IFERROR((CK16-CM16)/ABS(CM16),0) -> -0.80082849 | CS16: =SUBTOTAL(9,CS14:CS15) -> 165.1535 | CT16: =SUBTOTAL(9,CT14:CT15) -> 1246.0075 | CU16: =SUBTOTAL(9,CU14:CU15) -> 1133.5493 | CV16: =SUBTOTAL(9,CV14:CV15) -> -1080.854 | CW16: =SUBTOTAL(9,CW14:CW15) -> -968.3958 | CX16: =IFERROR((CS16-CT16)/ABS(CT16),0) -> -0.86745385 | CY16: =IFERROR((CS16-CU16)/ABS(CU16),0) -> -0.85430409
B17: Central Total | I17: =SUBTOTAL(9,I6:I16) -> 170116.49 | J17: =SUBTOTAL(9,J6:J16) -> 164055.49 | K17: =SUBTOTAL(9,K6:K16) -> 161484.91 | L17: =I17-J17 -> 6061.0004 | M17: =I17-K17 -> 8631.5816 | N17: =IFERROR((I17-J17)/ABS(J17),0) -> 0.036944819 | O17: =IFERROR((I17-K17)/ABS(K17),0) -> 0.05345132 | Q17: =SUBTOTAL(9,Q6:Q16) -> 7240.0801 | R17: =SUBTOTAL(9,R6:R16) -> 9427.9145 | S17: =SUBTOTAL(9,S6:S16) -> 8978.8421 | T17: =Q17-R17 -> -2187.8344 | U17: =Q17-S17 -> -1738.762 | V17: =IFERROR((Q17-R17)/ABS(R17),0) -> -0.23205921 | W17: =IFERROR((Q17-S17)/ABS(S17),0) -> -0.19365103 | Y17: =SUBTOTAL(9,Y6:Y16) -> 41294.318 | Z17: =SUBTOTAL(9,Z6:Z16) -> 41079.44 | AA17: =SUBTOTAL(9,AA6:AA16) -> 38311.266 | AB17: =Y17-Z17 -> 214.87883 | AC17: =Y17-AA17 -> 2983.0522 | AD17: =IFERROR((Y17-Z17)/ABS(Z17),0) -> 0.0052308121 | AE17: =IFERROR((Y17-AA17)/ABS(AA17),0) -> 0.077863575 | AG17: =SUBTOTAL(9,AG6:AG16) -> -651.57557 | AH17: =SUBTOTAL(9,AH6:AH16) -> -1003.0432 | AI17: =SUBTOTAL(9,AI6:AI16) -> -935.56187 | AJ17: =AG17-AH17 -> 351.46766 | AK17: =AG17-AI17 -> 283.9863 | AL17: =IFERROR((AG17-AH17)/ABS(AH17),0) -> 0.35040131 | AM17: =IFERROR((AG17-AI17)/ABS(AI17),0) -> 0.30354625 | AO17: =SUBTOTAL(9,AO6:AO16) -> -2803.2503 | AP17: =SUBTOTAL(9,AP6:AP16) -> -3034.7315 | AQ17: =SUBTOTAL(9,AQ6:AQ16) -> -2536.253 | AR17: =AO17-AP17 -> 231.48118 | AS17: =AO17-AQ17 -> -266.99726 | AT17: =IFERROR((AO17-AP17)/ABS(AP17),0) -> 0.076277319 | AU17: =IFERROR((AO17-AQ17)/ABS(AQ17),0) -> -0.10527233 | AW17: =SUBTOTAL(9,AW6:AW16) -> 37839.492 | AX17: =SUBTOTAL(9,AX6:AX16) -> 37041.665 | AY17: =SUBTOTAL(9,AY6:AY16) -> 34839.451 | AZ17: =AW17-AX17 -> 797.82767 | BA17: =AW17-AY17 -> 3000.0412 | BB17: =IFERROR((AW17-AX17)/ABS(AX17),0) -> 0.021538656 | BC17: =IFERROR((AW17-AY17)/ABS(AY17),0) -> 0.086110461 | BE17: =SUBTOTAL(9,BE6:BE16) -> -12574.453 | BF17: =SUBTOTAL(9,BF6:BF16) -> -12098.019 | BG17: =SUBTOTAL(9,BG6:BG16) -> -12277.018 | BH17: =BE17-BF17 -> -476.43417 | BI17: =BE17-BG17 -> -297.43511 | BJ17: =IFERROR((BE17-BF17)/ABS(BF17),0) -> -0.039381172 | BK17: =IFERROR((BE17-BG17)/ABS(BG17),0) -> -0.024226983 | BM17: =SUBTOTAL(9,BM6:BM16) -> -4671.4194 | BN17: =SUBTOTAL(9,BN6:BN16) -> -4893.5996 | BO17: =SUBTOTAL(9,BO6:BO16) -> -5074.1049 | BP17: =BM17-BN17 -> 222.18019 | BQ17: =BM17-BO17 -> 402.68558 | BR17: =IFERROR((BM17-BN17)/ABS(BN17),0) -> 0.045402201 | BS17: =IFERROR((BM17-BO17)/ABS(BO17),0) -> 0.079360909 | BU17: =SUBTOTAL(9,BU6:BU16) -> -8490.5138 | BV17: =SUBTOTAL(9,BV6:BV16) -> -7871.2008 | BW17: =SUBTOTAL(9,BW6:BW16) -> -8256.8976 | BX17: =BU17-BV17 -> -619.31302 | BY17: =BU17-BW17 -> -233.61622 | BZ17: =IFERROR((BU17-BV17)/ABS(BV17),0) -> -0.078680882 | CA17: =IFERROR((BU17-BW17)/ABS(BW17),0) -> -0.028293462 | CC17: =SUBTOTAL(9,CC6:CC16) -> 12103.106 | CD17: =SUBTOTAL(9,CD6:CD16) -> 12178.845 | CE17: =SUBTOTAL(9,CE6:CE16) -> 9231.4307 | CF17: =CC17-CD17 -> -75.73933 | CG17: =CC17-CE17 -> 2871.6755 | CH17: =IFERROR((CC17-CD17)/ABS(CD17),0) -> -0.0062189253 | CI17: =IFERROR((CC17-CE17)/ABS(CE17),0) -> 0.31107588 | CK17: =SUBTOTAL(9,CK6:CK16) -> -4534.6968 | CL17: =SUBTOTAL(9,CL6:CL16) -> -3938.4147 | CM17: =SUBTOTAL(9,CM6:CM16) -> -3442.1743 | CN17: =CK17-CL17 -> -596.28207 | CO17: =CK17-CM17 -> -1092.5225 | CP17: =IFERROR((CK17-CL17)/ABS(CL17),0) -> -0.15140154 | CQ17: =IFERROR((CK17-CM17)/ABS(CM17),0) -> -0.31739316 | CS17: =SUBTOTAL(9,CS6:CS16) -> 7568.4094 | CT17: =SUBTOTAL(9,CT6:CT16) -> 8240.4308 | CU17: =SUBTOTAL(9,CU6:CU16) -> 5789.2564 | CV17: =SUBTOTAL(9,CV6:CV16) -> -672.0214 | CW17: =SUBTOTAL(9,CW6:CW16) -> 1779.1529 | CX17: =IFERROR((CS17-CT17)/ABS(CT17),0) -> -0.081551732 | CY17: =IFERROR((CS17-CU17)/ABS(CU17),0) -> 0.30731976
B18: East | C18: Eastern - Crescent | D18: 402 | E18: Ras Tanoura | F18: Super | G18: LFL | I18: =SUMIFS('P&L Data'!$N:$N,'P&L Data'!$B:$B,$D18,'P&L Data'!$C:$C,$I$4) -> 20081.159 | J18: =SUMIFS('P&L Data'!$P:$P,'P&L Data'!$B:$B,$D18,'P&L Data'!$C:$C,$I$4) -> 20121.195 | K18: =SUMIFS('P&L Data'!$T:$T,'P&L Data'!$B:$B,$D18,'P&L Data'!$C:$C,$I$4) -> 19160.679 | L18: =I18-J18 -> -40.03608 | M18: =I18-K18 -> 920.47956 | N18: =IFERROR((I18-J18)/ABS(J18),0) -> -0.0019897467 | O18: =IFERROR((I18-K18)/ABS(K18),0) -> 0.048040028 | Q18: =SUMIFS('P&L Data'!$N:$N,'P&L Data'!$B:$B,$D18,'P&L Data'!$C:$C,$Q$4) -> 1480.2832 | R18: =SUMIFS('P&L Data'!$P:$P,'P&L Data'!$B:$B,$D18,'P&L Data'!$C:$C,$Q$4) -> 1465.047 | S18: =SUMIFS('P&L Data'!$T:$T,'P&L Data'!$B:$B,$D18,'P&L Data'!$C:$C,$Q$4) -> 1988.2945 | T18: =Q18-R18 -> 15.2362 | U18: =Q18-S18 -> -508.01129 | V18: =IFERROR((Q18-R18)/ABS(R18),0) -> 0.010399803 | W18: =IFERROR((Q18-S18)/ABS(S18),0) -> -0.25550103 | Y18: =SUMIFS('P&L Data'!$N:$N,'P&L Data'!$B:$B,$D18,'P&L Data'!$C:$C,$Y$4) -> 5532.2875 | Z18: =SUMIFS('P&L Data'!$P:$P,'P&L Data'!$B:$B,$D18,'P&L Data'!$C:$C,$Y$4) -> 5342.3605 | AA18: =SUMIFS('P&L Data'!$T:$T,'P&L Data'!$B:$B,$D18,'P&L Data'!$C:$C,$Y$4) -> 5488.6641 | AB18: =Y18-Z18 -> 189.92697 | AC18: =Y18-AA18 -> 43.623395 | AD18: =IFERROR((Y18-Z18)/ABS(Z18),0) -> 0.035551133 | AE18: =IFERROR((Y18-AA18)/ABS(AA18),0) -> 0.0079479077 | AG18: =SUMIFS('P&L Data'!$N:$N,'P&L Data'!$B:$B,$D18,'P&L Data'!$C:$C,$AG$4) -> -64.26216 | AH18: =SUMIFS('P&L Data'!$P:$P,'P&L Data'!$B:$B,$D18,'P&L Data'!$C:$C,$AG$4) -> -128.92507 | AI18: =SUMIFS('P&L Data'!$T:$T,'P&L Data'!$B:$B,$D18,'P&L Data'!$C:$C,$AG$4) -> -148.92065 | AJ18: =AG18-AH18 -> 64.66291 | AK18: =AG18-AI18 -> 84.65849 | AL18: =IFERROR((AG18-AH18)/ABS(AH18),0) -> 0.5015542 | AM18: =IFERROR((AG18-AI18)/ABS(AI18),0) -> 0.56848053 | AO18: =SUMIFS('P&L Data'!$N:$N,'P&L Data'!$B:$B,$D18,'P&L Data'!$C:$C,$AO$4) -> -370.63342 | AP18: =SUMIFS('P&L Data'!$P:$P,'P&L Data'!$B:$B,$D18,'P&L Data'!$C:$C,$AO$4) -> -399.73026 | AQ18: =SUMIFS('P&L Data'!$T:$T,'P&L Data'!$B:$B,$D18,'P&L Data'!$C:$C,$AO$4) -> -347.71075 | AR18: =AO18-AP18 -> 29.09684 | AS18: =AO18-AQ18 -> -22.92267 | AT18: =IFERROR((AO18-AP18)/ABS(AP18),0) -> 0.072791187 | AU18: =IFERROR((AO18-AQ18)/ABS(AQ18),0) -> -0.065924536 | AW18: =SUMIFS('P&L Data'!$N:$N,'P&L Data'!$B:$B,$D18,'P&L Data'!$C:$C,$AW$4) -> 5097.3919 | AX18: =SUMIFS('P&L Data'!$P:$P,'P&L Data'!$B:$B,$D18,'P&L Data'!$C:$C,$AW$4) -> 4813.7052 | AY18: =SUMIFS('P&L Data'!$T:$T,'P&L Data'!$B:$B,$D18,'P&L Data'!$C:$C,$AW$4) -> 4992.0327 | AZ18: =AW18-AX18 -> 283.68672 | BA18: =AW18-AY18 -> 105.35922 | BB18: =IFERROR((AW18-AX18)/ABS(AX18),0) -> 0.058933132 | BC18: =IFERROR((AW18-AY18)/ABS(AY18),0) -> 0.021105474 | BE18: =SUMIFS('P&L Data'!$N:$N,'P&L Data'!$B:$B,$D18,'P&L Data'!$C:$C,$BE$4) -> -1307.7717 | BF18: =SUMIFS('P&L Data'!$P:$P,'P&L Data'!$B:$B,$D18,'P&L Data'!$C:$C,$BE$4) -> -1349.1994 | BG18: =SUMIFS('P&L Data'!$T:$T,'P&L Data'!$B:$B,$D18,'P&L Data'!$C:$C,$BE$4) -> -1293.7509 | BH18: =BE18-BF18 -> 41.42766 | BI18: =BE18-BG18 -> -14.0208 | BJ18: =IFERROR((BE18-BF18)/ABS(BF18),0) -> 0.030705366 | BK18: =IFERROR((BE18-BG18)/ABS(BG18),0) -> -0.010837326 | BM18: =SUMIFS('P&L Data'!$N:$N,'P&L Data'!$B:$B,$D18,'P&L Data'!$C:$C,$BM$4) -> -570.4042 | BN18: =SUMIFS('P&L Data'!$P:$P,'P&L Data'!$B:$B,$D18,'P&L Data'!$C:$C,$BM$4) -> -570.27541 | BO18: =SUMIFS('P&L Data'!$T:$T,'P&L Data'!$B:$B,$D18,'P&L Data'!$C:$C,$BM$4) -> -480.30593 | BP18: =BM18-BN18 -> -0.12879 | BQ18: =BM18-BO18 -> -90.09827 | BR18: =IFERROR((BM18-BN18)/ABS(BN18),0) -> -0.00022583825 | BS18: =IFERROR((BM18-BO18)/ABS(BO18),0) -> -0.18758517 | BU18: =SUMIFS('P&L Data'!$N:$N,'P&L Data'!$B:$B,$D18,'P&L Data'!$C:$C,$BU$4) -> -507.82747 | BV18: =SUMIFS('P&L Data'!$P:$P,'P&L Data'!$B:$B,$D18,'P&L Data'!$C:$C,$BU$4) -> -505.16466 | BW18: =SUMIFS('P&L Data'!$T:$T,'P&L Data'!$B:$B,$D18,'P&L Data'!$C:$C,$BU$4) -> -480.60655 | BX18: =BU18-BV18 -> -2.66281 | BY18: =BU18-BW18 -> -27.22092 | BZ18: =IFERROR((BU18-BV18)/ABS(BV18),0) -> -0.0052711724 | CA18: =IFERROR((BU18-BW18)/ABS(BW18),0) -> -0.056638679 | CC18: =SUMIFS('P&L Data'!$N:$N,'P&L Data'!$B:$B,$D18,'P&L Data'!$C:$C,$CC$4) -> 2711.3885 | CD18: =SUMIFS('P&L Data'!$P:$P,'P&L Data'!$B:$B,$D18,'P&L Data'!$C:$C,$CC$4) -> 2389.0657 | CE18: =SUMIFS('P&L Data'!$T:$T,'P&L Data'!$B:$B,$D18,'P&L Data'!$C:$C,$CC$4) -> 2737.3693 | CF18: =CC18-CD18 -> 322.32278 | CG18: =CC18-CE18 -> -25.980775 | CH18: =IFERROR((CC18-CD18)/ABS(CD18),0) -> 0.13491583 | CI18: =IFERROR((CC18-CE18)/ABS(CE18),0) -> -0.0094911472 | CK18: =SUMIFS('P&L Data'!$N:$N,'P&L Data'!$B:$B,$D18,'P&L Data'!$C:$C,$CK$4) -> -611.54353 | CL18: =SUMIFS('P&L Data'!$P:$P,'P&L Data'!$B:$B,$D18,'P&L Data'!$C:$C,$CK$4) -> -586.45099 | CM18: =SUMIFS('P&L Data'!$T:$T,'P&L Data'!$B:$B,$D18,'P&L Data'!$C:$C,$CK$4) -> -615.07577 | CN18: =CK18-CL18 -> -25.09254 | CO18: =CK18-CM18 -> 3.53224 | CP18: =IFERROR((CK18-CL18)/ABS(CL18),0) -> -0.042787105 | CQ18: =IFERROR((CK18-CM18)/ABS(CM18),0) -> 0.0057427721 | CS18: =SUMIFS('P&L Data'!$N:$N,'P&L Data'!$B:$B,$D18,'P&L Data'!$C:$C,$CS$4) -> 2099.845 | CT18: =SUMIFS('P&L Data'!$P:$P,'P&L Data'!$B:$B,$D18,'P&L Data'!$C:$C,$CS$4) -> 1802.6147 | CU18: =SUMIFS('P&L Data'!$T:$T,'P&L Data'!$B:$B,$D18,'P&L Data'!$C:$C,$CS$4) -> 2122.2935 | CV18: =CS18-CT18 -> 297.23024 | CW18: =CS18-CU18 -> -22.448535 | CX18: =IFERROR((CS18-CT18)/ABS(CT18),0) -> 0.16488839 | CY18: =IFERROR((CS18-CU18)/ABS(CU18),0) -> -0.010577488
B19: East | C19: Eastern - Crescent | D19: 40013 | E19: King Faisal | F19: Hyper | G19: LFL | I19: =SUMIFS('P&L Data'!$N:$N,'P&L Data'!$B:$B,$D19,'P&L Data'!$C:$C,$I$4) -> 18220.99 | J19: =SUMIFS('P&L Data'!$P:$P,'P&L Data'!$B:$B,$D19,'P&L Data'!$C:$C,$I$4) -> 16816.752 | K19: =SUMIFS('P&L Data'!$T:$T,'P&L Data'!$B:$B,$D19,'P&L Data'!$C:$C,$I$4) -> 18592.789 | L19: =I19-J19 -> 1404.2372 | M19: =I19-K19 -> -371.79995 | N19: =IFERROR((I19-J19)/ABS(J19),0) -> 0.083502284 | O19: =IFERROR((I19-K19)/ABS(K19),0) -> -0.019996997 | Q19: =SUMIFS('P&L Data'!$N:$N,'P&L Data'!$B:$B,$D19,'P&L Data'!$C:$C,$Q$4) -> 879.16963 | R19: =SUMIFS('P&L Data'!$P:$P,'P&L Data'!$B:$B,$D19,'P&L Data'!$C:$C,$Q$4) -> 1013.9987 | S19: =SUMIFS('P&L Data'!$T:$T,'P&L Data'!$B:$B,$D19,'P&L Data'!$C:$C,$Q$4) -> 1458.3109 | T19: =Q19-R19 -> -134.8291 | U19: =Q19-S19 -> -579.14131 | V19: =IFERROR((Q19-R19)/ABS(R19),0) -> -0.13296772 | W19: =IFERROR((Q19-S19)/ABS(S19),0) -> -0.39713157 | Y19: =SUMIFS('P&L Data'!$N:$N,'P&L Data'!$B:$B,$D19,'P&L Data'!$C:$C,$Y$4) -> 4430.5333 | Z19: =SUMIFS('P&L Data'!$P:$P,'P&L Data'!$B:$B,$D19,'P&L Data'!$C:$C,$Y$4) -> 4240.731 | AA19: =SUMIFS('P&L Data'!$T:$T,'P&L Data'!$B:$B,$D19,'P&L Data'!$C:$C,$Y$4) -> 4760.9881 | AB19: =Y19-Z19 -> 189.80237 | AC19: =Y19-AA19 -> -330.45474 | AD19: =IFERROR((Y19-Z19)/ABS(Z19),0) -> 0.044756994 | AE19: =IFERROR((Y19-AA19)/ABS(AA19),0) -> -0.069408857 | AG19: =SUMIFS('P&L Data'!$N:$N,'P&L Data'!$B:$B,$D19,'P&L Data'!$C:$C,$AG$4) -> -91.41759 | AH19: =SUMIFS('P&L Data'!$P:$P,'P&L Data'!$B:$B,$D19,'P&L Data'!$C:$C,$AG$4) -> -107.57257 | AI19: =SUMIFS('P&L Data'!$T:$T,'P&L Data'!$B:$B,$D19,'P&L Data'!$C:$C,$AG$4) -> -143.93166 | AJ19: =AG19-AH19 -> 16.15498 | AK19: =AG19-AI19 -> 52.51407 | AL19: =IFERROR((AG19-AH19)/ABS(AH19),0) -> 0.1501775 | AM19: =IFERROR((AG19-AI19)/ABS(AI19),0) -> 0.3648542 | AO19: =SUMIFS('P&L Data'!$N:$N,'P&L Data'!$B:$B,$D19,'P&L Data'!$C:$C,$AO$4) -> -335.5996 | AP19: =SUMIFS('P&L Data'!$P:$P,'P&L Data'!$B:$B,$D19,'P&L Data'!$C:$C,$AO$4) -> -327.49598 | AQ19: =SUMIFS('P&L Data'!$T:$T,'P&L Data'!$B:$B,$D19,'P&L Data'!$C:$C,$AO$4) -> -315.53509 | AR19: =AO19-AP19 -> -8.10362 | AS19: =AO19-AQ19 -> -20.064508 | AT19: =IFERROR((AO19-AP19)/ABS(AP19),0) -> -0.024744182 | AU19: =IFERROR((AO19-AQ19)/ABS(AQ19),0) -> -0.063588831 | AW19: =SUMIFS('P&L Data'!$N:$N,'P&L Data'!$B:$B,$D19,'P&L Data'!$C:$C,$AW$4) -> 4003.5161 | AX19: =SUMIFS('P&L Data'!$P:$P,'P&L Data'!$B:$B,$D19,'P&L Data'!$C:$C,$AW$4) -> 3805.6624 | AY19: =SUMIFS('P&L Data'!$T:$T,'P&L Data'!$B:$B,$D19,'P&L Data'!$C:$C,$AW$4) -> 4301.5213 | AZ19: =AW19-AX19 -> 197.85373 | BA19: =AW19-AY19 -> -298.00518 | BB19: =IFERROR((AW19-AX19)/ABS(AX19),0) -> 0.051989302 | BC19: =IFERROR((AW19-AY19)/ABS(AY19),0) -> -0.069279019 | BE19: =SUMIFS('P&L Data'!$N:$N,'P&L Data'!$B:$B,$D19,'P&L Data'!$C:$C,$BE$4) -> -1375.6674 | BF19: =SUMIFS('P&L Data'!$P:$P,'P&L Data'!$B:$B,$D19,'P&L Data'!$C:$C,$BE$4) -> -1482.33 | BG19: =SUMIFS('P&L Data'!$T:$T,'P&L Data'!$B:$B,$D19,'P&L Data'!$C:$C,$BE$4) -> -1625.3752 | BH19: =BE19-BF19 -> 106.66259 | BI19: =BE19-BG19 -> 249.7078 | BJ19: =IFERROR((BE19-BF19)/ABS(BF19),0) -> 0.071956034 | BK19: =IFERROR((BE19-BG19)/ABS(BG19),0) -> 0.15363086 | BM19: =SUMIFS('P&L Data'!$N:$N,'P&L Data'!$B:$B,$D19,'P&L Data'!$C:$C,$BM$4) -> -701.59465 | BN19: =SUMIFS('P&L Data'!$P:$P,'P&L Data'!$B:$B,$D19,'P&L Data'!$C:$C,$BM$4) -> -636.36208 | BO19: =SUMIFS('P&L Data'!$T:$T,'P&L Data'!$B:$B,$D19,'P&L Data'!$C:$C,$BM$4) -> -612.66207 | BP19: =BM19-BN19 -> -65.23257 | BQ19: =BM19-BO19 -> -88.93258 | BR19: =IFERROR((BM19-BN19)/ABS(BN19),0) -> -0.10250857 | BS19: =IFERROR((BM19-BO19)/ABS(BO19),0) -> -0.14515764 | BU19: =SUMIFS('P&L Data'!$N:$N,'P&L Data'!$B:$B,$D19,'P&L Data'!$C:$C,$BU$4) -> -1760.1473 | BV19: =SUMIFS('P&L Data'!$P:$P,'P&L Data'!$B:$B,$D19,'P&L Data'!$C:$C,$BU$4) -> -1760.1473 | BW19: =SUMIFS('P&L Data'!$T:$T,'P&L Data'!$B:$B,$D19,'P&L Data'!$C:$C,$BU$4) -> -1760.1473 | BX19: =BU19-BV19 -> 0 | BY19: =BU19-BW19 -> 0 | BZ19: =IFERROR((BU19-BV19)/ABS(BV19),0) -> 0 | CA19: =IFERROR((BU19-BW19)/ABS(BW19),0) -> 0 | CC19: =SUMIFS('P&L Data'!$N:$N,'P&L Data'!$B:$B,$D19,'P&L Data'!$C:$C,$CC$4) -> 166.10677 | CD19: =SUMIFS('P&L Data'!$P:$P,'P&L Data'!$B:$B,$D19,'P&L Data'!$C:$C,$CC$4) -> -73.17698 | CE19: =SUMIFS('P&L Data'!$T:$T,'P&L Data'!$B:$B,$D19,'P&L Data'!$C:$C,$CC$4) -> 303.33673 | CF19: =CC19-CD19 -> 239.28375 | CG19: =CC19-CE19 -> -137.22996 | CH19: =IFERROR((CC19-CD19)/ABS(CD19),0) -> 3.269932 | CI19: =IFERROR((CC19-CE19)/ABS(CE19),0) -> -0.45240139 | CK19: =SUMIFS('P&L Data'!$N:$N,'P&L Data'!$B:$B,$D19,'P&L Data'!$C:$C,$CK$4) -> -260.53206 | CL19: =SUMIFS('P&L Data'!$P:$P,'P&L Data'!$B:$B,$D19,'P&L Data'!$C:$C,$CK$4) -> -252.77984 | CM19: =SUMIFS('P&L Data'!$T:$T,'P&L Data'!$B:$B,$D19,'P&L Data'!$C:$C,$CK$4) -> -286.64747 | CN19: =CK19-CL19 -> -7.75222 | CO19: =CK19-CM19 -> 26.11541 | CP19: =IFERROR((CK19-CL19)/ABS(CL19),0) -> -0.030667873 | CQ19: =IFERROR((CK19-CM19)/ABS(CM19),0) -> 0.091106368 | CS19: =SUMIFS('P&L Data'!$N:$N,'P&L Data'!$B:$B,$D19,'P&L Data'!$C:$C,$CS$4) -> -94.42529 | CT19: =SUMIFS('P&L Data'!$P:$P,'P&L Data'!$B:$B,$D19,'P&L Data'!$C:$C,$CS$4) -> -325.95682 | CU19: =SUMIFS('P&L Data'!$T:$T,'P&L Data'!$B:$B,$D19,'P&L Data'!$C:$C,$CS$4) -> 16.689257 | CV19: =CS19-CT19 -> 231.53153 | CW19: =CS19-CU19 -> -111.11455 | CX19: =IFERROR((CS19-CT19)/ABS(CT19),0) -> 0.7103135 | CY19: =IFERROR((CS19-CU19)/ABS(CU19),0) -> -6.6578485
B20: East | C20: Eastern - Crescent Total | I20: =SUBTOTAL(9,I18:I19) -> 38302.148 | J20: =SUBTOTAL(9,J18:J19) -> 36937.947 | K20: =SUBTOTAL(9,K18:K19) -> 37753.468 | L20: =I20-J20 -> 1364.2012 | M20: =I20-K20 -> 548.67961 | N20: =IFERROR((I20-J20)/ABS(J20),0) -> 0.036932241 | O20: =IFERROR((I20-K20)/ABS(K20),0) -> 0.014533224 | Q20: =SUBTOTAL(9,Q18:Q19) -> 2359.4529 | R20: =SUBTOTAL(9,R18:R19) -> 2479.0458 | S20: =SUBTOTAL(9,S18:S19) -> 3446.6055 | T20: =Q20-R20 -> -119.5929 | U20: =Q20-S20 -> -1087.1526 | V20: =IFERROR((Q20-R20)/ABS(R20),0) -> -0.048241506 | W20: =IFERROR((Q20-S20)/ABS(S20),0) -> -0.31542705 | Y20: =SUBTOTAL(9,Y18:Y19) -> 9962.8208 | Z20: =SUBTOTAL(9,Z18:Z19) -> 9583.0914 | AA20: =SUBTOTAL(9,AA18:AA19) -> 10249.652 | AB20: =Y20-Z20 -> 379.72934 | AC20: =Y20-AA20 -> -286.83134 | AD20: =IFERROR((Y20-Z20)/ABS(Z20),0) -> 0.039624931 | AE20: =IFERROR((Y20-AA20)/ABS(AA20),0) -> -0.027984496 | AG20: =SUBTOTAL(9,AG18:AG19) -> -155.67975 | AH20: =SUBTOTAL(9,AH18:AH19) -> -236.49764 | AI20: =SUBTOTAL(9,AI18:AI19) -> -292.85231 | AJ20: =AG20-AH20 -> 80.81789 | AK20: =AG20-AI20 -> 137.17256 | AL20: =IFERROR((AG20-AH20)/ABS(AH20),0) -> 0.3417281 | AM20: =IFERROR((AG20-AI20)/ABS(AI20),0) -> 0.46840184 | AO20: =SUBTOTAL(9,AO18:AO19) -> -706.23302 | AP20: =SUBTOTAL(9,AP18:AP19) -> -727.22624 | AQ20: =SUBTOTAL(9,AQ18:AQ19) -> -663.24584 | AR20: =AO20-AP20 -> 20.99322 | AS20: =AO20-AQ20 -> -42.987178 | AT20: =IFERROR((AO20-AP20)/ABS(AP20),0) -> 0.028867523 | AU20: =IFERROR((AO20-AQ20)/ABS(AQ20),0) -> -0.064813339 | AW20: =SUBTOTAL(9,AW18:AW19) -> 9100.908 | AX20: =SUBTOTAL(9,AX18:AX19) -> 8619.3676 | AY20: =SUBTOTAL(9,AY18:AY19) -> 9293.554 | AZ20: =AW20-AX20 -> 481.54045 | BA20: =AW20-AY20 -> -192.64596 | BB20: =IFERROR((AW20-AX20)/ABS(AX20),0) -> 0.05586726 | BC20: =IFERROR((AW20-AY20)/ABS(AY20),0) -> -0.020728987 | BE20: =SUBTOTAL(9,BE18:BE19) -> -2683.4391 | BF20: =SUBTOTAL(9,BF18:BF19) -> -2831.5294 | BG20: =SUBTOTAL(9,BG18:BG19) -> -2919.1261 | BH20: =BE20-BF20 -> 148.09025 | BI20: =BE20-BG20 -> 235.687 | BJ20: =IFERROR((BE20-BF20)/ABS(BF20),0) -> 0.052300446 | BK20: =IFERROR((BE20-BG20)/ABS(BG20),0) -> 0.080738889 | BM20: =SUBTOTAL(9,BM18:BM19) -> -1271.9988 | BN20: =SUBTOTAL(9,BN18:BN19) -> -1206.6375 | BO20: =SUBTOTAL(9,BO18:BO19) -> -1092.968 | BP20: =BM20-BN20 -> -65.36136 | BQ20: =BM20-BO20 -> -179.03085 | BR20: =IFERROR((BM20-BN20)/ABS(BN20),0) -> -0.054168183 | BS20: =IFERROR((BM20-BO20)/ABS(BO20),0) -> -0.16380246 | BU20: =SUBTOTAL(9,BU18:BU19) -> -2267.9748 | BV20: =SUBTOTAL(9,BV18:BV19) -> -2265.3119 | BW20: =SUBTOTAL(9,BW18:BW19) -> -2240.7538 | BX20: =BU20-BV20 -> -2.66281 | BY20: =BU20-BW20 -> -27.22092 | BZ20: =IFERROR((BU20-BV20)/ABS(BV20),0) -> -0.0011754717 | CA20: =IFERROR((BU20-BW20)/ABS(BW20),0) -> -0.012148108 | CC20: =SUBTOTAL(9,CC18:CC19) -> 2877.4953 | CD20: =SUBTOTAL(9,CD18:CD19) -> 2315.8887 | CE20: =SUBTOTAL(9,CE18:CE19) -> 3040.706 | CF20: =CC20-CD20 -> 561.60653 | CG20: =CC20-CE20 -> -163.21073 | CH20: =IFERROR((CC20-CD20)/ABS(CD20),0) -> 0.24250152 | CI20: =IFERROR((CC20-CE20)/ABS(CE20),0) -> -0.053675275 | CK20: =SUBTOTAL(9,CK18:CK19) -> -872.07559 | CL20: =SUBTOTAL(9,CL18:CL19) -> -839.23083 | CM20: =SUBTOTAL(9,CM18:CM19) -> -901.72324 | CN20: =CK20-CL20 -> -32.84476 | CO20: =CK20-CM20 -> 29.64765 | CP20: =IFERROR((CK20-CL20)/ABS(CL20),0) -> -0.039136741 | CQ20: =IFERROR((CK20-CM20)/ABS(CM20),0) -> 0.03287888 | CS20: =SUBTOTAL(9,CS18:CS19) -> 2005.4197 | CT20: =SUBTOTAL(9,CT18:CT19) -> 1476.6579 | CU20: =SUBTOTAL(9,CU18:CU19) -> 2138.9828 | CV20: =SUBTOTAL(9,CV18:CV19) -> 528.76177 | CW20: =SUBTOTAL(9,CW18:CW19) -> -133.56308 | CX20: =IFERROR((CS20-CT20)/ABS(CT20),0) -> 0.35808007 | CY20: =IFERROR((CS20-CU20)/ABS(CU20),0) -> -0.062442337
B21: East | C21: Eastern - Nucleus | D21: 403 | E21: Abdulaziz Road | F21: Super | G21: LFL | I21: =SUMIFS('P&L Data'!$N:$N,'P&L Data'!$B:$B,$D21,'P&L Data'!$C:$C,$I$4) -> 17491.603 | J21: =SUMIFS('P&L Data'!$P:$P,'P&L Data'!$B:$B,$D21,'P&L Data'!$C:$C,$I$4) -> 18027.356 | K21: =SUMIFS('P&L Data'!$T:$T,'P&L Data'!$B:$B,$D21,'P&L Data'!$C:$C,$I$4) -> 17875.271 | L21: =I21-J21 -> -535.75295 | M21: =I21-K21 -> -383.66813 | N21: =IFERROR((I21-J21)/ABS(J21),0) -> -0.029718886 | O21: =IFERROR((I21-K21)/ABS(K21),0) -> -0.021463625 | Q21: =SUMIFS('P&L Data'!$N:$N,'P&L Data'!$B:$B,$D21,'P&L Data'!$C:$C,$Q$4) -> 457.02187 | R21: =SUMIFS('P&L Data'!$P:$P,'P&L Data'!$B:$B,$D21,'P&L Data'!$C:$C,$Q$4) -> 562.02675 | S21: =SUMIFS('P&L Data'!$T:$T,'P&L Data'!$B:$B,$D21,'P&L Data'!$C:$C,$Q$4) -> 485.75011 | T21: =Q21-R21 -> -105.00488 | U21: =Q21-S21 -> -28.728243 | V21: =IFERROR((Q21-R21)/ABS(R21),0) -> -0.18683253 | W21: =IFERROR((Q21-S21)/ABS(S21),0) -> -0.05914202 | Y21: =SUMIFS('P&L Data'!$N:$N,'P&L Data'!$B:$B,$D21,'P&L Data'!$C:$C,$Y$4) -> 3820.6273 | Z21: =SUMIFS('P&L Data'!$P:$P,'P&L Data'!$B:$B,$D21,'P&L Data'!$C:$C,$Y$4) -> 3887.6298 | AA21: =SUMIFS('P&L Data'!$T:$T,'P&L Data'!$B:$B,$D21,'P&L Data'!$C:$C,$Y$4) -> 3581.8751 | AB21: =Y21-Z21 -> -67.00248 | AC21: =Y21-AA21 -> 238.75218 | AD21: =IFERROR((Y21-Z21)/ABS(Z21),0) -> -0.017234789 | AE21: =IFERROR((Y21-AA21)/ABS(AA21),0) -> 0.06665564 | AG21: =SUMIFS('P&L Data'!$N:$N,'P&L Data'!$B:$B,$D21,'P&L Data'!$C:$C,$AG$4) -> -52.59127 | AH21: =SUMIFS('P&L Data'!$P:$P,'P&L Data'!$B:$B,$D21,'P&L Data'!$C:$C,$AG$4) -> -104.03199 | AI21: =SUMIFS('P&L Data'!$T:$T,'P&L Data'!$B:$B,$D21,'P&L Data'!$C:$C,$AG$4) -> -105.28811 | AJ21: =AG21-AH21 -> 51.44072 | AK21: =AG21-AI21 -> 52.69684 | AL21: =IFERROR((AG21-AH21)/ABS(AH21),0) -> 0.49447021 | AM21: =IFERROR((AG21-AI21)/ABS(AI21),0) -> 0.50050134 | AO21: =SUMIFS('P&L Data'!$N:$N,'P&L Data'!$B:$B,$D21,'P&L Data'!$C:$C,$AO$4) -> -305.91338 | AP21: =SUMIFS('P&L Data'!$P:$P,'P&L Data'!$B:$B,$D21,'P&L Data'!$C:$C,$AO$4) -> -336.35045 | AQ21: =SUMIFS('P&L Data'!$T:$T,'P&L Data'!$B:$B,$D21,'P&L Data'!$C:$C,$AO$4) -> -272.74924 | AR21: =AO21-AP21 -> 30.43707 | AS21: =AO21-AQ21 -> -33.16414 | AT21: =IFERROR((AO21-AP21)/ABS(AP21),0) -> 0.090492134 | AU21: =IFERROR((AO21-AQ21)/ABS(AQ21),0) -> -0.12159205 | AW21: =SUMIFS('P&L Data'!$N:$N,'P&L Data'!$B:$B,$D21,'P&L Data'!$C:$C,$AW$4) -> 3462.1227 | AX21: =SUMIFS('P&L Data'!$P:$P,'P&L Data'!$B:$B,$D21,'P&L Data'!$C:$C,$AW$4) -> 3447.2473 | AY21: =SUMIFS('P&L Data'!$T:$T,'P&L Data'!$B:$B,$D21,'P&L Data'!$C:$C,$AW$4) -> 3203.8378 | AZ21: =AW21-AX21 -> 14.87531 | BA21: =AW21-AY21 -> 258.28488 | BB21: =IFERROR((AW21-AX21)/ABS(AX21),0) -> 0.004315127 | BC21: =IFERROR((AW21-AY21)/ABS(AY21),0) -> 0.080617339 | BE21: =SUMIFS('P&L Data'!$N:$N,'P&L Data'!$B:$B,$D21,'P&L Data'!$C:$C,$BE$4) -> -1275.7016 | BF21: =SUMIFS('P&L Data'!$P:$P,'P&L Data'!$B:$B,$D21,'P&L Data'!$C:$C,$BE$4) -> -1314.7497 | BG21: =SUMIFS('P&L Data'!$T:$T,'P&L Data'!$B:$B,$D21,'P&L Data'!$C:$C,$BE$4) -> -1232.559 | BH21: =BE21-BF21 -> 39.04805 | BI21: =BE21-BG21 -> -43.14259 | BJ21: =IFERROR((BE21-BF21)/ABS(BF21),0) -> 0.029699988 | BK21: =IFERROR((BE21-BG21)/ABS(BG21),0) -> -0.035002453 | BM21: =SUMIFS('P&L Data'!$N:$N,'P&L Data'!$B:$B,$D21,'P&L Data'!$C:$C,$BM$4) -> -545.18259 | BN21: =SUMIFS('P&L Data'!$P:$P,'P&L Data'!$B:$B,$D21,'P&L Data'!$C:$C,$BM$4) -> -526.71839 | BO21: =SUMIFS('P&L Data'!$T:$T,'P&L Data'!$B:$B,$D21,'P&L Data'!$C:$C,$BM$4) -> -510.32952 | BP21: =BM21-BN21 -> -18.4642 | BQ21: =BM21-BO21 -> -34.85307 | BR21: =IFERROR((BM21-BN21)/ABS(BN21),0) -> -0.035055165 | BS21: =IFERROR((BM21-BO21)/ABS(BO21),0) -> -0.068295226 | BU21: =SUMIFS('P&L Data'!$N:$N,'P&L Data'!$B:$B,$D21,'P&L Data'!$C:$C,$BU$4) -> -510.33404 | BV21: =SUMIFS('P&L Data'!$P:$P,'P&L Data'!$B:$B,$D21,'P&L Data'!$C:$C,$BU$4) -> -510.33404 | BW21: =SUMIFS('P&L Data'!$T:$T,'P&L Data'!$B:$B,$D21,'P&L Data'!$C:$C,$BU$4) -> -510.33404 | BX21: =BU21-BV21 -> 0 | BY21: =BU21-BW21 -> 0 | BZ21: =IFERROR((BU21-BV21)/ABS(BV21),0) -> 0 | CA21: =IFERROR((BU21-BW21)/ABS(BW21),0) -> 0 | CC21: =SUMIFS('P&L Data'!$N:$N,'P&L Data'!$B:$B,$D21,'P&L Data'!$C:$C,$CC$4) -> 1130.9044 | CD21: =SUMIFS('P&L Data'!$P:$P,'P&L Data'!$B:$B,$D21,'P&L Data'!$C:$C,$CC$4) -> 1095.4452 | CE21: =SUMIFS('P&L Data'!$T:$T,'P&L Data'!$B:$B,$D21,'P&L Data'!$C:$C,$CC$4) -> 950.61518 | CF21: =CC21-CD21 -> 35.45916 | CG21: =CC21-CE21 -> 180.28922 | CH21: =IFERROR((CC21-CD21)/ABS(CD21),0) -> 0.032369633 | CI21: =IFERROR((CC21-CE21)/ABS(CE21),0) -> 0.18965531 | CK21: =SUMIFS('P&L Data'!$N:$N,'P&L Data'!$B:$B,$D21,'P&L Data'!$C:$C,$CK$4) -> -599.01965 | CL21: =SUMIFS('P&L Data'!$P:$P,'P&L Data'!$B:$B,$D21,'P&L Data'!$C:$C,$CK$4) -> -381.79382 | CM21: =SUMIFS('P&L Data'!$T:$T,'P&L Data'!$B:$B,$D21,'P&L Data'!$C:$C,$CK$4) -> -395.13775 | CN21: =CK21-CL21 -> -217.22583 | CO21: =CK21-CM21 -> -203.8819 | CP21: =IFERROR((CK21-CL21)/ABS(CL21),0) -> -0.5689611 | CQ21: =IFERROR((CK21-CM21)/ABS(CM21),0) -> -0.51597677 | CS21: =SUMIFS('P&L Data'!$N:$N,'P&L Data'!$B:$B,$D21,'P&L Data'!$C:$C,$CS$4) -> 531.88475 | CT21: =SUMIFS('P&L Data'!$P:$P,'P&L Data'!$B:$B,$D21,'P&L Data'!$C:$C,$CS$4) -> 713.65142 | CU21: =SUMIFS('P&L Data'!$T:$T,'P&L Data'!$B:$B,$D21,'P&L Data'!$C:$C,$CS$4) -> 555.47743 | CV21: =CS21-CT21 -> -181.76667 | CW21: =CS21-CU21 -> -23.592683 | CX21: =IFERROR((CS21-CT21)/ABS(CT21),0) -> -0.25469951 | CY21: =IFERROR((CS21-CU21)/ABS(CU21),0) -> -0.042472801
B22: East | C22: Eastern - Nucleus | D22: 40004 | E22: Jarir Palaza | F22: Hyper | G22: LFL | I22: =SUMIFS('P&L Data'!$N:$N,'P&L Data'!$B:$B,$D22,'P&L Data'!$C:$C,$I$4) -> 45810.779 | J22: =SUMIFS('P&L Data'!$P:$P,'P&L Data'!$B:$B,$D22,'P&L Data'!$C:$C,$I$4) -> 45889.676 | K22: =SUMIFS('P&L Data'!$T:$T,'P&L Data'!$B:$B,$D22,'P&L Data'!$C:$C,$I$4) -> 40338.094 | L22: =I22-J22 -> -78.89678 | M22: =I22-K22 -> 5472.6855 | N22: =IFERROR((I22-J22)/ABS(J22),0) -> -0.0017192708 | O22: =IFERROR((I22-K22)/ABS(K22),0) -> 0.1356704 | Q22: =SUMIFS('P&L Data'!$N:$N,'P&L Data'!$B:$B,$D22,'P&L Data'!$C:$C,$Q$4) -> 3758.6206 | R22: =SUMIFS('P&L Data'!$P:$P,'P&L Data'!$B:$B,$D22,'P&L Data'!$C:$C,$Q$4) -> 3623.8625 | S22: =SUMIFS('P&L Data'!$T:$T,'P&L Data'!$B:$B,$D22,'P&L Data'!$C:$C,$Q$4) -> 4155.3537 | T22: =Q22-R22 -> 134.75817 | U22: =Q22-S22 -> -396.73304 | V22: =IFERROR((Q22-R22)/ABS(R22),0) -> 0.037186337 | W22: =IFERROR((Q22-S22)/ABS(S22),0) -> -0.095475156 | Y22: =SUMIFS('P&L Data'!$N:$N,'P&L Data'!$B:$B,$D22,'P&L Data'!$C:$C,$Y$4) -> 12502.499 | Z22: =SUMIFS('P&L Data'!$P:$P,'P&L Data'!$B:$B,$D22,'P&L Data'!$C:$C,$Y$4) -> 12283.954 | AA22: =SUMIFS('P&L Data'!$T:$T,'P&L Data'!$B:$B,$D22,'P&L Data'!$C:$C,$Y$4) -> 11412.367 | AB22: =Y22-Z22 -> 218.54481 | AC22: =Y22-AA22 -> 1090.1318 | AD22: =IFERROR((Y22-Z22)/ABS(Z22),0) -> 0.01779108 | AE22: =IFERROR((Y22-AA22)/ABS(AA22),0) -> 0.095521975 | AG22: =SUMIFS('P&L Data'!$N:$N,'P&L Data'!$B:$B,$D22,'P&L Data'!$C:$C,$AG$4) -> -151.68627 | AH22: =SUMIFS('P&L Data'!$P:$P,'P&L Data'!$B:$B,$D22,'P&L Data'!$C:$C,$AG$4) -> -277.68355 | AI22: =SUMIFS('P&L Data'!$T:$T,'P&L Data'!$B:$B,$D22,'P&L Data'!$C:$C,$AG$4) -> -101.6682 | AJ22: =AG22-AH22 -> 125.99728 | AK22: =AG22-AI22 -> -50.01807 | AL22: =IFERROR((AG22-AH22)/ABS(AH22),0) -> 0.45374413 | AM22: =IFERROR((AG22-AI22)/ABS(AI22),0) -> -0.4919736 | AO22: =SUMIFS('P&L Data'!$N:$N,'P&L Data'!$B:$B,$D22,'P&L Data'!$C:$C,$AO$4) -> -806.63312 | AP22: =SUMIFS('P&L Data'!$P:$P,'P&L Data'!$B:$B,$D22,'P&L Data'!$C:$C,$AO$4) -> -882.73461 | AQ22: =SUMIFS('P&L Data'!$T:$T,'P&L Data'!$B:$B,$D22,'P&L Data'!$C:$C,$AO$4) -> -680.88048 | AR22: =AO22-AP22 -> 76.10149 | AS22: =AO22-AQ22 -> -125.75264 | AT22: =IFERROR((AO22-AP22)/ABS(AP22),0) -> 0.086211064 | AU22: =IFERROR((AO22-AQ22)/ABS(AQ22),0) -> -0.18469122 | AW22: =SUMIFS('P&L Data'!$N:$N,'P&L Data'!$B:$B,$D22,'P&L Data'!$C:$C,$AW$4) -> 11544.18 | AX22: =SUMIFS('P&L Data'!$P:$P,'P&L Data'!$B:$B,$D22,'P&L Data'!$C:$C,$AW$4) -> 11123.536 | AY22: =SUMIFS('P&L Data'!$T:$T,'P&L Data'!$B:$B,$D22,'P&L Data'!$C:$C,$AW$4) -> 10629.818 | AZ22: =AW22-AX22 -> 420.64358 | BA22: =AW22-AY22 -> 914.36113 | BB22: =IFERROR((AW22-AX22)/ABS(AX22),0) -> 0.037815635 | BC22: =IFERROR((AW22-AY22)/ABS(AY22),0) -> 0.086018509 | BE22: =SUMIFS('P&L Data'!$N:$N,'P&L Data'!$B:$B,$D22,'P&L Data'!$C:$C,$BE$4) -> -3062.029 | BF22: =SUMIFS('P&L Data'!$P:$P,'P&L Data'!$B:$B,$D22,'P&L Data'!$C:$C,$BE$4) -> -2741.4133 | BG22: =SUMIFS('P&L Data'!$T:$T,'P&L Data'!$B:$B,$D22,'P&L Data'!$C:$C,$BE$4) -> -2734.0391 | BH22: =BE22-BF22 -> -320.61569 | BI22: =BE22-BG22 -> -327.98989 | BJ22: =IFERROR((BE22-BF22)/ABS(BF22),0) -> -0.1169527 | BK22: =IFERROR((BE22-BG22)/ABS(BG22),0) -> -0.11996532 | BM22: =SUMIFS('P&L Data'!$N:$N,'P&L Data'!$B:$B,$D22,'P&L Data'!$C:$C,$BM$4) -> -1168.9917 | BN22: =SUMIFS('P&L Data'!$P:$P,'P&L Data'!$B:$B,$D22,'P&L Data'!$C:$C,$BM$4) -> -1435.3066 | BO22: =SUMIFS('P&L Data'!$T:$T,'P&L Data'!$B:$B,$D22,'P&L Data'!$C:$C,$BM$4) -> -1633.0376 | BP22: =BM22-BN22 -> 266.31492 | BQ22: =BM22-BO22 -> 464.04598 | BR22: =IFERROR((BM22-BN22)/ABS(BN22),0) -> 0.18554567 | BS22: =IFERROR((BM22-BO22)/ABS(BO22),0) -> 0.28416123 | BU22: =SUMIFS('P&L Data'!$N:$N,'P&L Data'!$B:$B,$D22,'P&L Data'!$C:$C,$BU$4) -> -1508.4022 | BV22: =SUMIFS('P&L Data'!$P:$P,'P&L Data'!$B:$B,$D22,'P&L Data'!$C:$C,$BU$4) -> -1508.4022 | BW22: =SUMIFS('P&L Data'!$T:$T,'P&L Data'!$B:$B,$D22,'P&L Data'!$C:$C,$BU$4) -> -1508.4022 | BX22: =BU22-BV22 -> 0 | BY22: =BU22-BW22 -> 0 | BZ22: =IFERROR((BU22-BV22)/ABS(BV22),0) -> 0 | CA22: =IFERROR((BU22-BW22)/ABS(BW22),0) -> 0 | CC22: =SUMIFS('P&L Data'!$N:$N,'P&L Data'!$B:$B,$D22,'P&L Data'!$C:$C,$CC$4) -> 5804.7567 | CD22: =SUMIFS('P&L Data'!$P:$P,'P&L Data'!$B:$B,$D22,'P&L Data'!$C:$C,$CC$4) -> 5438.4139 | CE22: =SUMIFS('P&L Data'!$T:$T,'P&L Data'!$B:$B,$D22,'P&L Data'!$C:$C,$CC$4) -> 4754.3395 | CF22: =CC22-CD22 -> 366.34281 | CG22: =CC22-CE22 -> 1050.4172 | CH22: =IFERROR((CC22-CD22)/ABS(CD22),0) -> 0.067362069 | CI22: =IFERROR((CC22-CE22)/ABS(CE22),0) -> 0.22093862 | CK22: =SUMIFS('P&L Data'!$N:$N,'P&L Data'!$B:$B,$D22,'P&L Data'!$C:$C,$CK$4) -> -1551.4712 | CL22: =SUMIFS('P&L Data'!$P:$P,'P&L Data'!$B:$B,$D22,'P&L Data'!$C:$C,$CK$4) -> -1450.7237 | CM22: =SUMIFS('P&L Data'!$T:$T,'P&L Data'!$B:$B,$D22,'P&L Data'!$C:$C,$CK$4) -> -1436.0115 | CN22: =CK22-CL22 -> -100.74748 | CO22: =CK22-CM22 -> -115.45971 | CP22: =IFERROR((CK22-CL22)/ABS(CL22),0) -> -0.069446357 | CQ22: =IFERROR((CK22-CM22)/ABS(CM22),0) -> -0.080403053 | CS22: =SUMIFS('P&L Data'!$N:$N,'P&L Data'!$B:$B,$D22,'P&L Data'!$C:$C,$CS$4) -> 4253.2855 | CT22: =SUMIFS('P&L Data'!$P:$P,'P&L Data'!$B:$B,$D22,'P&L Data'!$C:$C,$CS$4) -> 3987.6901 | CU22: =SUMIFS('P&L Data'!$T:$T,'P&L Data'!$B:$B,$D22,'P&L Data'!$C:$C,$CS$4) -> 3318.3279 | CV22: =CS22-CT22 -> 265.59533 | CW22: =CS22-CU22 -> 934.95751 | CX22: =IFERROR((CS22-CT22)/ABS(CT22),0) -> 0.066603804 | CY22: =IFERROR((CS22-CU22)/ABS(CU22),0) -> 0.28175561
B23: East | C23: Eastern - Nucleus Total | I23: =SUBTOTAL(9,I21:I22) -> 63302.383 | J23: =SUBTOTAL(9,J21:J22) -> 63917.033 | K23: =SUBTOTAL(9,K21:K22) -> 58213.365 | L23: =I23-J23 -> -614.64973 | M23: =I23-K23 -> 5089.0173 | N23: =IFERROR((I23-J23)/ABS(J23),0) -> -0.0096163684 | O23: =IFERROR((I23-K23)/ABS(K23),0) -> 0.087420084 | Q23: =SUBTOTAL(9,Q21:Q22) -> 4215.6425 | R23: =SUBTOTAL(9,R21:R22) -> 4185.8892 | S23: =SUBTOTAL(9,S21:S22) -> 4641.1038 | T23: =Q23-R23 -> 29.75329 | U23: =Q23-S23 -> -425.46128 | V23: =IFERROR((Q23-R23)/ABS(R23),0) -> 0.0071079975 | W23: =IFERROR((Q23-S23)/ABS(S23),0) -> -0.091672434 | Y23: =SUBTOTAL(9,Y21:Y22) -> 16323.126 | Z23: =SUBTOTAL(9,Z21:Z22) -> 16171.584 | AA23: =SUBTOTAL(9,AA21:AA22) -> 14994.242 | AB23: =Y23-Z23 -> 151.54233 | AC23: =Y23-AA23 -> 1328.884 | AD23: =IFERROR((Y23-Z23)/ABS(Z23),0) -> 0.0093709021 | AE23: =IFERROR((Y23-AA23)/ABS(AA23),0) -> 0.088626288 | AG23: =SUBTOTAL(9,AG21:AG22) -> -204.27754 | AH23: =SUBTOTAL(9,AH21:AH22) -> -381.71554 | AI23: =SUBTOTAL(9,AI21:AI22) -> -206.95631 | AJ23: =AG23-AH23 -> 177.438 | AK23: =AG23-AI23 -> 2.67877 | AL23: =IFERROR((AG23-AH23)/ABS(AH23),0) -> 0.46484353 | AM23: =IFERROR((AG23-AI23)/ABS(AI23),0) -> 0.01294365 | AO23: =SUBTOTAL(9,AO21:AO22) -> -1112.5465 | AP23: =SUBTOTAL(9,AP21:AP22) -> -1219.0851 | AQ23: =SUBTOTAL(9,AQ21:AQ22) -> -953.62972 | AR23: =AO23-AP23 -> 106.53856 | AS23: =AO23-AQ23 -> -158.91678 | AT23: =IFERROR((AO23-AP23)/ABS(AP23),0) -> 0.087392228 | AU23: =IFERROR((AO23-AQ23)/ABS(AQ23),0) -> -0.16664412 | AW23: =SUBTOTAL(9,AW21:AW22) -> 15006.302 | AX23: =SUBTOTAL(9,AX21:AX22) -> 14570.783 | AY23: =SUBTOTAL(9,AY21:AY22) -> 13833.656 | AZ23: =AW23-AX23 -> 435.51889 | BA23: =AW23-AY23 -> 1172.646 | BB23: =IFERROR((AW23-AX23)/ABS(AX23),0) -> 0.029889875 | BC23: =IFERROR((AW23-AY23)/ABS(AY23),0) -> 0.084767613 | BE23: =SUBTOTAL(9,BE21:BE22) -> -4337.7306 | BF23: =SUBTOTAL(9,BF21:BF22) -> -4056.163 | BG23: =SUBTOTAL(9,BG21:BG22) -> -3966.5982 | BH23: =BE23-BF23 -> -281.56764 | BI23: =BE23-BG23 -> -371.13248 | BJ23: =IFERROR((BE23-BF23)/ABS(BF23),0) -> -0.06941724 | BK23: =IFERROR((BE23-BG23)/ABS(BG23),0) -> -0.093564426 | BM23: =SUBTOTAL(9,BM21:BM22) -> -1714.1743 | BN23: =SUBTOTAL(9,BN21:BN22) -> -1962.025 | BO23: =SUBTOTAL(9,BO21:BO22) -> -2143.3672 | BP23: =BM23-BN23 -> 247.85072 | BQ23: =BM23-BO23 -> 429.19291 | BR23: =IFERROR((BM23-BN23)/ABS(BN23),0) -> 0.12632394 | BS23: =IFERROR((BM23-BO23)/ABS(BO23),0) -> 0.20024237 | BU23: =SUBTOTAL(9,BU21:BU22) -> -2018.7362 | BV23: =SUBTOTAL(9,BV21:BV22) -> -2018.7362 | BW23: =SUBTOTAL(9,BW21:BW22) -> -2018.7362 | BX23: =BU23-BV23 -> 0 | BY23: =BU23-BW23 -> 0 | BZ23: =IFERROR((BU23-BV23)/ABS(BV23),0) -> 0 | CA23: =IFERROR((BU23-BW23)/ABS(BW23),0) -> 0 | CC23: =SUBTOTAL(9,CC21:CC22) -> 6935.6611 | CD23: =SUBTOTAL(9,CD21:CD22) -> 6533.8591 | CE23: =SUBTOTAL(9,CE21:CE22) -> 5704.9546 | CF23: =CC23-CD23 -> 401.80197 | CG23: =CC23-CE23 -> 1230.7064 | CH23: =IFERROR((CC23-CD23)/ABS(CD23),0) -> 0.061495353 | CI23: =IFERROR((CC23-CE23)/ABS(CE23),0) -> 0.21572589 | CK23: =SUBTOTAL(9,CK21:CK22) -> -2150.4909 | CL23: =SUBTOTAL(9,CL21:CL22) -> -1832.5176 | CM23: =SUBTOTAL(9,CM21:CM22) -> -1831.1493 | CN23: =CK23-CL23 -> -317.97331 | CO23: =CK23-CM23 -> -319.34161 | CP23: =IFERROR((CK23-CL23)/ABS(CL23),0) -> -0.1735172 | CQ23: =IFERROR((CK23-CM23)/ABS(CM23),0) -> -0.17439409 | CS23: =SUBTOTAL(9,CS21:CS22) -> 4785.1702 | CT23: =SUBTOTAL(9,CT21:CT22) -> 4701.3415 | CU23: =SUBTOTAL(9,CU21:CU22) -> 3873.8054 | CV23: =SUBTOTAL(9,CV21:CV22) -> 83.82866 | CW23: =SUBTOTAL(9,CW21:CW22) -> 911.36483 | CX23: =IFERROR((CS23-CT23)/ABS(CT23),0) -> 0.017830796 | CY23: =IFERROR((CS23-CU23)/ABS(CU23),0) -> 0.23526345
B24: East | C24: Eastern - South | D24: 404 | E24: Al Hassa | F24: Super | G24: LFL | I24: =SUMIFS('P&L Data'!$N:$N,'P&L Data'!$B:$B,$D24,'P&L Data'!$C:$C,$I$4) -> 21390.412 | J24: =SUMIFS('P&L Data'!$P:$P,'P&L Data'!$B:$B,$D24,'P&L Data'!$C:$C,$I$4) -> 21643.454 | K24: =SUMIFS('P&L Data'!$T:$T,'P&L Data'!$B:$B,$D24,'P&L Data'!$C:$C,$I$4) -> 21883.537 | L24: =I24-J24 -> -253.0422 | M24: =I24-K24 -> -493.12506 | N24: =IFERROR((I24-J24)/ABS(J24),0) -> -0.011691396 | O24: =IFERROR((I24-K24)/ABS(K24),0) -> -0.022534065 | Q24: =SUMIFS('P&L Data'!$N:$N,'P&L Data'!$B:$B,$D24,'P&L Data'!$C:$C,$Q$4) -> 578.01322 | R24: =SUMIFS('P&L Data'!$P:$P,'P&L Data'!$B:$B,$D24,'P&L Data'!$C:$C,$Q$4) -> 691.35243 | S24: =SUMIFS('P&L Data'!$T:$T,'P&L Data'!$B:$B,$D24,'P&L Data'!$C:$C,$Q$4) -> 705.06066 | T24: =Q24-R24 -> -113.33921 | U24: =Q24-S24 -> -127.04744 | V24: =IFERROR((Q24-R24)/ABS(R24),0) -> -0.1639384 | W24: =IFERROR((Q24-S24)/ABS(S24),0) -> -0.18019363 | Y24: =SUMIFS('P&L Data'!$N:$N,'P&L Data'!$B:$B,$D24,'P&L Data'!$C:$C,$Y$4) -> 4927.2246 | Z24: =SUMIFS('P&L Data'!$P:$P,'P&L Data'!$B:$B,$D24,'P&L Data'!$C:$C,$Y$4) -> 4851.8079 | AA24: =SUMIFS('P&L Data'!$T:$T,'P&L Data'!$B:$B,$D24,'P&L Data'!$C:$C,$Y$4) -> 4618.2214 | AB24: =Y24-Z24 -> 75.41663 | AC24: =Y24-AA24 -> 309.0032 | AD24: =IFERROR((Y24-Z24)/ABS(Z24),0) -> 0.015544026 | AE24: =IFERROR((Y24-AA24)/ABS(AA24),0) -> 0.066909569 | AG24: =SUMIFS('P&L Data'!$N:$N,'P&L Data'!$B:$B,$D24,'P&L Data'!$C:$C,$AG$4) -> -54.85592 | AH24: =SUMIFS('P&L Data'!$P:$P,'P&L Data'!$B:$B,$D24,'P&L Data'!$C:$C,$AG$4) -> -134.18504 | AI24: =SUMIFS('P&L Data'!$T:$T,'P&L Data'!$B:$B,$D24,'P&L Data'!$C:$C,$AG$4) -> -101.24665 | AJ24: =AG24-AH24 -> 79.32912 | AK24: =AG24-AI24 -> 46.39073 | AL24: =IFERROR((AG24-AH24)/ABS(AH24),0) -> 0.59119198 | AM24: =IFERROR((AG24-AI24)/ABS(AI24),0) -> 0.45819521 | AO24: =SUMIFS('P&L Data'!$N:$N,'P&L Data'!$B:$B,$D24,'P&L Data'!$C:$C,$AO$4) -> -386.05073 | AP24: =SUMIFS('P&L Data'!$P:$P,'P&L Data'!$B:$B,$D24,'P&L Data'!$C:$C,$AO$4) -> -408.86965 | AQ24: =SUMIFS('P&L Data'!$T:$T,'P&L Data'!$B:$B,$D24,'P&L Data'!$C:$C,$AO$4) -> -360.00399 | AR24: =AO24-AP24 -> 22.81892 | AS24: =AO24-AQ24 -> -26.04674 | AT24: =IFERROR((AO24-AP24)/ABS(AP24),0) -> 0.055809767 | AU24: =IFERROR((AO24-AQ24)/ABS(AQ24),0) -> -0.072351254 | AW24: =SUMIFS('P&L Data'!$N:$N,'P&L Data'!$B:$B,$D24,'P&L Data'!$C:$C,$AW$4) -> 4486.3179 | AX24: =SUMIFS('P&L Data'!$P:$P,'P&L Data'!$B:$B,$D24,'P&L Data'!$C:$C,$AW$4) -> 4308.7532 | AY24: =SUMIFS('P&L Data'!$T:$T,'P&L Data'!$B:$B,$D24,'P&L Data'!$C:$C,$AW$4) -> 4156.9707 | AZ24: =AW24-AX24 -> 177.56467 | BA24: =AW24-AY24 -> 329.34719 | BB24: =IFERROR((AW24-AX24)/ABS(AX24),0) -> 0.04121022 | BC24: =IFERROR((AW24-AY24)/ABS(AY24),0) -> 0.079227691 | BE24: =SUMIFS('P&L Data'!$N:$N,'P&L Data'!$B:$B,$D24,'P&L Data'!$C:$C,$BE$4) -> -1590.5576 | BF24: =SUMIFS('P&L Data'!$P:$P,'P&L Data'!$B:$B,$D24,'P&L Data'!$C:$C,$BE$4) -> -1573.3537 | BG24: =SUMIFS('P&L Data'!$T:$T,'P&L Data'!$B:$B,$D24,'P&L Data'!$C:$C,$BE$4) -> -1526.9219 | BH24: =BE24-BF24 -> -17.20385 | BI24: =BE24-BG24 -> -63.6357 | BJ24: =IFERROR((BE24-BF24)/ABS(BF24),0) -> -0.010934509 | BK24: =IFERROR((BE24-BG24)/ABS(BG24),0) -> -0.041675807 | BM24: =SUMIFS('P&L Data'!$N:$N,'P&L Data'!$B:$B,$D24,'P&L Data'!$C:$C,$BM$4) -> -340.97274 | BN24: =SUMIFS('P&L Data'!$P:$P,'P&L Data'!$B:$B,$D24,'P&L Data'!$C:$C,$BM$4) -> -349.03118 | BO24: =SUMIFS('P&L Data'!$T:$T,'P&L Data'!$B:$B,$D24,'P&L Data'!$C:$C,$BM$4) -> -476.94569 | BP24: =BM24-BN24 -> 8.05844 | BQ24: =BM24-BO24 -> 135.97295 | BR24: =IFERROR((BM24-BN24)/ABS(BN24),0) -> 0.023088023 | BS24: =IFERROR((BM24-BO24)/ABS(BO24),0) -> 0.28509106 | BU24: =SUMIFS('P&L Data'!$N:$N,'P&L Data'!$B:$B,$D24,'P&L Data'!$C:$C,$BU$4) -> -514.64312 | BV24: =SUMIFS('P&L Data'!$P:$P,'P&L Data'!$B:$B,$D24,'P&L Data'!$C:$C,$BU$4) -> -514.64312 | BW24: =SUMIFS('P&L Data'!$T:$T,'P&L Data'!$B:$B,$D24,'P&L Data'!$C:$C,$BU$4) -> -476.95376 | BX24: =BU24-BV24 -> 0 | BY24: =BU24-BW24 -> -37.68936 | BZ24: =IFERROR((BU24-BV24)/ABS(BV24),0) -> 0 | CA24: =IFERROR((BU24-BW24)/ABS(BW24),0) -> -0.079020994 | CC24: =SUMIFS('P&L Data'!$N:$N,'P&L Data'!$B:$B,$D24,'P&L Data'!$C:$C,$CC$4) -> 2040.1445 | CD24: =SUMIFS('P&L Data'!$P:$P,'P&L Data'!$B:$B,$D24,'P&L Data'!$C:$C,$CC$4) -> 1871.7252 | CE24: =SUMIFS('P&L Data'!$T:$T,'P&L Data'!$B:$B,$D24,'P&L Data'!$C:$C,$CC$4) -> 1676.1494 | CF24: =CC24-CD24 -> 168.41926 | CG24: =CC24-CE24 -> 363.99508 | CH24: =IFERROR((CC24-CD24)/ABS(CD24),0) -> 0.089980761 | CI24: =IFERROR((CC24-CE24)/ABS(CE24),0) -> 0.21716148 | CK24: =SUMIFS('P&L Data'!$N:$N,'P&L Data'!$B:$B,$D24,'P&L Data'!$C:$C,$CK$4) -> -559.94048 | CL24: =SUMIFS('P&L Data'!$P:$P,'P&L Data'!$B:$B,$D24,'P&L Data'!$C:$C,$CK$4) -> -498.15164 | CM24: =SUMIFS('P&L Data'!$T:$T,'P&L Data'!$B:$B,$D24,'P&L Data'!$C:$C,$CK$4) -> -532.90943 | CN24: =CK24-CL24 -> -61.78884 | CO24: =CK24-CM24 -> -27.03105 | CP24: =IFERROR((CK24-CL24)/ABS(CL24),0) -> -0.12403621 | CQ24: =IFERROR((CK24-CM24)/ABS(CM24),0) -> -0.050723535 | CS24: =SUMIFS('P&L Data'!$N:$N,'P&L Data'!$B:$B,$D24,'P&L Data'!$C:$C,$CS$4) -> 1480.204 | CT24: =SUMIFS('P&L Data'!$P:$P,'P&L Data'!$B:$B,$D24,'P&L Data'!$C:$C,$CS$4) -> 1373.5736 | CU24: =SUMIFS('P&L Data'!$T:$T,'P&L Data'!$B:$B,$D24,'P&L Data'!$C:$C,$CS$4) -> 1143.24 | CV24: =CS24-CT24 -> 106.63042 | CW24: =CS24-CU24 -> 336.96403 | CX24: =IFERROR((CS24-CT24)/ABS(CT24),0) -> 0.077629929 | CY24: =IFERROR((CS24-CU24)/ABS(CU24),0) -> 0.29474479
B25: East | C25: Eastern - South | D25: 40005 | E25: King Saud | F25: Hyper | G25: LFL | I25: =SUMIFS('P&L Data'!$N:$N,'P&L Data'!$B:$B,$D25,'P&L Data'!$C:$C,$I$4) -> 25551.634 | J25: =SUMIFS('P&L Data'!$P:$P,'P&L Data'!$B:$B,$D25,'P&L Data'!$C:$C,$I$4) -> 25904.944 | K25: =SUMIFS('P&L Data'!$T:$T,'P&L Data'!$B:$B,$D25,'P&L Data'!$C:$C,$I$4) -> 23845.285 | L25: =I25-J25 -> -353.31008 | M25: =I25-K25 -> 1706.3485 | N25: =IFERROR((I25-J25)/ABS(J25),0) -> -0.013638712 | O25: =IFERROR((I25-K25)/ABS(K25),0) -> 0.071559156 | Q25: =SUMIFS('P&L Data'!$N:$N,'P&L Data'!$B:$B,$D25,'P&L Data'!$C:$C,$Q$4) -> 1567.232 | R25: =SUMIFS('P&L Data'!$P:$P,'P&L Data'!$B:$B,$D25,'P&L Data'!$C:$C,$Q$4) -> 1680.1125 | S25: =SUMIFS('P&L Data'!$T:$T,'P&L Data'!$B:$B,$D25,'P&L Data'!$C:$C,$Q$4) -> 1799.6773 | T25: =Q25-R25 -> -112.88053 | U25: =Q25-S25 -> -232.4453 | V25: =IFERROR((Q25-R25)/ABS(R25),0) -> -0.067186292 | W25: =IFERROR((Q25-S25)/ABS(S25),0) -> -0.12915943 | Y25: =SUMIFS('P&L Data'!$N:$N,'P&L Data'!$B:$B,$D25,'P&L Data'!$C:$C,$Y$4) -> 6523.7809 | Z25: =SUMIFS('P&L Data'!$P:$P,'P&L Data'!$B:$B,$D25,'P&L Data'!$C:$C,$Y$4) -> 6450.4269 | AA25: =SUMIFS('P&L Data'!$T:$T,'P&L Data'!$B:$B,$D25,'P&L Data'!$C:$C,$Y$4) -> 5885.4744 | AB25: =Y25-Z25 -> 73.35399 | AC25: =Y25-AA25 -> 638.30648 | AD25: =IFERROR((Y25-Z25)/ABS(Z25),0) -> 0.011371959 | AE25: =IFERROR((Y25-AA25)/ABS(AA25),0) -> 0.10845455 | AG25: =SUMIFS('P&L Data'!$N:$N,'P&L Data'!$B:$B,$D25,'P&L Data'!$C:$C,$AG$4) -> -6.53805 | AH25: =SUMIFS('P&L Data'!$P:$P,'P&L Data'!$B:$B,$D25,'P&L Data'!$C:$C,$AG$4) -> -152.26749 | AI25: =SUMIFS('P&L Data'!$T:$T,'P&L Data'!$B:$B,$D25,'P&L Data'!$C:$C,$AG$4) -> -96.74463 | AJ25: =AG25-AH25 -> 145.72944 | AK25: =AG25-AI25 -> 90.20658 | AL25: =IFERROR((AG25-AH25)/ABS(AH25),0) -> 0.95706208 | AM25: =IFERROR((AG25-AI25)/ABS(AI25),0) -> 0.9324195 | AO25: =SUMIFS('P&L Data'!$N:$N,'P&L Data'!$B:$B,$D25,'P&L Data'!$C:$C,$AO$4) -> -441.20679 | AP25: =SUMIFS('P&L Data'!$P:$P,'P&L Data'!$B:$B,$D25,'P&L Data'!$C:$C,$AO$4) -> -475.18953 | AQ25: =SUMIFS('P&L Data'!$T:$T,'P&L Data'!$B:$B,$D25,'P&L Data'!$C:$C,$AO$4) -> -374.33716 | AR25: =AO25-AP25 -> 33.98274 | AS25: =AO25-AQ25 -> -66.86963 | AT25: =IFERROR((AO25-AP25)/ABS(AP25),0) -> 0.071514076 | AU25: =IFERROR((AO25-AQ25)/ABS(AQ25),0) -> -0.17863476 | AW25: =SUMIFS('P&L Data'!$N:$N,'P&L Data'!$B:$B,$D25,'P&L Data'!$C:$C,$AW$4) -> 6076.036 | AX25: =SUMIFS('P&L Data'!$P:$P,'P&L Data'!$B:$B,$D25,'P&L Data'!$C:$C,$AW$4) -> 5822.9698 | AY25: =SUMIFS('P&L Data'!$T:$T,'P&L Data'!$B:$B,$D25,'P&L Data'!$C:$C,$AW$4) -> 5414.3926 | AZ25: =AW25-AX25 -> 253.06617 | BA25: =AW25-AY25 -> 661.64343 | BB25: =IFERROR((AW25-AX25)/ABS(AX25),0) -> 0.043459983 | BC25: =IFERROR((AW25-AY25)/ABS(AY25),0) -> 0.12220086 | BE25: =SUMIFS('P&L Data'!$N:$N,'P&L Data'!$B:$B,$D25,'P&L Data'!$C:$C,$BE$4) -> -1900.4149 | BF25: =SUMIFS('P&L Data'!$P:$P,'P&L Data'!$B:$B,$D25,'P&L Data'!$C:$C,$BE$4) -> -1832.4148 | BG25: =SUMIFS('P&L Data'!$T:$T,'P&L Data'!$B:$B,$D25,'P&L Data'!$C:$C,$BE$4) -> -1730.0783 | BH25: =BE25-BF25 -> -68.00009 | BI25: =BE25-BG25 -> -170.33656 | BJ25: =IFERROR((BE25-BF25)/ABS(BF25),0) -> -0.037109551 | BK25: =IFERROR((BE25-BG25)/ABS(BG25),0) -> -0.098455983 | BM25: =SUMIFS('P&L Data'!$N:$N,'P&L Data'!$B:$B,$D25,'P&L Data'!$C:$C,$BM$4) -> -607.73273 | BN25: =SUMIFS('P&L Data'!$P:$P,'P&L Data'!$B:$B,$D25,'P&L Data'!$C:$C,$BM$4) -> -598.77542 | BO25: =SUMIFS('P&L Data'!$T:$T,'P&L Data'!$B:$B,$D25,'P&L Data'!$C:$C,$BM$4) -> -717.42859 | BP25: =BM25-BN25 -> -8.95731 | BQ25: =BM25-BO25 -> 109.69586 | BR25: =IFERROR((BM25-BN25)/ABS(BN25),0) -> -0.014959382 | BS25: =IFERROR((BM25-BO25)/ABS(BO25),0) -> 0.15290143 | BU25: =SUMIFS('P&L Data'!$N:$N,'P&L Data'!$B:$B,$D25,'P&L Data'!$C:$C,$BU$4) -> -1706.9338 | BV25: =SUMIFS('P&L Data'!$P:$P,'P&L Data'!$B:$B,$D25,'P&L Data'!$C:$C,$BU$4) -> -1706.9338 | BW25: =SUMIFS('P&L Data'!$T:$T,'P&L Data'!$B:$B,$D25,'P&L Data'!$C:$C,$BU$4) -> -1706.9338 | BX25: =BU25-BV25 -> 0 | BY25: =BU25-BW25 -> 0 | BZ25: =IFERROR((BU25-BV25)/ABS(BV25),0) -> 0 | CA25: =IFERROR((BU25-BW25)/ABS(BW25),0) -> 0 | CC25: =SUMIFS('P&L Data'!$N:$N,'P&L Data'!$B:$B,$D25,'P&L Data'!$C:$C,$CC$4) -> 1860.9546 | CD25: =SUMIFS('P&L Data'!$P:$P,'P&L Data'!$B:$B,$D25,'P&L Data'!$C:$C,$CC$4) -> 1684.8458 | CE25: =SUMIFS('P&L Data'!$T:$T,'P&L Data'!$B:$B,$D25,'P&L Data'!$C:$C,$CC$4) -> 1259.9518 | CF25: =CC25-CD25 -> 176.10877 | CG25: =CC25-CE25 -> 601.00273 | CH25: =IFERROR((CC25-CD25)/ABS(CD25),0) -> 0.10452516 | CI25: =IFERROR((CC25-CE25)/ABS(CE25),0) -> 0.47700453 | CK25: =SUMIFS('P&L Data'!$N:$N,'P&L Data'!$B:$B,$D25,'P&L Data'!$C:$C,$CK$4) -> -788.64954 | CL25: =SUMIFS('P&L Data'!$P:$P,'P&L Data'!$B:$B,$D25,'P&L Data'!$C:$C,$CK$4) -> -622.83455 | CM25: =SUMIFS('P&L Data'!$T:$T,'P&L Data'!$B:$B,$D25,'P&L Data'!$C:$C,$CK$4) -> -708.42044 | CN25: =CK25-CL25 -> -165.81499 | CO25: =CK25-CM25 -> -80.2291 | CP25: =IFERROR((CK25-CL25)/ABS(CL25),0) -> -0.26622638 | CQ25: =IFERROR((CK25-CM25)/ABS(CM25),0) -> -0.11325068 | CS25: =SUMIFS('P&L Data'!$N:$N,'P&L Data'!$B:$B,$D25,'P&L Data'!$C:$C,$CS$4) -> 1072.305 | CT25: =SUMIFS('P&L Data'!$P:$P,'P&L Data'!$B:$B,$D25,'P&L Data'!$C:$C,$CS$4) -> 1062.0113 | CU25: =SUMIFS('P&L Data'!$T:$T,'P&L Data'!$B:$B,$D25,'P&L Data'!$C:$C,$CS$4) -> 551.5314 | CV25: =CS25-CT25 -> 10.29378 | CW25: =CS25-CU25 -> 520.77363 | CX25: =IFERROR((CS25-CT25)/ABS(CT25),0) -> 0.0096927222 | CY25: =IFERROR((CS25-CU25)/ABS(CU25),0) -> 0.94423207
B26: East | C26: Eastern - South Total | I26: =SUBTOTAL(9,I24:I25) -> 46942.046 | J26: =SUBTOTAL(9,J24:J25) -> 47548.398 | K26: =SUBTOTAL(9,K24:K25) -> 45728.823 | L26: =I26-J26 -> -606.35228 | M26: =I26-K26 -> 1213.2234 | N26: =IFERROR((I26-J26)/ABS(J26),0) -> -0.012752318 | O26: =IFERROR((I26-K26)/ABS(K26),0) -> 0.026530826 | Q26: =SUBTOTAL(9,Q24:Q25) -> 2145.2452 | R26: =SUBTOTAL(9,R24:R25) -> 2371.4649 | S26: =SUBTOTAL(9,S24:S25) -> 2504.7379 | T26: =Q26-R26 -> -226.21974 | U26: =Q26-S26 -> -359.49273 | V26: =IFERROR((Q26-R26)/ABS(R26),0) -> -0.095392403 | W26: =IFERROR((Q26-S26)/ABS(S26),0) -> -0.14352509 | Y26: =SUBTOTAL(9,Y24:Y25) -> 11451.005 | Z26: =SUBTOTAL(9,Z24:Z25) -> 11302.235 | AA26: =SUBTOTAL(9,AA24:AA25) -> 10503.696 | AB26: =Y26-Z26 -> 148.77062 | AC26: =Y26-AA26 -> 947.30969 | AD26: =IFERROR((Y26-Z26)/ABS(Z26),0) -> 0.013162938 | AE26: =IFERROR((Y26-AA26)/ABS(AA26),0) -> 0.090188226 | AG26: =SUBTOTAL(9,AG24:AG25) -> -61.39397 | AH26: =SUBTOTAL(9,AH24:AH25) -> -286.45253 | AI26: =SUBTOTAL(9,AI24:AI25) -> -197.99128 | AJ26: =AG26-AH26 -> 225.05856 | AK26: =AG26-AI26 -> 136.59731 | AL26: =IFERROR((AG26-AH26)/ABS(AH26),0) -> 0.78567489 | AM26: =IFERROR((AG26-AI26)/ABS(AI26),0) -> 0.68991579 | AO26: =SUBTOTAL(9,AO24:AO25) -> -827.25752 | AP26: =SUBTOTAL(9,AP24:AP25) -> -884.05918 | AQ26: =SUBTOTAL(9,AQ24:AQ25) -> -734.34115 | AR26: =AO26-AP26 -> 56.80166 | AS26: =AO26-AQ26 -> -92.91637 | AT26: =IFERROR((AO26-AP26)/ABS(AP26),0) -> 0.06425097 | AU26: =IFERROR((AO26-AQ26)/ABS(AQ26),0) -> -0.12653025 | AW26: =SUBTOTAL(9,AW24:AW25) -> 10562.354 | AX26: =SUBTOTAL(9,AX24:AX25) -> 10131.723 | AY26: =SUBTOTAL(9,AY24:AY25) -> 9571.3633 | AZ26: =AW26-AX26 -> 430.63084 | BA26: =AW26-AY26 -> 990.99063 | BB26: =IFERROR((AW26-AX26)/ABS(AX26),0) -> 0.042503219 | BC26: =IFERROR((AW26-AY26)/ABS(AY26),0) -> 0.10353704 | BE26: =SUBTOTAL(9,BE24:BE25) -> -3490.9724 | BF26: =SUBTOTAL(9,BF24:BF25) -> -3405.7685 | BG26: =SUBTOTAL(9,BG24:BG25) -> -3257.0002 | BH26: =BE26-BF26 -> -85.20394 | BI26: =BE26-BG26 -> -233.97226 | BJ26: =IFERROR((BE26-BF26)/ABS(BF26),0) -> -0.025017537 | BK26: =IFERROR((BE26-BG26)/ABS(BG26),0) -> -0.071836736 | BM26: =SUBTOTAL(9,BM24:BM25) -> -948.70547 | BN26: =SUBTOTAL(9,BN24:BN25) -> -947.8066 | BO26: =SUBTOTAL(9,BO24:BO25) -> -1194.3743 | BP26: =BM26-BN26 -> -0.89887 | BQ26: =BM26-BO26 -> 245.66881 | BR26: =IFERROR((BM26-BN26)/ABS(BN26),0) -> -0.00094836858 | BS26: =IFERROR((BM26-BO26)/ABS(BO26),0) -> 0.2056883 | BU26: =SUBTOTAL(9,BU24:BU25) -> -2221.577 | BV26: =SUBTOTAL(9,BV24:BV25) -> -2221.577 | BW26: =SUBTOTAL(9,BW24:BW25) -> -2183.8876 | BX26: =BU26-BV26 -> 0 | BY26: =BU26-BW26 -> -37.68936 | BZ26: =IFERROR((BU26-BV26)/ABS(BV26),0) -> 0 | CA26: =IFERROR((BU26-BW26)/ABS(BW26),0) -> -0.017257921 | CC26: =SUBTOTAL(9,CC24:CC25) -> 3901.0991 | CD26: =SUBTOTAL(9,CD24:CD25) -> 3556.571 | CE26: =SUBTOTAL(9,CE24:CE25) -> 2936.1012 | CF26: =CC26-CD26 -> 344.52803 | CG26: =CC26-CE26 -> 964.99782 | CH26: =IFERROR((CC26-CD26)/ABS(CD26),0) -> 0.096870842 | CI26: =IFERROR((CC26-CE26)/ABS(CE26),0) -> 0.3286664 | CK26: =SUBTOTAL(9,CK24:CK25) -> -1348.59 | CL26: =SUBTOTAL(9,CL24:CL25) -> -1120.9862 | CM26: =SUBTOTAL(9,CM24:CM25) -> -1241.3299 | CN26: =CK26-CL26 -> -227.60383 | CO26: =CK26-CM26 -> -107.26015 | CP26: =IFERROR((CK26-CL26)/ABS(CL26),0) -> -0.20303892 | CQ26: =IFERROR((CK26-CM26)/ABS(CM26),0) -> -0.086407451 | CS26: =SUBTOTAL(9,CS24:CS25) -> 2552.509 | CT26: =SUBTOTAL(9,CT24:CT25) -> 2435.5848 | CU26: =SUBTOTAL(9,CU24:CU25) -> 1694.7714 | CV26: =SUBTOTAL(9,CV24:CV25) -> 116.9242 | CW26: =SUBTOTAL(9,CW24:CW25) -> 857.73767 | CX26: =IFERROR((CS26-CT26)/ABS(CT26),0) -> 0.048006622 | CY26: =IFERROR((CS26-CU26)/ABS(CU26),0) -> 0.50610819
B27: East Total | I27: =SUBTOTAL(9,I18:I26) -> 148546.58 | J27: =SUBTOTAL(9,J18:J26) -> 148403.38 | K27: =SUBTOTAL(9,K18:K26) -> 141695.66 | L27: =I27-J27 -> 143.19914 | M27: =I27-K27 -> 6850.9204 | N27: =IFERROR((I27-J27)/ABS(J27),0) -> 0.00096493181 | O27: =IFERROR((I27-K27)/ABS(K27),0) -> 0.048349544 | Q27: =SUBTOTAL(9,Q18:Q26) -> 8720.3406 | R27: =SUBTOTAL(9,R18:R26) -> 9036.3999 | S27: =SUBTOTAL(9,S18:S26) -> 10592.447 | T27: =Q27-R27 -> -316.05935 | U27: =Q27-S27 -> -1872.1066 | V27: =IFERROR((Q27-R27)/ABS(R27),0) -> -0.034976246 | W27: =IFERROR((Q27-S27)/ABS(S27),0) -> -0.17673976 | Y27: =SUBTOTAL(9,Y18:Y26) -> 37736.952 | Z27: =SUBTOTAL(9,Z18:Z26) -> 37056.91 | AA27: =SUBTOTAL(9,AA18:AA26) -> 35747.59 | AB27: =Y27-Z27 -> 680.04229 | AC27: =Y27-AA27 -> 1989.3624 | AD27: =IFERROR((Y27-Z27)/ABS(Z27),0) -> 0.018351295 | AE27: =IFERROR((Y27-AA27)/ABS(AA27),0) -> 0.055650251 | AG27: =SUBTOTAL(9,AG18:AG26) -> -421.35126 | AH27: =SUBTOTAL(9,AH18:AH26) -> -904.66571 | AI27: =SUBTOTAL(9,AI18:AI26) -> -697.7999 | AJ27: =AG27-AH27 -> 483.31445 | AK27: =AG27-AI27 -> 276.44864 | AL27: =IFERROR((AG27-AH27)/ABS(AH27),0) -> 0.53424646 | AM27: =IFERROR((AG27-AI27)/ABS(AI27),0) -> 0.3961718 | AO27: =SUBTOTAL(9,AO18:AO26) -> -2646.037 | AP27: =SUBTOTAL(9,AP18:AP26) -> -2830.3705 | AQ27: =SUBTOTAL(9,AQ18:AQ26) -> -2351.2167 | AR27: =AO27-AP27 -> 184.33344 | AS27: =AO27-AQ27 -> -294.82033 | AT27: =IFERROR((AO27-AP27)/ABS(AP27),0) -> 0.065126965 | AU27: =IFERROR((AO27-AQ27)/ABS(AQ27),0) -> -0.12539054 | AW27: =SUBTOTAL(9,AW18:AW26) -> 34669.564 | AX27: =SUBTOTAL(9,AX18:AX26) -> 33321.874 | AY27: =SUBTOTAL(9,AY18:AY26) -> 32698.573 | AZ27: =AW27-AX27 -> 1347.6902 | BA27: =AW27-AY27 -> 1970.9907 | BB27: =IFERROR((AW27-AX27)/ABS(AX27),0) -> 0.04044461 | BC27: =IFERROR((AW27-AY27)/ABS(AY27),0) -> 0.060277574 | BE27: =SUBTOTAL(9,BE18:BE26) -> -10512.142 | BF27: =SUBTOTAL(9,BF18:BF26) -> -10293.461 | BG27: =SUBTOTAL(9,BG18:BG26) -> -10142.724 | BH27: =BE27-BF27 -> -218.68133 | BI27: =BE27-BG27 -> -369.41774 | BJ27: =IFERROR((BE27-BF27)/ABS(BF27),0) -> -0.021244685 | BK27: =IFERROR((BE27-BG27)/ABS(BG27),0) -> -0.036421944 | BM27: =SUBTOTAL(9,BM18:BM26) -> -3934.8786 | BN27: =SUBTOTAL(9,BN18:BN26) -> -4116.4691 | BO27: =SUBTOTAL(9,BO18:BO26) -> -4430.7094 | BP27: =BM27-BN27 -> 181.59049 | BQ27: =BM27-BO27 -> 495.83087 | BR27: =IFERROR((BM27-BN27)/ABS(BN27),0) -> 0.044113168 | BS27: =IFERROR((BM27-BO27)/ABS(BO27),0) -> 0.11190778 | BU27: =SUBTOTAL(9,BU18:BU26) -> -6508.2879 | BV27: =SUBTOTAL(9,BV18:BV26) -> -6505.6251 | BW27: =SUBTOTAL(9,BW18:BW26) -> -6443.3776 | BX27: =BU27-BV27 -> -2.66281 | BY27: =BU27-BW27 -> -64.91028 | BZ27: =IFERROR((BU27-BV27)/ABS(BV27),0) -> -0.00040930886 | CA27: =IFERROR((BU27-BW27)/ABS(BW27),0) -> -0.010073952 | CC27: =SUBTOTAL(9,CC18:CC26) -> 13714.255 | CD27: =SUBTOTAL(9,CD18:CD26) -> 12406.319 | CE27: =SUBTOTAL(9,CE18:CE26) -> 11681.762 | CF27: =CC27-CD27 -> 1307.9365 | CG27: =CC27-CE27 -> 2032.4935 | CH27: =IFERROR((CC27-CD27)/ABS(CD27),0) -> 0.10542503 | CI27: =IFERROR((CC27-CE27)/ABS(CE27),0) -> 0.17398861 | CK27: =SUBTOTAL(9,CK18:CK26) -> -4371.1565 | CL27: =SUBTOTAL(9,CL18:CL26) -> -3792.7346 | CM27: =SUBTOTAL(9,CM18:CM26) -> -3974.2024 | CN27: =CK27-CL27 -> -578.4219 | CO27: =CK27-CM27 -> -396.95411 | CP27: =IFERROR((CK27-CL27)/ABS(CL27),0) -> -0.15250788 | CQ27: =IFERROR((CK27-CM27)/ABS(CM27),0) -> -0.099882712 | CS27: =SUBTOTAL(9,CS18:CS26) -> 9343.0989 | CT27: =SUBTOTAL(9,CT18:CT26) -> 8613.5843 | CU27: =SUBTOTAL(9,CU18:CU26) -> 7707.5595 | CV27: =CS27-CT27 -> 729.51463 | CW27: =CS27-CU27 -> 1635.5394 | CX27: =IFERROR((CS27-CT27)/ABS(CT27),0) -> 0.084693503 | CY27: =IFERROR((CS27-CU27)/ABS(CU27),0) -> 0.21219939
B28: South | C28: South | D28: 701 | E28: Abha | F28: Super | G28: LFL | I28: =SUMIFS('P&L Data'!$N:$N,'P&L Data'!$B:$B,$D28,'P&L Data'!$C:$C,$I$4) -> 14170.928 | J28: =SUMIFS('P&L Data'!$P:$P,'P&L Data'!$B:$B,$D28,'P&L Data'!$C:$C,$I$4) -> 19805.617 | K28: =SUMIFS('P&L Data'!$T:$T,'P&L Data'!$B:$B,$D28,'P&L Data'!$C:$C,$I$4) -> 17945.083 | L28: =I28-J28 -> -5634.6888 | M28: =I28-K28 -> -3774.1551 | N28: =IFERROR((I28-J28)/ABS(J28),0) -> -0.28449954 | O28: =IFERROR((I28-K28)/ABS(K28),0) -> -0.21031695 | Q28: =SUMIFS('P&L Data'!$N:$N,'P&L Data'!$B:$B,$D28,'P&L Data'!$C:$C,$Q$4) -> 596.61581 | R28: =SUMIFS('P&L Data'!$P:$P,'P&L Data'!$B:$B,$D28,'P&L Data'!$C:$C,$Q$4) -> 1072.3038 | S28: =SUMIFS('P&L Data'!$T:$T,'P&L Data'!$B:$B,$D28,'P&L Data'!$C:$C,$Q$4) -> 822.5195 | T28: =Q28-R28 -> -475.68796 | U28: =Q28-S28 -> -225.90369 | V28: =IFERROR((Q28-R28)/ABS(R28),0) -> -0.44361306 | W28: =IFERROR((Q28-S28)/ABS(S28),0) -> -0.27464843 | Y28: =SUMIFS('P&L Data'!$N:$N,'P&L Data'!$B:$B,$D28,'P&L Data'!$C:$C,$Y$4) -> 3472.9324 | Z28: =SUMIFS('P&L Data'!$P:$P,'P&L Data'!$B:$B,$D28,'P&L Data'!$C:$C,$Y$4) -> 4954.6699 | AA28: =SUMIFS('P&L Data'!$T:$T,'P&L Data'!$B:$B,$D28,'P&L Data'!$C:$C,$Y$4) -> 4163.4164 | AB28: =Y28-Z28 -> -1481.7374 | AC28: =Y28-AA28 -> -690.48394 | AD28: =IFERROR((Y28-Z28)/ABS(Z28),0) -> -0.29905876 | AE28: =IFERROR((Y28-AA28)/ABS(AA28),0) -> -0.16584552 | AG28: =SUMIFS('P&L Data'!$N:$N,'P&L Data'!$B:$B,$D28,'P&L Data'!$C:$C,$AG$4) -> -76.13469 | AH28: =SUMIFS('P&L Data'!$P:$P,'P&L Data'!$B:$B,$D28,'P&L Data'!$C:$C,$AG$4) -> -126.13234 | AI28: =SUMIFS('P&L Data'!$T:$T,'P&L Data'!$B:$B,$D28,'P&L Data'!$C:$C,$AG$4) -> -89.89684 | AJ28: =AG28-AH28 -> 49.99765 | AK28: =AG28-AI28 -> 13.76215 | AL28: =IFERROR((AG28-AH28)/ABS(AH28),0) -> 0.39639041 | AM28: =IFERROR((AG28-AI28)/ABS(AI28),0) -> 0.15308825 | AO28: =SUMIFS('P&L Data'!$N:$N,'P&L Data'!$B:$B,$D28,'P&L Data'!$C:$C,$AO$4) -> -237.96595 | AP28: =SUMIFS('P&L Data'!$P:$P,'P&L Data'!$B:$B,$D28,'P&L Data'!$C:$C,$AO$4) -> -352.91377 | AQ28: =SUMIFS('P&L Data'!$T:$T,'P&L Data'!$B:$B,$D28,'P&L Data'!$C:$C,$AO$4) -> -282.56409 | AR28: =AO28-AP28 -> 114.94782 | AS28: =AO28-AQ28 -> 44.59814 | AT28: =IFERROR((AO28-AP28)/ABS(AP28),0) -> 0.32571078 | AU28: =IFERROR((AO28-AQ28)/ABS(AQ28),0) -> 0.15783371 | AW28: =SUMIFS('P&L Data'!$N:$N,'P&L Data'!$B:$B,$D28,'P&L Data'!$C:$C,$AW$4) -> 3158.8318 | AX28: =SUMIFS('P&L Data'!$P:$P,'P&L Data'!$B:$B,$D28,'P&L Data'!$C:$C,$AW$4) -> 4475.6237 | AY28: =SUMIFS('P&L Data'!$T:$T,'P&L Data'!$B:$B,$D28,'P&L Data'!$C:$C,$AW$4) -> 3790.9554 | AZ28: =AW28-AX28 -> -1316.7919 | BA28: =AW28-AY28 -> -632.12365 | BB28: =IFERROR((AW28-AX28)/ABS(AX28),0) -> -0.29421417 | BC28: =IFERROR((AW28-AY28)/ABS(AY28),0) -> -0.16674521 | BE28: =SUMIFS('P&L Data'!$N:$N,'P&L Data'!$B:$B,$D28,'P&L Data'!$C:$C,$BE$4) -> -1075.128 | BF28: =SUMIFS('P&L Data'!$P:$P,'P&L Data'!$B:$B,$D28,'P&L Data'!$C:$C,$BE$4) -> -1238.4525 | BG28: =SUMIFS('P&L Data'!$T:$T,'P&L Data'!$B:$B,$D28,'P&L Data'!$C:$C,$BE$4) -> -1133.7307 | BH28: =BE28-BF28 -> 163.32453 | BI28: =BE28-BG28 -> 58.60269 | BJ28: =IFERROR((BE28-BF28)/ABS(BF28),0) -> 0.13187791 | BK28: =IFERROR((BE28-BG28)/ABS(BG28),0) -> 0.051690134 | BM28: =SUMIFS('P&L Data'!$N:$N,'P&L Data'!$B:$B,$D28,'P&L Data'!$C:$C,$BM$4) -> -388.63346 | BN28: =SUMIFS('P&L Data'!$P:$P,'P&L Data'!$B:$B,$D28,'P&L Data'!$C:$C,$BM$4) -> -546.80584 | BO28: =SUMIFS('P&L Data'!$T:$T,'P&L Data'!$B:$B,$D28,'P&L Data'!$C:$C,$BM$4) -> -479.22045 | BP28: =BM28-BN28 -> 158.17238 | BQ28: =BM28-BO28 -> 90.58699 | BR28: =IFERROR((BM28-BN28)/ABS(BN28),0) -> 0.28926608 | BS28: =IFERROR((BM28-BO28)/ABS(BO28),0) -> 0.18902989 | BU28: =SUMIFS('P&L Data'!$N:$N,'P&L Data'!$B:$B,$D28,'P&L Data'!$C:$C,$BU$4) -> -564.5952 | BV28: =SUMIFS('P&L Data'!$P:$P,'P&L Data'!$B:$B,$D28,'P&L Data'!$C:$C,$BU$4) -> -560.0052 | BW28: =SUMIFS('P&L Data'!$T:$T,'P&L Data'!$B:$B,$D28,'P&L Data'!$C:$C,$BU$4) -> -379.86 | BX28: =BU28-BV28 -> -4.59 | BY28: =BU28-BW28 -> -184.7352 | BZ28: =IFERROR((BU28-BV28)/ABS(BV28),0) -> -0.0081963525 | CA28: =IFERROR((BU28-BW28)/ABS(BW28),0) -> -0.48632444 | CC28: =SUMIFS('P&L Data'!$N:$N,'P&L Data'!$B:$B,$D28,'P&L Data'!$C:$C,$CC$4) -> 1130.4752 | CD28: =SUMIFS('P&L Data'!$P:$P,'P&L Data'!$B:$B,$D28,'P&L Data'!$C:$C,$CC$4) -> 2130.3602 | CE28: =SUMIFS('P&L Data'!$T:$T,'P&L Data'!$B:$B,$D28,'P&L Data'!$C:$C,$CC$4) -> 1798.1443 | CF28: =CC28-CD28 -> -999.88503 | CG28: =CC28-CE28 -> -667.66917 | CH28: =IFERROR((CC28-CD28)/ABS(CD28),0) -> -0.46935022 | CI28: =IFERROR((CC28-CE28)/ABS(CE28),0) -> -0.37131011 | CK28: =SUMIFS('P&L Data'!$N:$N,'P&L Data'!$B:$B,$D28,'P&L Data'!$C:$C,$CK$4) -> -327.24143 | CL28: =SUMIFS('P&L Data'!$P:$P,'P&L Data'!$B:$B,$D28,'P&L Data'!$C:$C,$CK$4) -> -650.14727 | CM28: =SUMIFS('P&L Data'!$T:$T,'P&L Data'!$B:$B,$D28,'P&L Data'!$C:$C,$CK$4) -> -205.16298 | CN28: =CK28-CL28 -> 322.90584 | CO28: =CK28-CM28 -> -122.07845 | CP28: =IFERROR((CK28-CL28)/ABS(CL28),0) -> 0.49666569 | CQ28: =IFERROR((CK28-CM28)/ABS(CM28),0) -> -0.59503157 | CS28: =SUMIFS('P&L Data'!$N:$N,'P&L Data'!$B:$B,$D28,'P&L Data'!$C:$C,$CS$4) -> 803.23374 | CT28: =SUMIFS('P&L Data'!$P:$P,'P&L Data'!$B:$B,$D28,'P&L Data'!$C:$C,$CS$4) -> 1480.2129 | CU28: =SUMIFS('P&L Data'!$T:$T,'P&L Data'!$B:$B,$D28,'P&L Data'!$C:$C,$CS$4) -> 1592.9814 | CV28: =CS28-CT28 -> -676.97919 | CW28: =CS28-CU28 -> -789.74762 | CX28: =IFERROR((CS28-CT28)/ABS(CT28),0) -> -0.45735257 | CY28: =IFERROR((CS28-CU28)/ABS(CU28),0) -> -0.49576702
B29: South | C29: South | D29: 70001 | E29: Beishah | F29: Hyper | G29: LFL | I29: =SUMIFS('P&L Data'!$N:$N,'P&L Data'!$B:$B,$D29,'P&L Data'!$C:$C,$I$4) -> 34834.617 | J29: =SUMIFS('P&L Data'!$P:$P,'P&L Data'!$B:$B,$D29,'P&L Data'!$C:$C,$I$4) -> 33972.844 | K29: =SUMIFS('P&L Data'!$T:$T,'P&L Data'!$B:$B,$D29,'P&L Data'!$C:$C,$I$4) -> 33600.445 | L29: =I29-J29 -> 861.77258 | M29: =I29-K29 -> 1234.172 | N29: =IFERROR((I29-J29)/ABS(J29),0) -> 0.025366513 | O29: =IFERROR((I29-K29)/ABS(K29),0) -> 0.036730824 | Q29: =SUMIFS('P&L Data'!$N:$N,'P&L Data'!$B:$B,$D29,'P&L Data'!$C:$C,$Q$4) -> 685.96074 | R29: =SUMIFS('P&L Data'!$P:$P,'P&L Data'!$B:$B,$D29,'P&L Data'!$C:$C,$Q$4) -> 1368.9915 | S29: =SUMIFS('P&L Data'!$T:$T,'P&L Data'!$B:$B,$D29,'P&L Data'!$C:$C,$Q$4) -> 1708.6027 | T29: =Q29-R29 -> -683.03074 | U29: =Q29-S29 -> -1022.642 | V29: =IFERROR((Q29-R29)/ABS(R29),0) -> -0.49892987 | W29: =IFERROR((Q29-S29)/ABS(S29),0) -> -0.59852532 | Y29: =SUMIFS('P&L Data'!$N:$N,'P&L Data'!$B:$B,$D29,'P&L Data'!$C:$C,$Y$4) -> 7914.8957 | Z29: =SUMIFS('P&L Data'!$P:$P,'P&L Data'!$B:$B,$D29,'P&L Data'!$C:$C,$Y$4) -> 8256.565 | AA29: =SUMIFS('P&L Data'!$T:$T,'P&L Data'!$B:$B,$D29,'P&L Data'!$C:$C,$Y$4) -> 8209.6329 | AB29: =Y29-Z29 -> -341.66928 | AC29: =Y29-AA29 -> -294.73719 | AD29: =IFERROR((Y29-Z29)/ABS(Z29),0) -> -0.041381528 | AE29: =IFERROR((Y29-AA29)/ABS(AA29),0) -> -0.035901384 | AG29: =SUMIFS('P&L Data'!$N:$N,'P&L Data'!$B:$B,$D29,'P&L Data'!$C:$C,$AG$4) -> -106.51909 | AH29: =SUMIFS('P&L Data'!$P:$P,'P&L Data'!$B:$B,$D29,'P&L Data'!$C:$C,$AG$4) -> -223.78103 | AI29: =SUMIFS('P&L Data'!$T:$T,'P&L Data'!$B:$B,$D29,'P&L Data'!$C:$C,$AG$4) -> -186.46278 | AJ29: =AG29-AH29 -> 117.26194 | AK29: =AG29-AI29 -> 79.94369 | AL29: =IFERROR((AG29-AH29)/ABS(AH29),0) -> 0.52400304 | AM29: =IFERROR((AG29-AI29)/ABS(AI29),0) -> 0.42873806 | AO29: =SUMIFS('P&L Data'!$N:$N,'P&L Data'!$B:$B,$D29,'P&L Data'!$C:$C,$AO$4) -> -553.34642 | AP29: =SUMIFS('P&L Data'!$P:$P,'P&L Data'!$B:$B,$D29,'P&L Data'!$C:$C,$AO$4) -> -600.40494 | AQ29: =SUMIFS('P&L Data'!$T:$T,'P&L Data'!$B:$B,$D29,'P&L Data'!$C:$C,$AO$4) -> -546.57516 | AR29: =AO29-AP29 -> 47.05852 | AS29: =AO29-AQ29 -> -6.77126 | AT29: =IFERROR((AO29-AP29)/ABS(AP29),0) -> 0.078377969 | AU29: =IFERROR((AO29-AQ29)/ABS(AQ29),0) -> -0.012388525 | AW29: =SUMIFS('P&L Data'!$N:$N,'P&L Data'!$B:$B,$D29,'P&L Data'!$C:$C,$AW$4) -> 7255.0302 | AX29: =SUMIFS('P&L Data'!$P:$P,'P&L Data'!$B:$B,$D29,'P&L Data'!$C:$C,$AW$4) -> 7432.3791 | AY29: =SUMIFS('P&L Data'!$T:$T,'P&L Data'!$B:$B,$D29,'P&L Data'!$C:$C,$AW$4) -> 7476.595 | AZ29: =AW29-AX29 -> -177.34882 | BA29: =AW29-AY29 -> -221.56476 | BB29: =IFERROR((AW29-AX29)/ABS(AX29),0) -> -0.023861649 | BC29: =IFERROR((AW29-AY29)/ABS(AY29),0) -> -0.029634447 | BE29: =SUMIFS('P&L Data'!$N:$N,'P&L Data'!$B:$B,$D29,'P&L Data'!$C:$C,$BE$4) -> -1696.0323 | BF29: =SUMIFS('P&L Data'!$P:$P,'P&L Data'!$B:$B,$D29,'P&L Data'!$C:$C,$BE$4) -> -1775.7628 | BG29: =SUMIFS('P&L Data'!$T:$T,'P&L Data'!$B:$B,$D29,'P&L Data'!$C:$C,$BE$4) -> -1744.7105 | BH29: =BE29-BF29 -> 79.73052 | BI29: =BE29-BG29 -> 48.6782 | BJ29: =IFERROR((BE29-BF29)/ABS(BF29),0) -> 0.044899308 | BK29: =IFERROR((BE29-BG29)/ABS(BG29),0) -> 0.027900446 | BM29: =SUMIFS('P&L Data'!$N:$N,'P&L Data'!$B:$B,$D29,'P&L Data'!$C:$C,$BM$4) -> -617.72527 | BN29: =SUMIFS('P&L Data'!$P:$P,'P&L Data'!$B:$B,$D29,'P&L Data'!$C:$C,$BM$4) -> -571.97031 | BO29: =SUMIFS('P&L Data'!$T:$T,'P&L Data'!$B:$B,$D29,'P&L Data'!$C:$C,$BM$4) -> -275.45606 | BP29: =BM29-BN29 -> -45.75496 | BQ29: =BM29-BO29 -> -342.26921 | BR29: =IFERROR((BM29-BN29)/ABS(BN29),0) -> -0.079995341 | BS29: =IFERROR((BM29-BO29)/ABS(BO29),0) -> -1.2425547 | BU29: =SUMIFS('P&L Data'!$N:$N,'P&L Data'!$B:$B,$D29,'P&L Data'!$C:$C,$BU$4) -> -910.39049 | BV29: =SUMIFS('P&L Data'!$P:$P,'P&L Data'!$B:$B,$D29,'P&L Data'!$C:$C,$BU$4) -> -887.47047 | BW29: =SUMIFS('P&L Data'!$T:$T,'P&L Data'!$B:$B,$D29,'P&L Data'!$C:$C,$BU$4) -> -855.96045 | BX29: =BU29-BV29 -> -22.92002 | BY29: =BU29-BW29 -> -54.43004 | BZ29: =IFERROR((BU29-BV29)/ABS(BV29),0) -> -0.025826234 | CA29: =IFERROR((BU29-BW29)/ABS(BW29),0) -> -0.063589433 | CC29: =SUMIFS('P&L Data'!$N:$N,'P&L Data'!$B:$B,$D29,'P&L Data'!$C:$C,$CC$4) -> 4030.8822 | CD29: =SUMIFS('P&L Data'!$P:$P,'P&L Data'!$B:$B,$D29,'P&L Data'!$C:$C,$CC$4) -> 4197.1755 | CE29: =SUMIFS('P&L Data'!$T:$T,'P&L Data'!$B:$B,$D29,'P&L Data'!$C:$C,$CC$4) -> 4600.468 | CF29: =CC29-CD29 -> -166.29328 | CG29: =CC29-CE29 -> -569.58581 | CH29: =IFERROR((CC29-CD29)/ABS(CD29),0) -> -0.039620283 | CI29: =IFERROR((CC29-CE29)/ABS(CE29),0) -> -0.1238104 | CK29: =SUMIFS('P&L Data'!$N:$N,'P&L Data'!$B:$B,$D29,'P&L Data'!$C:$C,$CK$4) -> -267.48011 | CL29: =SUMIFS('P&L Data'!$P:$P,'P&L Data'!$B:$B,$D29,'P&L Data'!$C:$C,$CK$4) -> -331.81886 | CM29: =SUMIFS('P&L Data'!$T:$T,'P&L Data'!$B:$B,$D29,'P&L Data'!$C:$C,$CK$4) -> -295.98122 | CN29: =CK29-CL29 -> 64.33875 | CO29: =CK29-CM29 -> 28.50111 | CP29: =IFERROR((CK29-CL29)/ABS(CL29),0) -> 0.19389721 | CQ29: =IFERROR((CK29-CM29)/ABS(CM29),0) -> 0.096293643 | CS29: =SUMIFS('P&L Data'!$N:$N,'P&L Data'!$B:$B,$D29,'P&L Data'!$C:$C,$CS$4) -> 3763.4021 | CT29: =SUMIFS('P&L Data'!$P:$P,'P&L Data'!$B:$B,$D29,'P&L Data'!$C:$C,$CS$4) -> 3865.3566 | CU29: =SUMIFS('P&L Data'!$T:$T,'P&L Data'!$B:$B,$D29,'P&L Data'!$C:$C,$CS$4) -> 4304.4868 | CV29: =CS29-CT29 -> -101.95453 | CW29: =CS29-CU29 -> -541.0847 | CX29: =IFERROR((CS29-CT29)/ABS(CT29),0) -> -0.026376487 | CY29: =IFERROR((CS29-CU29)/ABS(CU29),0) -> -0.12570249
B30: South | C30: South Total | I30: =SUBTOTAL(9,I28:I29) -> 49005.545 | J30: =SUBTOTAL(9,J28:J29) -> 53778.461 | K30: =SUBTOTAL(9,K28:K29) -> 51545.528 | L30: =I30-J30 -> -4772.9162 | M30: =I30-K30 -> -2539.9831 | N30: =IFERROR((I30-J30)/ABS(J30),0) -> -0.088751447 | O30: =IFERROR((I30-K30)/ABS(K30),0) -> -0.049276498 | Q30: =SUBTOTAL(9,Q28:Q29) -> 1282.5766 | R30: =SUBTOTAL(9,R28:R29) -> 2441.2952 | S30: =SUBTOTAL(9,S28:S29) -> 2531.1222 | T30: =Q30-R30 -> -1158.7187 | U30: =Q30-S30 -> -1248.5457 | V30: =IFERROR((Q30-R30)/ABS(R30),0) -> -0.47463276 | W30: =IFERROR((Q30-S30)/ABS(S30),0) -> -0.49327751 | Y30: =SUBTOTAL(9,Y28:Y29) -> 11387.828 | Z30: =SUBTOTAL(9,Z28:Z29) -> 13211.235 | AA30: =SUBTOTAL(9,AA28:AA29) -> 12373.049 | AB30: =Y30-Z30 -> -1823.4067 | AC30: =Y30-AA30 -> -985.22113 | AD30: =IFERROR((Y30-Z30)/ABS(Z30),0) -> -0.1380194 | AE30: =IFERROR((Y30-AA30)/ABS(AA30),0) -> -0.07962638 | AG30: =SUBTOTAL(9,AG28:AG29) -> -182.65378 | AH30: =SUBTOTAL(9,AH28:AH29) -> -349.91337 | AI30: =SUBTOTAL(9,AI28:AI29) -> -276.35962 | AJ30: =AG30-AH30 -> 167.25959 | AK30: =AG30-AI30 -> 93.70584 | AL30: =IFERROR((AG30-AH30)/ABS(AH30),0) -> 0.47800286 | AM30: =IFERROR((AG30-AI30)/ABS(AI30),0) -> 0.33907211 | AO30: =SUBTOTAL(9,AO28:AO29) -> -791.31237 | AP30: =SUBTOTAL(9,AP28:AP29) -> -953.31871 | AQ30: =SUBTOTAL(9,AQ28:AQ29) -> -829.13925 | AR30: =AO30-AP30 -> 162.00634 | AS30: =AO30-AQ30 -> 37.82688 | AT30: =IFERROR((AO30-AP30)/ABS(AP30),0) -> 0.16993933 | AU30: =IFERROR((AO30-AQ30)/ABS(AQ30),0) -> 0.045621866 | AW30: =SUBTOTAL(9,AW28:AW29) -> 10413.862 | AX30: =SUBTOTAL(9,AX28:AX29) -> 11908.003 | AY30: =SUBTOTAL(9,AY28:AY29) -> 11267.55 | AZ30: =AW30-AX30 -> -1494.1408 | BA30: =AW30-AY30 -> -853.68841 | BB30: =IFERROR((AW30-AX30)/ABS(AX30),0) -> -0.12547367 | BC30: =IFERROR((AW30-AY30)/ABS(AY30),0) -> -0.075765217 | BE30: =SUBTOTAL(9,BE28:BE29) -> -2771.1602 | BF30: =SUBTOTAL(9,BF28:BF29) -> -3014.2153 | BG30: =SUBTOTAL(9,BG28:BG29) -> -2878.4411 | BH30: =BE30-BF30 -> 243.05505 | BI30: =BE30-BG30 -> 107.28089 | BJ30: =IFERROR((BE30-BF30)/ABS(BF30),0) -> 0.080636261 | BK30: =IFERROR((BE30-BG30)/ABS(BG30),0) -> 0.037270483 | BM30: =SUBTOTAL(9,BM28:BM29) -> -1006.3587 | BN30: =SUBTOTAL(9,BN28:BN29) -> -1118.7762 | BO30: =SUBTOTAL(9,BO28:BO29) -> -754.67651 | BP30: =BM30-BN30 -> 112.41742 | BQ30: =BM30-BO30 -> -251.68222 | BR30: =IFERROR((BM30-BN30)/ABS(BN30),0) -> 0.1004825 | BS30: =IFERROR((BM30-BO30)/ABS(BO30),0) -> -0.33349683 | BU30: =SUBTOTAL(9,BU28:BU29) -> -1474.9857 | BV30: =SUBTOTAL(9,BV28:BV29) -> -1447.4757 | BW30: =SUBTOTAL(9,BW28:BW29) -> -1235.8205 | BX30: =BU30-BV30 -> -27.51002 | BY30: =BU30-BW30 -> -239.16524 | BZ30: =IFERROR((BU30-BV30)/ABS(BV30),0) -> -0.019005515 | CA30: =IFERROR((BU30-BW30)/ABS(BW30),0) -> -0.1935275 | CC30: =SUBTOTAL(9,CC28:CC29) -> 5161.3574 | CD30: =SUBTOTAL(9,CD28:CD29) -> 6327.5357 | CE30: =SUBTOTAL(9,CE28:CE29) -> 6398.6124 | CF30: =CC30-CD30 -> -1166.1783 | CG30: =CC30-CE30 -> -1237.255 | CH30: =IFERROR((CC30-CD30)/ABS(CD30),0) -> -0.18430213 | CI30: =IFERROR((CC30-CE30)/ABS(CE30),0) -> -0.19336301 | CK30: =SUBTOTAL(9,CK28:CK29) -> -594.72154 | CL30: =SUBTOTAL(9,CL28:CL29) -> -981.96613 | CM30: =SUBTOTAL(9,CM28:CM29) -> -501.1442 | CN30: =CK30-CL30 -> 387.24459 | CO30: =CK30-CM30 -> -93.57734 | CP30: =IFERROR((CK30-CL30)/ABS(CL30),0) -> 0.39435636 | CQ30: =IFERROR((CK30-CM30)/ABS(CM30),0) -> -0.18672737 | CS30: =SUBTOTAL(9,CS28:CS29) -> 4566.6358 | CT30: =SUBTOTAL(9,CT28:CT29) -> 5345.5696 | CU30: =SUBTOTAL(9,CU28:CU29) -> 5897.4682 | CV30: =SUBTOTAL(9,CV28:CV29) -> -778.93372 | CW30: =SUBTOTAL(9,CW28:CW29) -> -1330.8323 | CX30: =IFERROR((CS30-CT30)/ABS(CT30),0) -> -0.14571576 | CY30: =IFERROR((CS30-CU30)/ABS(CU30),0) -> -0.22566164
B31: South Total | I31: =SUBTOTAL(9,I28:I30) -> 49005.545 | J31: =SUBTOTAL(9,J28:J30) -> 53778.461 | K31: =SUBTOTAL(9,K28:K30) -> 51545.528 | L31: =I31-J31 -> -4772.9162 | M31: =I31-K31 -> -2539.9831 | N31: =IFERROR((I31-J31)/ABS(J31),0) -> -0.088751447 | O31: =IFERROR((I31-K31)/ABS(K31),0) -> -0.049276498 | Q31: =SUBTOTAL(9,Q28:Q30) -> 1282.5766 | R31: =SUBTOTAL(9,R28:R30) -> 2441.2952 | S31: =SUBTOTAL(9,S28:S30) -> 2531.1222 | T31: =Q31-R31 -> -1158.7187 | U31: =Q31-S31 -> -1248.5457 | V31: =IFERROR((Q31-R31)/ABS(R31),0) -> -0.47463276 | W31: =IFERROR((Q31-S31)/ABS(S31),0) -> -0.49327751 | Y31: =SUBTOTAL(9,Y28:Y30) -> 11387.828 | Z31: =SUBTOTAL(9,Z28:Z30) -> 13211.235 | AA31: =SUBTOTAL(9,AA28:AA30) -> 12373.049 | AB31: =Y31-Z31 -> -1823.4067 | AC31: =Y31-AA31 -> -985.22113 | AD31: =IFERROR((Y31-Z31)/ABS(Z31),0) -> -0.1380194 | AE31: =IFERROR((Y31-AA31)/ABS(AA31),0) -> -0.07962638 | AG31: =SUBTOTAL(9,AG28:AG30) -> -182.65378 | AH31: =SUBTOTAL(9,AH28:AH30) -> -349.91337 | AI31: =SUBTOTAL(9,AI28:AI30) -> -276.35962 | AJ31: =AG31-AH31 -> 167.25959 | AK31: =AG31-AI31 -> 93.70584 | AL31: =IFERROR((AG31-AH31)/ABS(AH31),0) -> 0.47800286 | AM31: =IFERROR((AG31-AI31)/ABS(AI31),0) -> 0.33907211 | AO31: =SUBTOTAL(9,AO28:AO30) -> -791.31237 | AP31: =SUBTOTAL(9,AP28:AP30) -> -953.31871 | AQ31: =SUBTOTAL(9,AQ28:AQ30) -> -829.13925 | AR31: =AO31-AP31 -> 162.00634 | AS31: =AO31-AQ31 -> 37.82688 | AT31: =IFERROR((AO31-AP31)/ABS(AP31),0) -> 0.16993933 | AU31: =IFERROR((AO31-AQ31)/ABS(AQ31),0) -> 0.045621866 | AW31: =SUBTOTAL(9,AW28:AW30) -> 10413.862 | AX31: =SUBTOTAL(9,AX28:AX30) -> 11908.003 | AY31: =SUBTOTAL(9,AY28:AY30) -> 11267.55 | AZ31: =AW31-AX31 -> -1494.1408 | BA31: =AW31-AY31 -> -853.68841 | BB31: =IFERROR((AW31-AX31)/ABS(AX31),0) -> -0.12547367 | BC31: =IFERROR((AW31-AY31)/ABS(AY31),0) -> -0.075765217 | BE31: =SUBTOTAL(9,BE28:BE30) -> -2771.1602 | BF31: =SUBTOTAL(9,BF28:BF30) -> -3014.2153 | BG31: =SUBTOTAL(9,BG28:BG30) -> -2878.4411 | BH31: =BE31-BF31 -> 243.05505 | BI31: =BE31-BG31 -> 107.28089 | BJ31: =IFERROR((BE31-BF31)/ABS(BF31),0) -> 0.080636261 | BK31: =IFERROR((BE31-BG31)/ABS(BG31),0) -> 0.037270483 | BM31: =SUBTOTAL(9,BM28:BM30) -> -1006.3587 | BN31: =SUBTOTAL(9,BN28:BN30) -> -1118.7762 | BO31: =SUBTOTAL(9,BO28:BO30) -> -754.67651 | BP31: =BM31-BN31 -> 112.41742 | BQ31: =BM31-BO31 -> -251.68222 | BR31: =IFERROR((BM31-BN31)/ABS(BN31),0) -> 0.1004825 | BS31: =IFERROR((BM31-BO31)/ABS(BO31),0) -> -0.33349683 | BU31: =SUBTOTAL(9,BU28:BU30) -> -1474.9857 | BV31: =SUBTOTAL(9,BV28:BV30) -> -1447.4757 | BW31: =SUBTOTAL(9,BW28:BW30) -> -1235.8205 | BX31: =BU31-BV31 -> -27.51002 | BY31: =BU31-BW31 -> -239.16524 | BZ31: =IFERROR((BU31-BV31)/ABS(BV31),0) -> -0.019005515 | CA31: =IFERROR((BU31-BW31)/ABS(BW31),0) -> -0.1935275 | CC31: =SUBTOTAL(9,CC28:CC30) -> 5161.3574 | CD31: =SUBTOTAL(9,CD28:CD30) -> 6327.5357 | CE31: =SUBTOTAL(9,CE28:CE30) -> 6398.6124 | CF31: =CC31-CD31 -> -1166.1783 | CG31: =CC31-CE31 -> -1237.255 | CH31: =IFERROR((CC31-CD31)/ABS(CD31),0) -> -0.18430213 | CI31: =IFERROR((CC31-CE31)/ABS(CE31),0) -> -0.19336301 | CK31: =SUBTOTAL(9,CK28:CK30) -> -594.72154 | CL31: =SUBTOTAL(9,CL28:CL30) -> -981.96613 | CM31: =SUBTOTAL(9,CM28:CM30) -> -501.1442 | CN31: =CK31-CL31 -> 387.24459 | CO31: =CK31-CM31 -> -93.57734 | CP31: =IFERROR((CK31-CL31)/ABS(CL31),0) -> 0.39435636 | CQ31: =IFERROR((CK31-CM31)/ABS(CM31),0) -> -0.18672737 | CS31: =SUBTOTAL(9,CS28:CS30) -> 4566.6358 | CT31: =SUBTOTAL(9,CT28:CT30) -> 5345.5696 | CU31: =SUBTOTAL(9,CU28:CU30) -> 5897.4682 | CV31: =CS31-CT31 -> -778.93372 | CW31: =CS31-CU31 -> -1330.8323 | CX31: =IFERROR((CS31-CT31)/ABS(CT31),0) -> -0.14571576 | CY31: =IFERROR((CS31-CU31)/ABS(CU31),0) -> -0.22566164
B32: West | C32: Western - Crescent | D32: 236 | E32: Hai Al Sammer | F32: Super | G32: LFL | I32: =SUMIFS('P&L Data'!$N:$N,'P&L Data'!$B:$B,$D32,'P&L Data'!$C:$C,$I$4) -> 26973.041 | J32: =SUMIFS('P&L Data'!$P:$P,'P&L Data'!$B:$B,$D32,'P&L Data'!$C:$C,$I$4) -> 28094.92 | K32: =SUMIFS('P&L Data'!$T:$T,'P&L Data'!$B:$B,$D32,'P&L Data'!$C:$C,$I$4) -> 29323.444 | L32: =I32-J32 -> -1121.8791 | M32: =I32-K32 -> -2350.4028 | N32: =IFERROR((I32-J32)/ABS(J32),0) -> -0.039931743 | O32: =IFERROR((I32-K32)/ABS(K32),0) -> -0.080154393 | Q32: =SUMIFS('P&L Data'!$N:$N,'P&L Data'!$B:$B,$D32,'P&L Data'!$C:$C,$Q$4) -> 2042.6262 | R32: =SUMIFS('P&L Data'!$P:$P,'P&L Data'!$B:$B,$D32,'P&L Data'!$C:$C,$Q$4) -> 1964.2787 | S32: =SUMIFS('P&L Data'!$T:$T,'P&L Data'!$B:$B,$D32,'P&L Data'!$C:$C,$Q$4) -> 2458.4745 | T32: =Q32-R32 -> 78.34756 | U32: =Q32-S32 -> -415.84827 | V32: =IFERROR((Q32-R32)/ABS(R32),0) -> 0.039886174 | W32: =IFERROR((Q32-S32)/ABS(S32),0) -> -0.16914891 | Y32: =SUMIFS('P&L Data'!$N:$N,'P&L Data'!$B:$B,$D32,'P&L Data'!$C:$C,$Y$4) -> 7298.6395 | Z32: =SUMIFS('P&L Data'!$P:$P,'P&L Data'!$B:$B,$D32,'P&L Data'!$C:$C,$Y$4) -> 7049.7738 | AA32: =SUMIFS('P&L Data'!$T:$T,'P&L Data'!$B:$B,$D32,'P&L Data'!$C:$C,$Y$4) -> 7215.7537 | AB32: =Y32-Z32 -> 248.86566 | AC32: =Y32-AA32 -> 82.885813 | AD32: =IFERROR((Y32-Z32)/ABS(Z32),0) -> 0.035301226 | AE32: =IFERROR((Y32-AA32)/ABS(AA32),0) -> 0.011486785 | AG32: =SUMIFS('P&L Data'!$N:$N,'P&L Data'!$B:$B,$D32,'P&L Data'!$C:$C,$AG$4) -> -61.75487 | AH32: =SUMIFS('P&L Data'!$P:$P,'P&L Data'!$B:$B,$D32,'P&L Data'!$C:$C,$AG$4) -> -150.73826 | AI32: =SUMIFS('P&L Data'!$T:$T,'P&L Data'!$B:$B,$D32,'P&L Data'!$C:$C,$AG$4) -> -96.28863 | AJ32: =AG32-AH32 -> 88.98339 | AK32: =AG32-AI32 -> 34.53376 | AL32: =IFERROR((AG32-AH32)/ABS(AH32),0) -> 0.59031722 | AM32: =IFERROR((AG32-AI32)/ABS(AI32),0) -> 0.35864837 | AO32: =SUMIFS('P&L Data'!$N:$N,'P&L Data'!$B:$B,$D32,'P&L Data'!$C:$C,$AO$4) -> -461.2388 | AP32: =SUMIFS('P&L Data'!$P:$P,'P&L Data'!$B:$B,$D32,'P&L Data'!$C:$C,$AO$4) -> -500.8323 | AQ32: =SUMIFS('P&L Data'!$T:$T,'P&L Data'!$B:$B,$D32,'P&L Data'!$C:$C,$AO$4) -> -438.00631 | AR32: =AO32-AP32 -> 39.5935 | AS32: =AO32-AQ32 -> -23.23249 | AT32: =IFERROR((AO32-AP32)/ABS(AP32),0) -> 0.079055404 | AU32: =IFERROR((AO32-AQ32)/ABS(AQ32),0) -> -0.05304145 | AW32: =SUMIFS('P&L Data'!$N:$N,'P&L Data'!$B:$B,$D32,'P&L Data'!$C:$C,$AW$4) -> 6775.6458 | AX32: =SUMIFS('P&L Data'!$P:$P,'P&L Data'!$B:$B,$D32,'P&L Data'!$C:$C,$AW$4) -> 6398.2033 | AY32: =SUMIFS('P&L Data'!$T:$T,'P&L Data'!$B:$B,$D32,'P&L Data'!$C:$C,$AW$4) -> 6681.4587 | AZ32: =AW32-AX32 -> 377.44255 | BA32: =AW32-AY32 -> 94.187083 | BB32: =IFERROR((AW32-AX32)/ABS(AX32),0) -> 0.05899196 | BC32: =IFERROR((AW32-AY32)/ABS(AY32),0) -> 0.014096784 | BE32: =SUMIFS('P&L Data'!$N:$N,'P&L Data'!$B:$B,$D32,'P&L Data'!$C:$C,$BE$4) -> -1800.8677 | BF32: =SUMIFS('P&L Data'!$P:$P,'P&L Data'!$B:$B,$D32,'P&L Data'!$C:$C,$BE$4) -> -1877.474 | BG32: =SUMIFS('P&L Data'!$T:$T,'P&L Data'!$B:$B,$D32,'P&L Data'!$C:$C,$BE$4) -> -1748.7122 | BH32: =BE32-BF32 -> 76.60625 | BI32: =BE32-BG32 -> -52.15548 | BJ32: =IFERROR((BE32-BF32)/ABS(BF32),0) -> 0.040802829 | BK32: =IFERROR((BE32-BG32)/ABS(BG32),0) -> -0.029825078 | BM32: =SUMIFS('P&L Data'!$N:$N,'P&L Data'!$B:$B,$D32,'P&L Data'!$C:$C,$BM$4) -> -625.73431 | BN32: =SUMIFS('P&L Data'!$P:$P,'P&L Data'!$B:$B,$D32,'P&L Data'!$C:$C,$BM$4) -> -687.46318 | BO32: =SUMIFS('P&L Data'!$T:$T,'P&L Data'!$B:$B,$D32,'P&L Data'!$C:$C,$BM$4) -> -699.79595 | BP32: =BM32-BN32 -> 61.72887 | BQ32: =BM32-BO32 -> 74.06164 | BR32: =IFERROR((BM32-BN32)/ABS(BN32),0) -> 0.089792256 | BS32: =IFERROR((BM32-BO32)/ABS(BO32),0) -> 0.10583319 | BU32: =SUMIFS('P&L Data'!$N:$N,'P&L Data'!$B:$B,$D32,'P&L Data'!$C:$C,$BU$4) -> 0 | BV32: =SUMIFS('P&L Data'!$P:$P,'P&L Data'!$B:$B,$D32,'P&L Data'!$C:$C,$BU$4) -> 0 | BW32: =SUMIFS('P&L Data'!$T:$T,'P&L Data'!$B:$B,$D32,'P&L Data'!$C:$C,$BU$4) -> 0 | BX32: =BU32-BV32 -> 0 | BY32: =BU32-BW32 -> 0 | BZ32: =IFERROR((BU32-BV32)/ABS(BV32),0) -> 0 | CA32: =IFERROR((BU32-BW32)/ABS(BW32),0) -> 0 | CC32: =SUMIFS('P&L Data'!$N:$N,'P&L Data'!$B:$B,$D32,'P&L Data'!$C:$C,$CC$4) -> 4349.0438 | CD32: =SUMIFS('P&L Data'!$P:$P,'P&L Data'!$B:$B,$D32,'P&L Data'!$C:$C,$CC$4) -> 3833.2661 | CE32: =SUMIFS('P&L Data'!$T:$T,'P&L Data'!$B:$B,$D32,'P&L Data'!$C:$C,$CC$4) -> 4232.9505 | CF32: =CC32-CD32 -> 515.77767 | CG32: =CC32-CE32 -> 116.09324 | CH32: =IFERROR((CC32-CD32)/ABS(CD32),0) -> 0.13455306 | CI32: =IFERROR((CC32-CE32)/ABS(CE32),0) -> 0.027426081 | CK32: =SUMIFS('P&L Data'!$N:$N,'P&L Data'!$B:$B,$D32,'P&L Data'!$C:$C,$CK$4) -> -587.85175 | CL32: =SUMIFS('P&L Data'!$P:$P,'P&L Data'!$B:$B,$D32,'P&L Data'!$C:$C,$CK$4) -> -612.99999 | CM32: =SUMIFS('P&L Data'!$T:$T,'P&L Data'!$B:$B,$D32,'P&L Data'!$C:$C,$CK$4) -> -601.09996 | CN32: =CK32-CL32 -> 25.14824 | CO32: =CK32-CM32 -> 13.24821 | CP32: =IFERROR((CK32-CL32)/ABS(CL32),0) -> 0.041024862 | CQ32: =IFERROR((CK32-CM32)/ABS(CM32),0) -> 0.022039945 | CS32: =SUMIFS('P&L Data'!$N:$N,'P&L Data'!$B:$B,$D32,'P&L Data'!$C:$C,$CS$4) -> 3761.192 | CT32: =SUMIFS('P&L Data'!$P:$P,'P&L Data'!$B:$B,$D32,'P&L Data'!$C:$C,$CS$4) -> 3220.2661 | CU32: =SUMIFS('P&L Data'!$T:$T,'P&L Data'!$B:$B,$D32,'P&L Data'!$C:$C,$CS$4) -> 3631.8506 | CV32: =CS32-CT32 -> 540.92591 | CW32: =CS32-CU32 -> 129.34145 | CX32: =IFERROR((CS32-CT32)/ABS(CT32),0) -> 0.16797553 | CY32: =IFERROR((CS32-CU32)/ABS(CU32),0) -> 0.035613099
B33: West | C33: Western - Crescent | D33: 20006 | E33: Mutib Street | F33: Hyper | G33: LFL | I33: =SUMIFS('P&L Data'!$N:$N,'P&L Data'!$B:$B,$D33,'P&L Data'!$C:$C,$I$4) -> 69869.524 | J33: =SUMIFS('P&L Data'!$P:$P,'P&L Data'!$B:$B,$D33,'P&L Data'!$C:$C,$I$4) -> 74065.995 | K33: =SUMIFS('P&L Data'!$T:$T,'P&L Data'!$B:$B,$D33,'P&L Data'!$C:$C,$I$4) -> 76543.815 | L33: =I33-J33 -> -4196.4711 | M33: =I33-K33 -> -6674.2913 | N33: =IFERROR((I33-J33)/ABS(J33),0) -> -0.056658539 | O33: =IFERROR((I33-K33)/ABS(K33),0) -> -0.087195697 | Q33: =SUMIFS('P&L Data'!$N:$N,'P&L Data'!$B:$B,$D33,'P&L Data'!$C:$C,$Q$4) -> 3942.0351 | R33: =SUMIFS('P&L Data'!$P:$P,'P&L Data'!$B:$B,$D33,'P&L Data'!$C:$C,$Q$4) -> 4477.132 | S33: =SUMIFS('P&L Data'!$T:$T,'P&L Data'!$B:$B,$D33,'P&L Data'!$C:$C,$Q$4) -> 4991.1494 | T33: =Q33-R33 -> -535.09692 | U33: =Q33-S33 -> -1049.1144 | V33: =IFERROR((Q33-R33)/ABS(R33),0) -> -0.11951779 | W33: =IFERROR((Q33-S33)/ABS(S33),0) -> -0.21019495 | Y33: =SUMIFS('P&L Data'!$N:$N,'P&L Data'!$B:$B,$D33,'P&L Data'!$C:$C,$Y$4) -> 17583.837 | Z33: =SUMIFS('P&L Data'!$P:$P,'P&L Data'!$B:$B,$D33,'P&L Data'!$C:$C,$Y$4) -> 18475.439 | AA33: =SUMIFS('P&L Data'!$T:$T,'P&L Data'!$B:$B,$D33,'P&L Data'!$C:$C,$Y$4) -> 18666.987 | AB33: =Y33-Z33 -> -891.60149 | AC33: =Y33-AA33 -> -1083.1497 | AD33: =IFERROR((Y33-Z33)/ABS(Z33),0) -> -0.048258745 | AE33: =IFERROR((Y33-AA33)/ABS(AA33),0) -> -0.058024879 | AG33: =SUMIFS('P&L Data'!$N:$N,'P&L Data'!$B:$B,$D33,'P&L Data'!$C:$C,$AG$4) -> -296.56066 | AH33: =SUMIFS('P&L Data'!$P:$P,'P&L Data'!$B:$B,$D33,'P&L Data'!$C:$C,$AG$4) -> -428.80983 | AI33: =SUMIFS('P&L Data'!$T:$T,'P&L Data'!$B:$B,$D33,'P&L Data'!$C:$C,$AG$4) -> -232.80258 | AJ33: =AG33-AH33 -> 132.24917 | AK33: =AG33-AI33 -> -63.75808 | AL33: =IFERROR((AG33-AH33)/ABS(AH33),0) -> 0.30840984 | AM33: =IFERROR((AG33-AI33)/ABS(AI33),0) -> -0.27387188 | AO33: =SUMIFS('P&L Data'!$N:$N,'P&L Data'!$B:$B,$D33,'P&L Data'!$C:$C,$AO$4) -> -1214.095 | AP33: =SUMIFS('P&L Data'!$P:$P,'P&L Data'!$B:$B,$D33,'P&L Data'!$C:$C,$AO$4) -> -1362.9831 | AQ33: =SUMIFS('P&L Data'!$T:$T,'P&L Data'!$B:$B,$D33,'P&L Data'!$C:$C,$AO$4) -> -1218.9676 | AR33: =AO33-AP33 -> 148.88812 | AS33: =AO33-AQ33 -> 4.8726503 | AT33: =IFERROR((AO33-AP33)/ABS(AP33),0) -> 0.10923695 | AU33: =IFERROR((AO33-AQ33)/ABS(AQ33),0) -> 0.0039973583 | AW33: =SUMIFS('P&L Data'!$N:$N,'P&L Data'!$B:$B,$D33,'P&L Data'!$C:$C,$AW$4) -> 16073.182 | AX33: =SUMIFS('P&L Data'!$P:$P,'P&L Data'!$B:$B,$D33,'P&L Data'!$C:$C,$AW$4) -> 16683.646 | AY33: =SUMIFS('P&L Data'!$T:$T,'P&L Data'!$B:$B,$D33,'P&L Data'!$C:$C,$AW$4) -> 17215.217 | AZ33: =AW33-AX33 -> -610.4642 | BA33: =AW33-AY33 -> -1142.0351 | BB33: =IFERROR((AW33-AX33)/ABS(AX33),0) -> -0.036590575 | BC33: =IFERROR((AW33-AY33)/ABS(AY33),0) -> -0.0663387 | BE33: =SUMIFS('P&L Data'!$N:$N,'P&L Data'!$B:$B,$D33,'P&L Data'!$C:$C,$BE$4) -> -5061.1581 | BF33: =SUMIFS('P&L Data'!$P:$P,'P&L Data'!$B:$B,$D33,'P&L Data'!$C:$C,$BE$4) -> -4886.3318 | BG33: =SUMIFS('P&L Data'!$T:$T,'P&L Data'!$B:$B,$D33,'P&L Data'!$C:$C,$BE$4) -> -4635.0322 | BH33: =BE33-BF33 -> -174.82623 | BI33: =BE33-BG33 -> -426.12583 | BJ33: =IFERROR((BE33-BF33)/ABS(BF33),0) -> -0.035778624 | BK33: =IFERROR((BE33-BG33)/ABS(BG33),0) -> -0.091935894 | BM33: =SUMIFS('P&L Data'!$N:$N,'P&L Data'!$B:$B,$D33,'P&L Data'!$C:$C,$BM$4) -> -1702.8157 | BN33: =SUMIFS('P&L Data'!$P:$P,'P&L Data'!$B:$B,$D33,'P&L Data'!$C:$C,$BM$4) -> -1653.1564 | BO33: =SUMIFS('P&L Data'!$T:$T,'P&L Data'!$B:$B,$D33,'P&L Data'!$C:$C,$BM$4) -> -1708.1346 | BP33: =BM33-BN33 -> -49.65936 | BQ33: =BM33-BO33 -> 5.3189 | BR33: =IFERROR((BM33-BN33)/ABS(BN33),0) -> -0.030039118 | BS33: =IFERROR((BM33-BO33)/ABS(BO33),0) -> 0.0031138646 | BU33: =SUMIFS('P&L Data'!$N:$N,'P&L Data'!$B:$B,$D33,'P&L Data'!$C:$C,$BU$4) -> -3754.2944 | BV33: =SUMIFS('P&L Data'!$P:$P,'P&L Data'!$B:$B,$D33,'P&L Data'!$C:$C,$BU$4) -> -3754.2944 | BW33: =SUMIFS('P&L Data'!$T:$T,'P&L Data'!$B:$B,$D33,'P&L Data'!$C:$C,$BU$4) -> -3754.2944 | BX33: =BU33-BV33 -> 0 | BY33: =BU33-BW33 -> 0 | BZ33: =IFERROR((BU33-BV33)/ABS(BV33),0) -> 0 | CA33: =IFERROR((BU33-BW33)/ABS(BW33),0) -> 0 | CC33: =SUMIFS('P&L Data'!$N:$N,'P&L Data'!$B:$B,$D33,'P&L Data'!$C:$C,$CC$4) -> 5554.9137 | CD33: =SUMIFS('P&L Data'!$P:$P,'P&L Data'!$B:$B,$D33,'P&L Data'!$C:$C,$CC$4) -> 6389.8635 | CE33: =SUMIFS('P&L Data'!$T:$T,'P&L Data'!$B:$B,$D33,'P&L Data'!$C:$C,$CC$4) -> 7117.7557 | CF33: =CC33-CD33 -> -834.94979 | CG33: =CC33-CE33 -> -1562.842 | CH33: =IFERROR((CC33-CD33)/ABS(CD33),0) -> -0.13066786 | CI33: =IFERROR((CC33-CE33)/ABS(CE33),0) -> -0.2195695 | CK33: =SUMIFS('P&L Data'!$N:$N,'P&L Data'!$B:$B,$D33,'P&L Data'!$C:$C,$CK$4) -> -1929.599 | CL33: =SUMIFS('P&L Data'!$P:$P,'P&L Data'!$B:$B,$D33,'P&L Data'!$C:$C,$CK$4) -> -1709.6989 | CM33: =SUMIFS('P&L Data'!$T:$T,'P&L Data'!$B:$B,$D33,'P&L Data'!$C:$C,$CK$4) -> -1583.3424 | CN33: =CK33-CL33 -> -219.90014 | CO33: =CK33-CM33 -> -346.2566 | CP33: =IFERROR((CK33-CL33)/ABS(CL33),0) -> -0.12861922 | CQ33: =IFERROR((CK33-CM33)/ABS(CM33),0) -> -0.21868712 | CS33: =SUMIFS('P&L Data'!$N:$N,'P&L Data'!$B:$B,$D33,'P&L Data'!$C:$C,$CS$4) -> 3625.3147 | CT33: =SUMIFS('P&L Data'!$P:$P,'P&L Data'!$B:$B,$D33,'P&L Data'!$C:$C,$CS$4) -> 4680.1646 | CU33: =SUMIFS('P&L Data'!$T:$T,'P&L Data'!$B:$B,$D33,'P&L Data'!$C:$C,$CS$4) -> 5534.4133 | CV33: =CS33-CT33 -> -1054.8499 | CW33: =CS33-CU33 -> -1909.0986 | CX33: =IFERROR((CS33-CT33)/ABS(CT33),0) -> -0.22538736 | CY33: =IFERROR((CS33-CU33)/ABS(CU33),0) -> -0.3449505
B34: West | C34: Western - Crescent Total | I34: =SUBTOTAL(9,I32:I33) -> 96842.564 | J34: =SUBTOTAL(9,J32:J33) -> 102160.91 | K34: =SUBTOTAL(9,K32:K33) -> 105867.26 | L34: =I34-J34 -> -5318.3502 | M34: =I34-K34 -> -9024.6941 | N34: =IFERROR((I34-J34)/ABS(J34),0) -> -0.052058561 | O34: =IFERROR((I34-K34)/ABS(K34),0) -> -0.085245374 | Q34: =SUBTOTAL(9,Q32:Q33) -> 5984.6613 | R34: =SUBTOTAL(9,R32:R33) -> 6441.4106 | S34: =SUBTOTAL(9,S32:S33) -> 7449.6239 | T34: =Q34-R34 -> -456.74936 | U34: =Q34-S34 -> -1464.9627 | V34: =IFERROR((Q34-R34)/ABS(R34),0) -> -0.070908282 | W34: =IFERROR((Q34-S34)/ABS(S34),0) -> -0.19664921 | Y34: =SUBTOTAL(9,Y32:Y33) -> 24882.477 | Z34: =SUBTOTAL(9,Z32:Z33) -> 25525.213 | AA34: =SUBTOTAL(9,AA32:AA33) -> 25882.741 | AB34: =Y34-Z34 -> -642.73583 | AC34: =Y34-AA34 -> -1000.2639 | AD34: =IFERROR((Y34-Z34)/ABS(Z34),0) -> -0.02518043 | AE34: =IFERROR((Y34-AA34)/ABS(AA34),0) -> -0.038645979 | AG34: =SUBTOTAL(9,AG32:AG33) -> -358.31553 | AH34: =SUBTOTAL(9,AH32:AH33) -> -579.54809 | AI34: =SUBTOTAL(9,AI32:AI33) -> -329.09121 | AJ34: =AG34-AH34 -> 221.23256 | AK34: =AG34-AI34 -> -29.22432 | AL34: =IFERROR((AG34-AH34)/ABS(AH34),0) -> 0.38173288 | AM34: =IFERROR((AG34-AI34)/ABS(AI34),0) -> -0.088803101 | AO34: =SUBTOTAL(9,AO32:AO33) -> -1675.3338 | AP34: =SUBTOTAL(9,AP32:AP33) -> -1863.8154 | AQ34: =SUBTOTAL(9,AQ32:AQ33) -> -1656.9739 | AR34: =AO34-AP34 -> 188.48162 | AS34: =AO34-AQ34 -> -18.35984 | AT34: =IFERROR((AO34-AP34)/ABS(AP34),0) -> 0.10112677 | AU34: =IFERROR((AO34-AQ34)/ABS(AQ34),0) -> -0.011080343 | AW34: =SUBTOTAL(9,AW32:AW33) -> 22848.828 | AX34: =SUBTOTAL(9,AX32:AX33) -> 23081.849 | AY34: =SUBTOTAL(9,AY32:AY33) -> 23896.676 | AZ34: =AW34-AX34 -> -233.02165 | BA34: =AW34-AY34 -> -1047.848 | BB34: =IFERROR((AW34-AX34)/ABS(AX34),0) -> -0.01009545 | BC34: =IFERROR((AW34-AY34)/ABS(AY34),0) -> -0.043849113 | BE34: =SUBTOTAL(9,BE32:BE33) -> -6862.0258 | BF34: =SUBTOTAL(9,BF32:BF33) -> -6763.8058 | BG34: =SUBTOTAL(9,BG32:BG33) -> -6383.7445 | BH34: =BE34-BF34 -> -98.21998 | BI34: =BE34-BG34 -> -478.28131 | BJ34: =IFERROR((BE34-BF34)/ABS(BF34),0) -> -0.014521407 | BK34: =IFERROR((BE34-BG34)/ABS(BG34),0) -> -0.07492175 | BM34: =SUBTOTAL(9,BM32:BM33) -> -2328.55 | BN34: =SUBTOTAL(9,BN32:BN33) -> -2340.6196 | BO34: =SUBTOTAL(9,BO32:BO33) -> -2407.9306 | BP34: =BM34-BN34 -> 12.06951 | BQ34: =BM34-BO34 -> 79.38054 | BR34: =IFERROR((BM34-BN34)/ABS(BN34),0) -> 0.005156545 | BS34: =IFERROR((BM34-BO34)/ABS(BO34),0) -> 0.032966291 | BU34: =SUBTOTAL(9,BU32:BU33) -> -3754.2944 | BV34: =SUBTOTAL(9,BV32:BV33) -> -3754.2944 | BW34: =SUBTOTAL(9,BW32:BW33) -> -3754.2944 | BX34: =BU34-BV34 -> 0 | BY34: =BU34-BW34 -> 0 | BZ34: =IFERROR((BU34-BV34)/ABS(BV34),0) -> 0 | CA34: =IFERROR((BU34-BW34)/ABS(BW34),0) -> 0 | CC34: =SUBTOTAL(9,CC32:CC33) -> 9903.9575 | CD34: =SUBTOTAL(9,CD32:CD33) -> 10223.13 | CE34: =SUBTOTAL(9,CE32:CE33) -> 11350.706 | CF34: =CC34-CD34 -> -319.17212 | CG34: =CC34-CE34 -> -1446.7488 | CH34: =IFERROR((CC34-CD34)/ABS(CD34),0) -> -0.031220588 | CI34: =IFERROR((CC34-CE34)/ABS(CE34),0) -> -0.12745892 | CK34: =SUBTOTAL(9,CK32:CK33) -> -2517.4508 | CL34: =SUBTOTAL(9,CL32:CL33) -> -2322.6989 | CM34: =SUBTOTAL(9,CM32:CM33) -> -2184.4424 | CN34: =CK34-CL34 -> -194.7519 | CO34: =CK34-CM34 -> -333.00839 | CP34: =IFERROR((CK34-CL34)/ABS(CL34),0) -> -0.083847244 | CQ34: =IFERROR((CK34-CM34)/ABS(CM34),0) -> -0.15244549 | CS34: =SUBTOTAL(9,CS32:CS33) -> 7386.5067 | CT34: =SUBTOTAL(9,CT32:CT33) -> 7900.4307 | CU34: =SUBTOTAL(9,CU32:CU33) -> 9166.2639 | CV34: =SUBTOTAL(9,CV32:CV33) -> -513.92402 | CW34: =SUBTOTAL(9,CW32:CW33) -> -1779.7572 | CX34: =IFERROR((CS34-CT34)/ABS(CT34),0) -> -0.065050127 | CY34: =IFERROR((CS34-CU34)/ABS(CU34),0) -> -0.19416386
B35: West | C35: Western - Nucleus | D35: 201 | E35: Safa | F35: Hyper | G35: LFL | I35: =SUMIFS('P&L Data'!$N:$N,'P&L Data'!$B:$B,$D35,'P&L Data'!$C:$C,$I$4) -> 39927.805 | J35: =SUMIFS('P&L Data'!$P:$P,'P&L Data'!$B:$B,$D35,'P&L Data'!$C:$C,$I$4) -> 39886.822 | K35: =SUMIFS('P&L Data'!$T:$T,'P&L Data'!$B:$B,$D35,'P&L Data'!$C:$C,$I$4) -> 44368.743 | L35: =I35-J35 -> 40.98304 | M35: =I35-K35 -> -4440.9388 | N35: =IFERROR((I35-J35)/ABS(J35),0) -> 0.0010274832 | O35: =IFERROR((I35-K35)/ABS(K35),0) -> -0.10009161 | Q35: =SUMIFS('P&L Data'!$N:$N,'P&L Data'!$B:$B,$D35,'P&L Data'!$C:$C,$Q$4) -> 501.69016 | R35: =SUMIFS('P&L Data'!$P:$P,'P&L Data'!$B:$B,$D35,'P&L Data'!$C:$C,$Q$4) -> 1539.2643 | S35: =SUMIFS('P&L Data'!$T:$T,'P&L Data'!$B:$B,$D35,'P&L Data'!$C:$C,$Q$4) -> 1275.2754 | T35: =Q35-R35 -> -1037.5741 | U35: =Q35-S35 -> -773.58521 | V35: =IFERROR((Q35-R35)/ABS(R35),0) -> -0.67407147 | W35: =IFERROR((Q35-S35)/ABS(S35),0) -> -0.60660249 | Y35: =SUMIFS('P&L Data'!$N:$N,'P&L Data'!$B:$B,$D35,'P&L Data'!$C:$C,$Y$4) -> 8440.9289 | Z35: =SUMIFS('P&L Data'!$P:$P,'P&L Data'!$B:$B,$D35,'P&L Data'!$C:$C,$Y$4) -> 9204.157 | AA35: =SUMIFS('P&L Data'!$T:$T,'P&L Data'!$B:$B,$D35,'P&L Data'!$C:$C,$Y$4) -> 9235.9684 | AB35: =Y35-Z35 -> -763.22811 | AC35: =Y35-AA35 -> -795.0395 | AD35: =IFERROR((Y35-Z35)/ABS(Z35),0) -> -0.082922109 | AE35: =IFERROR((Y35-AA35)/ABS(AA35),0) -> -0.086080794 | AG35: =SUMIFS('P&L Data'!$N:$N,'P&L Data'!$B:$B,$D35,'P&L Data'!$C:$C,$AG$4) -> -93.33612 | AH35: =SUMIFS('P&L Data'!$P:$P,'P&L Data'!$B:$B,$D35,'P&L Data'!$C:$C,$AG$4) -> -235.35553 | AI35: =SUMIFS('P&L Data'!$T:$T,'P&L Data'!$B:$B,$D35,'P&L Data'!$C:$C,$AG$4) -> -226.24707 | AJ35: =AG35-AH35 -> 142.01941 | AK35: =AG35-AI35 -> 132.91095 | AL35: =IFERROR((AG35-AH35)/ABS(AH35),0) -> 0.603425 | AM35: =IFERROR((AG35-AI35)/ABS(AI35),0) -> 0.58745932 | AO35: =SUMIFS('P&L Data'!$N:$N,'P&L Data'!$B:$B,$D35,'P&L Data'!$C:$C,$AO$4) -> -692.23965 | AP35: =SUMIFS('P&L Data'!$P:$P,'P&L Data'!$B:$B,$D35,'P&L Data'!$C:$C,$AO$4) -> -750.77172 | AQ35: =SUMIFS('P&L Data'!$T:$T,'P&L Data'!$B:$B,$D35,'P&L Data'!$C:$C,$AO$4) -> -754.89077 | AR35: =AO35-AP35 -> 58.53207 | AS35: =AO35-AQ35 -> 62.651123 | AT35: =IFERROR((AO35-AP35)/ABS(AP35),0) -> 0.07796254 | AU35: =IFERROR((AO35-AQ35)/ABS(AQ35),0) -> 0.082993627 | AW35: =SUMIFS('P&L Data'!$N:$N,'P&L Data'!$B:$B,$D35,'P&L Data'!$C:$C,$AW$4) -> 7655.3532 | AX35: =SUMIFS('P&L Data'!$P:$P,'P&L Data'!$B:$B,$D35,'P&L Data'!$C:$C,$AW$4) -> 8218.0298 | AY35: =SUMIFS('P&L Data'!$T:$T,'P&L Data'!$B:$B,$D35,'P&L Data'!$C:$C,$AW$4) -> 8254.8306 | AZ35: =AW35-AX35 -> -562.67663 | BA35: =AW35-AY35 -> -599.47742 | BB35: =IFERROR((AW35-AX35)/ABS(AX35),0) -> -0.068468556 | BC35: =IFERROR((AW35-AY35)/ABS(AY35),0) -> -0.072621408 | BE35: =SUMIFS('P&L Data'!$N:$N,'P&L Data'!$B:$B,$D35,'P&L Data'!$C:$C,$BE$4) -> -2492.623 | BF35: =SUMIFS('P&L Data'!$P:$P,'P&L Data'!$B:$B,$D35,'P&L Data'!$C:$C,$BE$4) -> -2593.2814 | BG35: =SUMIFS('P&L Data'!$T:$T,'P&L Data'!$B:$B,$D35,'P&L Data'!$C:$C,$BE$4) -> -2736.2593 | BH35: =BE35-BF35 -> 100.65836 | BI35: =BE35-BG35 -> 243.63621 | BJ35: =IFERROR((BE35-BF35)/ABS(BF35),0) -> 0.038815055 | BK35: =IFERROR((BE35-BG35)/ABS(BG35),0) -> 0.089039885 | BM35: =SUMIFS('P&L Data'!$N:$N,'P&L Data'!$B:$B,$D35,'P&L Data'!$C:$C,$BM$4) -> -980.46324 | BN35: =SUMIFS('P&L Data'!$P:$P,'P&L Data'!$B:$B,$D35,'P&L Data'!$C:$C,$BM$4) -> -880.76606 | BO35: =SUMIFS('P&L Data'!$T:$T,'P&L Data'!$B:$B,$D35,'P&L Data'!$C:$C,$BM$4) -> -1043.5678 | BP35: =BM35-BN35 -> -99.69718 | BQ35: =BM35-BO35 -> 63.1046 | BR35: =IFERROR((BM35-BN35)/ABS(BN35),0) -> -0.11319371 | BS35: =IFERROR((BM35-BO35)/ABS(BO35),0) -> 0.060470051 | BU35: =SUMIFS('P&L Data'!$N:$N,'P&L Data'!$B:$B,$D35,'P&L Data'!$C:$C,$BU$4) -> -2189.0709 | BV35: =SUMIFS('P&L Data'!$P:$P,'P&L Data'!$B:$B,$D35,'P&L Data'!$C:$C,$BU$4) -> -2189.0709 | BW35: =SUMIFS('P&L Data'!$T:$T,'P&L Data'!$B:$B,$D35,'P&L Data'!$C:$C,$BU$4) -> -2189.0709 | BX35: =BU35-BV35 -> 0 | BY35: =BU35-BW35 -> 0 | BZ35: =IFERROR((BU35-BV35)/ABS(BV35),0) -> 0 | CA35: =IFERROR((BU35-BW35)/ABS(BW35),0) -> 0 | CC35: =SUMIFS('P&L Data'!$N:$N,'P&L Data'!$B:$B,$D35,'P&L Data'!$C:$C,$CC$4) -> 1993.196 | CD35: =SUMIFS('P&L Data'!$P:$P,'P&L Data'!$B:$B,$D35,'P&L Data'!$C:$C,$CC$4) -> 2554.9114 | CE35: =SUMIFS('P&L Data'!$T:$T,'P&L Data'!$B:$B,$D35,'P&L Data'!$C:$C,$CC$4) -> 2285.9326 | CF35: =CC35-CD35 -> -561.71545 | CG35: =CC35-CE35 -> -292.73661 | CH35: =IFERROR((CC35-CD35)/ABS(CD35),0) -> -0.21985711 | CI35: =IFERROR((CC35-CE35)/ABS(CE35),0) -> -0.12806004 | CK35: =SUMIFS('P&L Data'!$N:$N,'P&L Data'!$B:$B,$D35,'P&L Data'!$C:$C,$CK$4) -> -452.26668 | CL35: =SUMIFS('P&L Data'!$P:$P,'P&L Data'!$B:$B,$D35,'P&L Data'!$C:$C,$CK$4) -> -449.80251 | CM35: =SUMIFS('P&L Data'!$T:$T,'P&L Data'!$B:$B,$D35,'P&L Data'!$C:$C,$CK$4) -> -486.20246 | CN35: =CK35-CL35 -> -2.46417 | CO35: =CK35-CM35 -> 33.93578 | CP35: =IFERROR((CK35-CL35)/ABS(CL35),0) -> -0.0054783376 | CQ35: =IFERROR((CK35-CM35)/ABS(CM35),0) -> 0.069797631 | CS35: =SUMIFS('P&L Data'!$N:$N,'P&L Data'!$B:$B,$D35,'P&L Data'!$C:$C,$CS$4) -> 1540.9293 | CT35: =SUMIFS('P&L Data'!$P:$P,'P&L Data'!$B:$B,$D35,'P&L Data'!$C:$C,$CS$4) -> 2105.1089 | CU35: =SUMIFS('P&L Data'!$T:$T,'P&L Data'!$B:$B,$D35,'P&L Data'!$C:$C,$CS$4) -> 1799.7301 | CV35: =CS35-CT35 -> -564.17962 | CW35: =CS35-CU35 -> -258.80083 | CX35: =IFERROR((CS35-CT35)/ABS(CT35),0) -> -0.26800496 | CY35: =IFERROR((CS35-CU35)/ABS(CU35),0) -> -0.1437998
B36: West | C36: Western - Nucleus | D36: 20001 | E36: Roshan Mall | F36: Hyper | G36: LFL | I36: =SUMIFS('P&L Data'!$N:$N,'P&L Data'!$B:$B,$D36,'P&L Data'!$C:$C,$I$4) -> 13815.637 | J36: =SUMIFS('P&L Data'!$P:$P,'P&L Data'!$B:$B,$D36,'P&L Data'!$C:$C,$I$4) -> 21158.569 | K36: =SUMIFS('P&L Data'!$T:$T,'P&L Data'!$B:$B,$D36,'P&L Data'!$C:$C,$I$4) -> 25577.632 | L36: =I36-J36 -> -7342.9314 | M36: =I36-K36 -> -11761.995 | N36: =IFERROR((I36-J36)/ABS(J36),0) -> -0.34704292 | O36: =IFERROR((I36-K36)/ABS(K36),0) -> -0.45985471 | Q36: =SUMIFS('P&L Data'!$N:$N,'P&L Data'!$B:$B,$D36,'P&L Data'!$C:$C,$Q$4) -> 544.5752 | R36: =SUMIFS('P&L Data'!$P:$P,'P&L Data'!$B:$B,$D36,'P&L Data'!$C:$C,$Q$4) -> 1304.2885 | S36: =SUMIFS('P&L Data'!$T:$T,'P&L Data'!$B:$B,$D36,'P&L Data'!$C:$C,$Q$4) -> 1849.6344 | T36: =Q36-R36 -> -759.71332 | U36: =Q36-S36 -> -1305.0592 | V36: =IFERROR((Q36-R36)/ABS(R36),0) -> -0.58247336 | W36: =IFERROR((Q36-S36)/ABS(S36),0) -> -0.70557684 | Y36: =SUMIFS('P&L Data'!$N:$N,'P&L Data'!$B:$B,$D36,'P&L Data'!$C:$C,$Y$4) -> 3275.3145 | Z36: =SUMIFS('P&L Data'!$P:$P,'P&L Data'!$B:$B,$D36,'P&L Data'!$C:$C,$Y$4) -> 5523.8341 | AA36: =SUMIFS('P&L Data'!$T:$T,'P&L Data'!$B:$B,$D36,'P&L Data'!$C:$C,$Y$4) -> 6622.9175 | AB36: =Y36-Z36 -> -2248.5196 | AC36: =Y36-AA36 -> -3347.603 | AD36: =IFERROR((Y36-Z36)/ABS(Z36),0) -> -0.40705778 | AE36: =IFERROR((Y36-AA36)/ABS(AA36),0) -> -0.50545745 | AG36: =SUMIFS('P&L Data'!$N:$N,'P&L Data'!$B:$B,$D36,'P&L Data'!$C:$C,$AG$4) -> -119.9676 | AH36: =SUMIFS('P&L Data'!$P:$P,'P&L Data'!$B:$B,$D36,'P&L Data'!$C:$C,$AG$4) -> -125.25093 | AI36: =SUMIFS('P&L Data'!$T:$T,'P&L Data'!$B:$B,$D36,'P&L Data'!$C:$C,$AG$4) -> -265.73012 | AJ36: =AG36-AH36 -> 5.28333 | AK36: =AG36-AI36 -> 145.76252 | AL36: =IFERROR((AG36-AH36)/ABS(AH36),0) -> 0.042181962 | AM36: =IFERROR((AG36-AI36)/ABS(AI36),0) -> 0.54853594 | AO36: =SUMIFS('P&L Data'!$N:$N,'P&L Data'!$B:$B,$D36,'P&L Data'!$C:$C,$AO$4) -> -248.35932 | AP36: =SUMIFS('P&L Data'!$P:$P,'P&L Data'!$B:$B,$D36,'P&L Data'!$C:$C,$AO$4) -> -403.43 | AQ36: =SUMIFS('P&L Data'!$T:$T,'P&L Data'!$B:$B,$D36,'P&L Data'!$C:$C,$AO$4) -> -429.76414 | AR36: =AO36-AP36 -> 155.07068 | AS36: =AO36-AQ36 -> 181.40482 | AT36: =IFERROR((AO36-AP36)/ABS(AP36),0) -> 0.38438064 | AU36: =IFERROR((AO36-AQ36)/ABS(AQ36),0) -> 0.4221032 | AW36: =SUMIFS('P&L Data'!$N:$N,'P&L Data'!$B:$B,$D36,'P&L Data'!$C:$C,$AW$4) -> 2906.9875 | AX36: =SUMIFS('P&L Data'!$P:$P,'P&L Data'!$B:$B,$D36,'P&L Data'!$C:$C,$AW$4) -> 4995.1532 | AY36: =SUMIFS('P&L Data'!$T:$T,'P&L Data'!$B:$B,$D36,'P&L Data'!$C:$C,$AW$4) -> 5927.4232 | AZ36: =AW36-AX36 -> -2088.1656 | BA36: =AW36-AY36 -> -3020.4357 | BB36: =IFERROR((AW36-AX36)/ABS(AX36),0) -> -0.41803836 | BC36: =IFERROR((AW36-AY36)/ABS(AY36),0) -> -0.50956977 | BE36: =SUMIFS('P&L Data'!$N:$N,'P&L Data'!$B:$B,$D36,'P&L Data'!$C:$C,$BE$4) -> -1969.5582 | BF36: =SUMIFS('P&L Data'!$P:$P,'P&L Data'!$B:$B,$D36,'P&L Data'!$C:$C,$BE$4) -> -2000.5936 | BG36: =SUMIFS('P&L Data'!$T:$T,'P&L Data'!$B:$B,$D36,'P&L Data'!$C:$C,$BE$4) -> -2462.1776 | BH36: =BE36-BF36 -> 31.03541 | BI36: =BE36-BG36 -> 492.61936 | BJ36: =IFERROR((BE36-BF36)/ABS(BF36),0) -> 0.0155131 | BK36: =IFERROR((BE36-BG36)/ABS(BG36),0) -> 0.20007467 | BM36: =SUMIFS('P&L Data'!$N:$N,'P&L Data'!$B:$B,$D36,'P&L Data'!$C:$C,$BM$4) -> -799.56904 | BN36: =SUMIFS('P&L Data'!$P:$P,'P&L Data'!$B:$B,$D36,'P&L Data'!$C:$C,$BM$4) -> -1064.9781 | BO36: =SUMIFS('P&L Data'!$T:$T,'P&L Data'!$B:$B,$D36,'P&L Data'!$C:$C,$BM$4) -> -1351.5988 | BP36: =BM36-BN36 -> 265.40903 | BQ36: =BM36-BO36 -> 552.02976 | BR36: =IFERROR((BM36-BN36)/ABS(BN36),0) -> 0.24921549 | BS36: =IFERROR((BM36-BO36)/ABS(BO36),0) -> 0.40842723 | BU36: =SUMIFS('P&L Data'!$N:$N,'P&L Data'!$B:$B,$D36,'P&L Data'!$C:$C,$BU$4) -> -1166.6667 | BV36: =SUMIFS('P&L Data'!$P:$P,'P&L Data'!$B:$B,$D36,'P&L Data'!$C:$C,$BU$4) -> -1166.6667 | BW36: =SUMIFS('P&L Data'!$T:$T,'P&L Data'!$B:$B,$D36,'P&L Data'!$C:$C,$BU$4) -> -1166.6667 | BX36: =BU36-BV36 -> 0 | BY36: =BU36-BW36 -> 0 | BZ36: =IFERROR((BU36-BV36)/ABS(BV36),0) -> 0 | CA36: =IFERROR((BU36-BW36)/ABS(BW36),0) -> 0 | CC36: =SUMIFS('P&L Data'!$N:$N,'P&L Data'!$B:$B,$D36,'P&L Data'!$C:$C,$CC$4) -> -1028.8064 | CD36: =SUMIFS('P&L Data'!$P:$P,'P&L Data'!$B:$B,$D36,'P&L Data'!$C:$C,$CC$4) -> 762.91477 | CE36: =SUMIFS('P&L Data'!$T:$T,'P&L Data'!$B:$B,$D36,'P&L Data'!$C:$C,$CC$4) -> 946.98013 | CF36: =CC36-CD36 -> -1791.7212 | CG36: =CC36-CE36 -> -1975.7865 | CH36: =IFERROR((CC36-CD36)/ABS(CD36),0) -> -2.3485208 | CI36: =IFERROR((CC36-CE36)/ABS(CE36),0) -> -2.0864076 | CK36: =SUMIFS('P&L Data'!$N:$N,'P&L Data'!$B:$B,$D36,'P&L Data'!$C:$C,$CK$4) -> -413.17758 | CL36: =SUMIFS('P&L Data'!$P:$P,'P&L Data'!$B:$B,$D36,'P&L Data'!$C:$C,$CK$4) -> -842.7406 | CM36: =SUMIFS('P&L Data'!$T:$T,'P&L Data'!$B:$B,$D36,'P&L Data'!$C:$C,$CK$4) -> -291.83532 | CN36: =CK36-CL36 -> 429.56302 | CO36: =CK36-CM36 -> -121.34226 | CP36: =IFERROR((CK36-CL36)/ABS(CL36),0) -> 0.50972152 | CQ36: =IFERROR((CK36-CM36)/ABS(CM36),0) -> -0.41579018 | CS36: =SUMIFS('P&L Data'!$N:$N,'P&L Data'!$B:$B,$D36,'P&L Data'!$C:$C,$CS$4) -> -1441.984 | CT36: =SUMIFS('P&L Data'!$P:$P,'P&L Data'!$B:$B,$D36,'P&L Data'!$C:$C,$CS$4) -> -79.82583 | CU36: =SUMIFS('P&L Data'!$T:$T,'P&L Data'!$B:$B,$D36,'P&L Data'!$C:$C,$CS$4) -> 655.14481 | CV36: =CS36-CT36 -> -1362.1582 | CW36: =CS36-CU36 -> -2097.1288 | CX36: =IFERROR((CS36-CT36)/ABS(CT36),0) -> -17.064128 | CY36: =IFERROR((CS36-CU36)/ABS(CU36),0) -> -3.2010156
B37: West | C37: Western - Nucleus Total | I37: =SUBTOTAL(9,I35:I36) -> 53743.442 | J37: =SUBTOTAL(9,J35:J36) -> 61045.39 | K37: =SUBTOTAL(9,K35:K36) -> 69946.375 | L37: =I37-J37 -> -7301.9484 | M37: =I37-K37 -> -16202.933 | N37: =IFERROR((I37-J37)/ABS(J37),0) -> -0.11961507 | O37: =IFERROR((I37-K37)/ABS(K37),0) -> -0.23164794 | Q37: =SUBTOTAL(9,Q35:Q36) -> 1046.2654 | R37: =SUBTOTAL(9,R35:R36) -> 2843.5528 | S37: =SUBTOTAL(9,S35:S36) -> 3124.9098 | T37: =Q37-R37 -> -1797.2875 | U37: =Q37-S37 -> -2078.6444 | V37: =IFERROR((Q37-R37)/ABS(R37),0) -> -0.632057 | W37: =IFERROR((Q37-S37)/ABS(S37),0) -> -0.66518542 | Y37: =SUBTOTAL(9,Y35:Y36) -> 11716.243 | Z37: =SUBTOTAL(9,Z35:Z36) -> 14727.991 | AA37: =SUBTOTAL(9,AA35:AA36) -> 15858.886 | AB37: =Y37-Z37 -> -3011.7477 | AC37: =Y37-AA37 -> -4142.6425 | AD37: =IFERROR((Y37-Z37)/ABS(Z37),0) -> -0.20449141 | AE37: =IFERROR((Y37-AA37)/ABS(AA37),0) -> -0.26121901 | AG37: =SUBTOTAL(9,AG35:AG36) -> -213.30372 | AH37: =SUBTOTAL(9,AH35:AH36) -> -360.60646 | AI37: =SUBTOTAL(9,AI35:AI36) -> -491.97719 | AJ37: =AG37-AH37 -> 147.30274 | AK37: =AG37-AI37 -> 278.67347 | AL37: =IFERROR((AG37-AH37)/ABS(AH37),0) -> 0.40848614 | AM37: =IFERROR((AG37-AI37)/ABS(AI37),0) -> 0.56643575 | AO37: =SUBTOTAL(9,AO35:AO36) -> -940.59897 | AP37: =SUBTOTAL(9,AP35:AP36) -> -1154.2017 | AQ37: =SUBTOTAL(9,AQ35:AQ36) -> -1184.6549 | AR37: =AO37-AP37 -> 213.60275 | AS37: =AO37-AQ37 -> 244.05594 | AT37: =IFERROR((AO37-AP37)/ABS(AP37),0) -> 0.18506535 | AU37: =IFERROR((AO37-AQ37)/ABS(AQ37),0) -> 0.20601437 | AW37: =SUBTOTAL(9,AW35:AW36) -> 10562.341 | AX37: =SUBTOTAL(9,AX35:AX36) -> 13213.183 | AY37: =SUBTOTAL(9,AY35:AY36) -> 14182.254 | AZ37: =AW37-AX37 -> -2650.8422 | BA37: =AW37-AY37 -> -3619.9131 | BB37: =IFERROR((AW37-AX37)/ABS(AX37),0) -> -0.20062102 | BC37: =IFERROR((AW37-AY37)/ABS(AY37),0) -> -0.25524244 | BE37: =SUBTOTAL(9,BE35:BE36) -> -4462.1813 | BF37: =SUBTOTAL(9,BF35:BF36) -> -4593.875 | BG37: =SUBTOTAL(9,BG35:BG36) -> -5198.4368 | BH37: =BE37-BF37 -> 131.69377 | BI37: =BE37-BG37 -> 736.25557 | BJ37: =IFERROR((BE37-BF37)/ABS(BF37),0) -> 0.028667251 | BK37: =IFERROR((BE37-BG37)/ABS(BG37),0) -> 0.14163018 | BM37: =SUBTOTAL(9,BM35:BM36) -> -1780.0323 | BN37: =SUBTOTAL(9,BN35:BN36) -> -1945.7441 | BO37: =SUBTOTAL(9,BO35:BO36) -> -2395.1666 | BP37: =BM37-BN37 -> 165.71185 | BQ37: =BM37-BO37 -> 615.13436 | BR37: =IFERROR((BM37-BN37)/ABS(BN37),0) -> 0.085166311 | BS37: =IFERROR((BM37-BO37)/ABS(BO37),0) -> 0.2568232 | BU37: =SUBTOTAL(9,BU35:BU36) -> -3355.7376 | BV37: =SUBTOTAL(9,BV35:BV36) -> -3355.7376 | BW37: =SUBTOTAL(9,BW35:BW36) -> -3355.7376 | BX37: =BU37-BV37 -> 0 | BY37: =BU37-BW37 -> 0 | BZ37: =IFERROR((BU37-BV37)/ABS(BV37),0) -> 0 | CA37: =IFERROR((BU37-BW37)/ABS(BW37),0) -> 0 | CC37: =SUBTOTAL(9,CC35:CC36) -> 964.38956 | CD37: =SUBTOTAL(9,CD35:CD36) -> 3317.8262 | CE37: =SUBTOTAL(9,CE35:CE36) -> 3232.9127 | CF37: =CC37-CD37 -> -2353.4366 | CG37: =CC37-CE37 -> -2268.5231 | CH37: =IFERROR((CC37-CD37)/ABS(CD37),0) -> -0.7093309 | CI37: =IFERROR((CC37-CE37)/ABS(CE37),0) -> -0.70169638 | CK37: =SUBTOTAL(9,CK35:CK36) -> -865.44426 | CL37: =SUBTOTAL(9,CL35:CL36) -> -1292.5431 | CM37: =SUBTOTAL(9,CM35:CM36) -> -778.03778 | CN37: =CK37-CL37 -> 427.09885 | CO37: =CK37-CM37 -> -87.40648 | CP37: =IFERROR((CK37-CL37)/ABS(CL37),0) -> 0.33043296 | CQ37: =IFERROR((CK37-CM37)/ABS(CM37),0) -> -0.11234221 | CS37: =SUBTOTAL(9,CS35:CS36) -> 98.9453 | CT37: =SUBTOTAL(9,CT35:CT36) -> 2025.2831 | CU37: =SUBTOTAL(9,CU35:CU36) -> 2454.8749 | CV37: =SUBTOTAL(9,CV35:CV36) -> -1926.3378 | CW37: =SUBTOTAL(9,CW35:CW36) -> -2355.9296 | CX37: =IFERROR((CS37-CT37)/ABS(CT37),0) -> -0.95114495 | CY37: =IFERROR((CS37-CU37)/ABS(CU37),0) -> -0.95969436
B38: West | C38: Western - South | D38: 204 | E38: Obaiken Mall Taif | F38: Super | G38: LFL | I38: =SUMIFS('P&L Data'!$N:$N,'P&L Data'!$B:$B,$D38,'P&L Data'!$C:$C,$I$4) -> 35952.544 | J38: =SUMIFS('P&L Data'!$P:$P,'P&L Data'!$B:$B,$D38,'P&L Data'!$C:$C,$I$4) -> 36985.304 | K38: =SUMIFS('P&L Data'!$T:$T,'P&L Data'!$B:$B,$D38,'P&L Data'!$C:$C,$I$4) -> 37611.906 | L38: =I38-J38 -> -1032.7603 | M38: =I38-K38 -> -1659.3617 | N38: =IFERROR((I38-J38)/ABS(J38),0) -> -0.027923531 | O38: =IFERROR((I38-K38)/ABS(K38),0) -> -0.044117992 | Q38: =SUMIFS('P&L Data'!$N:$N,'P&L Data'!$B:$B,$D38,'P&L Data'!$C:$C,$Q$4) -> 238.4278 | R38: =SUMIFS('P&L Data'!$P:$P,'P&L Data'!$B:$B,$D38,'P&L Data'!$C:$C,$Q$4) -> 1137.7033 | S38: =SUMIFS('P&L Data'!$T:$T,'P&L Data'!$B:$B,$D38,'P&L Data'!$C:$C,$Q$4) -> 358.94499 | T38: =Q38-R38 -> -899.27552 | U38: =Q38-S38 -> -120.51719 | V38: =IFERROR((Q38-R38)/ABS(R38),0) -> -0.7904306 | W38: =IFERROR((Q38-S38)/ABS(S38),0) -> -0.33575392 | Y38: =SUMIFS('P&L Data'!$N:$N,'P&L Data'!$B:$B,$D38,'P&L Data'!$C:$C,$Y$4) -> 7596.3156 | Z38: =SUMIFS('P&L Data'!$P:$P,'P&L Data'!$B:$B,$D38,'P&L Data'!$C:$C,$Y$4) -> 8441.1115 | AA38: =SUMIFS('P&L Data'!$T:$T,'P&L Data'!$B:$B,$D38,'P&L Data'!$C:$C,$Y$4) -> 7370.2393 | AB38: =Y38-Z38 -> -844.79593 | AC38: =Y38-AA38 -> 226.07626 | AD38: =IFERROR((Y38-Z38)/ABS(Z38),0) -> -0.10008112 | AE38: =IFERROR((Y38-AA38)/ABS(AA38),0) -> 0.030674209 | AG38: =SUMIFS('P&L Data'!$N:$N,'P&L Data'!$B:$B,$D38,'P&L Data'!$C:$C,$AG$4) -> -74.0072 | AH38: =SUMIFS('P&L Data'!$P:$P,'P&L Data'!$B:$B,$D38,'P&L Data'!$C:$C,$AG$4) -> -242.90847 | AI38: =SUMIFS('P&L Data'!$T:$T,'P&L Data'!$B:$B,$D38,'P&L Data'!$C:$C,$AG$4) -> -97.98138 | AJ38: =AG38-AH38 -> 168.90127 | AK38: =AG38-AI38 -> 23.97418 | AL38: =IFERROR((AG38-AH38)/ABS(AH38),0) -> 0.69532886 | AM38: =IFERROR((AG38-AI38)/ABS(AI38),0) -> 0.24468098 | AO38: =SUMIFS('P&L Data'!$N:$N,'P&L Data'!$B:$B,$D38,'P&L Data'!$C:$C,$AO$4) -> -633.83064 | AP38: =SUMIFS('P&L Data'!$P:$P,'P&L Data'!$B:$B,$D38,'P&L Data'!$C:$C,$AO$4) -> -671.68992 | AQ38: =SUMIFS('P&L Data'!$T:$T,'P&L Data'!$B:$B,$D38,'P&L Data'!$C:$C,$AO$4) -> -634.89065 | AR38: =AO38-AP38 -> 37.85928 | AS38: =AO38-AQ38 -> 1.06001 | AT38: =IFERROR((AO38-AP38)/ABS(AP38),0) -> 0.056364222 | AU38: =IFERROR((AO38-AQ38)/ABS(AQ38),0) -> 0.0016695946 | AW38: =SUMIFS('P&L Data'!$N:$N,'P&L Data'!$B:$B,$D38,'P&L Data'!$C:$C,$AW$4) -> 6888.4778 | AX38: =SUMIFS('P&L Data'!$P:$P,'P&L Data'!$B:$B,$D38,'P&L Data'!$C:$C,$AW$4) -> 7526.5132 | AY38: =SUMIFS('P&L Data'!$T:$T,'P&L Data'!$B:$B,$D38,'P&L Data'!$C:$C,$AW$4) -> 6637.3673 | AZ38: =AW38-AX38 -> -638.03538 | BA38: =AW38-AY38 -> 251.11045 | BB38: =IFERROR((AW38-AX38)/ABS(AX38),0) -> -0.084771709 | BC38: =IFERROR((AW38-AY38)/ABS(AY38),0) -> 0.03783284 | BE38: =SUMIFS('P&L Data'!$N:$N,'P&L Data'!$B:$B,$D38,'P&L Data'!$C:$C,$BE$4) -> -2163.5315 | BF38: =SUMIFS('P&L Data'!$P:$P,'P&L Data'!$B:$B,$D38,'P&L Data'!$C:$C,$BE$4) -> -2331.3335 | BG38: =SUMIFS('P&L Data'!$T:$T,'P&L Data'!$B:$B,$D38,'P&L Data'!$C:$C,$BE$4) -> -2259.5549 | BH38: =BE38-BF38 -> 167.80198 | BI38: =BE38-BG38 -> 96.02338 | BJ38: =IFERROR((BE38-BF38)/ABS(BF38),0) -> 0.071976823 | BK38: =IFERROR((BE38-BG38)/ABS(BG38),0) -> 0.04249659 | BM38: =SUMIFS('P&L Data'!$N:$N,'P&L Data'!$B:$B,$D38,'P&L Data'!$C:$C,$BM$4) -> -741.55259 | BN38: =SUMIFS('P&L Data'!$P:$P,'P&L Data'!$B:$B,$D38,'P&L Data'!$C:$C,$BM$4) -> -689.0602 | BO38: =SUMIFS('P&L Data'!$T:$T,'P&L Data'!$B:$B,$D38,'P&L Data'!$C:$C,$BM$4) -> -744.86756 | BP38: =BM38-BN38 -> -52.49239 | BQ38: =BM38-BO38 -> 3.31497 | BR38: =IFERROR((BM38-BN38)/ABS(BN38),0) -> -0.076179686 | BS38: =IFERROR((BM38-BO38)/ABS(BO38),0) -> 0.0044504153 | BU38: =SUMIFS('P&L Data'!$N:$N,'P&L Data'!$B:$B,$D38,'P&L Data'!$C:$C,$BU$4) -> -500 | BV38: =SUMIFS('P&L Data'!$P:$P,'P&L Data'!$B:$B,$D38,'P&L Data'!$C:$C,$BU$4) -> -500 | BW38: =SUMIFS('P&L Data'!$T:$T,'P&L Data'!$B:$B,$D38,'P&L Data'!$C:$C,$BU$4) -> -500 | BX38: =BU38-BV38 -> 0 | BY38: =BU38-BW38 -> 0 | BZ38: =IFERROR((BU38-BV38)/ABS(BV38),0) -> 0 | CA38: =IFERROR((BU38-BW38)/ABS(BW38),0) -> 0 | CC38: =SUMIFS('P&L Data'!$N:$N,'P&L Data'!$B:$B,$D38,'P&L Data'!$C:$C,$CC$4) -> 3483.3936 | CD38: =SUMIFS('P&L Data'!$P:$P,'P&L Data'!$B:$B,$D38,'P&L Data'!$C:$C,$CC$4) -> 4006.1194 | CE38: =SUMIFS('P&L Data'!$T:$T,'P&L Data'!$B:$B,$D38,'P&L Data'!$C:$C,$CC$4) -> 3132.9448 | CF38: =CC38-CD38 -> -522.72579 | CG38: =CC38-CE38 -> 350.4488 | CH38: =IFERROR((CC38-CD38)/ABS(CD38),0) -> -0.13048183 | CI38: =IFERROR((CC38-CE38)/ABS(CE38),0) -> 0.11185923 | CK38: =SUMIFS('P&L Data'!$N:$N,'P&L Data'!$B:$B,$D38,'P&L Data'!$C:$C,$CK$4) -> -957.73337 | CL38: =SUMIFS('P&L Data'!$P:$P,'P&L Data'!$B:$B,$D38,'P&L Data'!$C:$C,$CK$4) -> -870.50151 | CM38: =SUMIFS('P&L Data'!$T:$T,'P&L Data'!$B:$B,$D38,'P&L Data'!$C:$C,$CK$4) -> -915.96396 | CN38: =CK38-CL38 -> -87.23186 | CO38: =CK38-CM38 -> -41.76941 | CP38: =IFERROR((CK38-CL38)/ABS(CL38),0) -> -0.10020874 | CQ38: =IFERROR((CK38-CM38)/ABS(CM38),0) -> -0.045601587 | CS38: =SUMIFS('P&L Data'!$N:$N,'P&L Data'!$B:$B,$D38,'P&L Data'!$C:$C,$CS$4) -> 2525.6603 | CT38: =SUMIFS('P&L Data'!$P:$P,'P&L Data'!$B:$B,$D38,'P&L Data'!$C:$C,$CS$4) -> 3135.6179 | CU38: =SUMIFS('P&L Data'!$T:$T,'P&L Data'!$B:$B,$D38,'P&L Data'!$C:$C,$CS$4) -> 2216.9809 | CV38: =CS38-CT38 -> -609.95765 | CW38: =CS38-CU38 -> 308.67939 | CX38: =IFERROR((CS38-CT38)/ABS(CT38),0) -> -0.1945255 | CY38: =IFERROR((CS38-CU38)/ABS(CU38),0) -> 0.13923413
B39: West | C39: Western - South | D39: 20010 | E39: Al Malaika Mall Taif | F39: Hyper | G39: LFL | I39: =SUMIFS('P&L Data'!$N:$N,'P&L Data'!$B:$B,$D39,'P&L Data'!$C:$C,$I$4) -> 37618.89 | J39: =SUMIFS('P&L Data'!$P:$P,'P&L Data'!$B:$B,$D39,'P&L Data'!$C:$C,$I$4) -> 39215.074 | K39: =SUMIFS('P&L Data'!$T:$T,'P&L Data'!$B:$B,$D39,'P&L Data'!$C:$C,$I$4) -> 39150.64 | L39: =I39-J39 -> -1596.1838 | M39: =I39-K39 -> -1531.7499 | N39: =IFERROR((I39-J39)/ABS(J39),0) -> -0.040703322 | O39: =IFERROR((I39-K39)/ABS(K39),0) -> -0.039124518 | Q39: =SUMIFS('P&L Data'!$N:$N,'P&L Data'!$B:$B,$D39,'P&L Data'!$C:$C,$Q$4) -> -853.72754 | R39: =SUMIFS('P&L Data'!$P:$P,'P&L Data'!$B:$B,$D39,'P&L Data'!$C:$C,$Q$4) -> 615.88527 | S39: =SUMIFS('P&L Data'!$T:$T,'P&L Data'!$B:$B,$D39,'P&L Data'!$C:$C,$Q$4) -> -900.55047 | T39: =Q39-R39 -> -1469.6128 | U39: =Q39-S39 -> 46.822927 | V39: =IFERROR((Q39-R39)/ABS(R39),0) -> -2.3861795 | W39: =IFERROR((Q39-S39)/ABS(S39),0) -> 0.051993673 | Y39: =SUMIFS('P&L Data'!$N:$N,'P&L Data'!$B:$B,$D39,'P&L Data'!$C:$C,$Y$4) -> 7099.8585 | Z39: =SUMIFS('P&L Data'!$P:$P,'P&L Data'!$B:$B,$D39,'P&L Data'!$C:$C,$Y$4) -> 8619.9685 | AA39: =SUMIFS('P&L Data'!$T:$T,'P&L Data'!$B:$B,$D39,'P&L Data'!$C:$C,$Y$4) -> 6662.3869 | AB39: =Y39-Z39 -> -1520.11 | AC39: =Y39-AA39 -> 437.47166 | AD39: =IFERROR((Y39-Z39)/ABS(Z39),0) -> -0.17634751 | AE39: =IFERROR((Y39-AA39)/ABS(AA39),0) -> 0.065662903 | AG39: =SUMIFS('P&L Data'!$N:$N,'P&L Data'!$B:$B,$D39,'P&L Data'!$C:$C,$AG$4) -> -97.37184 | AH39: =SUMIFS('P&L Data'!$P:$P,'P&L Data'!$B:$B,$D39,'P&L Data'!$C:$C,$AG$4) -> -265.52706 | AI39: =SUMIFS('P&L Data'!$T:$T,'P&L Data'!$B:$B,$D39,'P&L Data'!$C:$C,$AG$4) -> -123.63538 | AJ39: =AG39-AH39 -> 168.15522 | AK39: =AG39-AI39 -> 26.26354 | AL39: =IFERROR((AG39-AH39)/ABS(AH39),0) -> 0.63328845 | AM39: =IFERROR((AG39-AI39)/ABS(AI39),0) -> 0.21242738 | AO39: =SUMIFS('P&L Data'!$N:$N,'P&L Data'!$B:$B,$D39,'P&L Data'!$C:$C,$AO$4) -> -659.09394 | AP39: =SUMIFS('P&L Data'!$P:$P,'P&L Data'!$B:$B,$D39,'P&L Data'!$C:$C,$AO$4) -> -714.27624 | AQ39: =SUMIFS('P&L Data'!$T:$T,'P&L Data'!$B:$B,$D39,'P&L Data'!$C:$C,$AO$4) -> -645.04706 | AR39: =AO39-AP39 -> 55.1823 | AS39: =AO39-AQ39 -> -14.046882 | AT39: =IFERROR((AO39-AP39)/ABS(AP39),0) -> 0.077256245 | AU39: =IFERROR((AO39-AQ39)/ABS(AQ39),0) -> -0.021776523 | AW39: =SUMIFS('P&L Data'!$N:$N,'P&L Data'!$B:$B,$D39,'P&L Data'!$C:$C,$AW$4) -> 6343.3928 | AX39: =SUMIFS('P&L Data'!$P:$P,'P&L Data'!$B:$B,$D39,'P&L Data'!$C:$C,$AW$4) -> 7640.1652 | AY39: =SUMIFS('P&L Data'!$T:$T,'P&L Data'!$B:$B,$D39,'P&L Data'!$C:$C,$AW$4) -> 5893.7045 | AZ39: =AW39-AX39 -> -1296.7725 | BA39: =AW39-AY39 -> 449.68832 | BB39: =IFERROR((AW39-AX39)/ABS(AX39),0) -> -0.16973095 | BC39: =IFERROR((AW39-AY39)/ABS(AY39),0) -> 0.076299774 | BE39: =SUMIFS('P&L Data'!$N:$N,'P&L Data'!$B:$B,$D39,'P&L Data'!$C:$C,$BE$4) -> -2324.238 | BF39: =SUMIFS('P&L Data'!$P:$P,'P&L Data'!$B:$B,$D39,'P&L Data'!$C:$C,$BE$4) -> -2314.4812 | BG39: =SUMIFS('P&L Data'!$T:$T,'P&L Data'!$B:$B,$D39,'P&L Data'!$C:$C,$BE$4) -> -2353.9712 | BH39: =BE39-BF39 -> -9.75679 | BI39: =BE39-BG39 -> 29.73316 | BJ39: =IFERROR((BE39-BF39)/ABS(BF39),0) -> -0.0042155408 | BK39: =IFERROR((BE39-BG39)/ABS(BG39),0) -> 0.012631064 | BM39: =SUMIFS('P&L Data'!$N:$N,'P&L Data'!$B:$B,$D39,'P&L Data'!$C:$C,$BM$4) -> -775.83135 | BN39: =SUMIFS('P&L Data'!$P:$P,'P&L Data'!$B:$B,$D39,'P&L Data'!$C:$C,$BM$4) -> -824.36725 | BO39: =SUMIFS('P&L Data'!$T:$T,'P&L Data'!$B:$B,$D39,'P&L Data'!$C:$C,$BM$4) -> -790.78178 | BP39: =BM39-BN39 -> 48.5359 | BQ39: =BM39-BO39 -> 14.95043 | BR39: =IFERROR((BM39-BN39)/ABS(BN39),0) -> 0.05887655 | BS39: =IFERROR((BM39-BO39)/ABS(BO39),0) -> 0.018905886 | BU39: =SUMIFS('P&L Data'!$N:$N,'P&L Data'!$B:$B,$D39,'P&L Data'!$C:$C,$BU$4) -> -861.44931 | BV39: =SUMIFS('P&L Data'!$P:$P,'P&L Data'!$B:$B,$D39,'P&L Data'!$C:$C,$BU$4) -> -813.76024 | BW39: =SUMIFS('P&L Data'!$T:$T,'P&L Data'!$B:$B,$D39,'P&L Data'!$C:$C,$BU$4) -> -813.76024 | BX39: =BU39-BV39 -> -47.68907 | BY39: =BU39-BW39 -> -47.68907 | BZ39: =IFERROR((BU39-BV39)/ABS(BV39),0) -> -0.058603342 | CA39: =IFERROR((BU39-BW39)/ABS(BW39),0) -> -0.058603342 | CC39: =SUMIFS('P&L Data'!$N:$N,'P&L Data'!$B:$B,$D39,'P&L Data'!$C:$C,$CC$4) -> 2381.8741 | CD39: =SUMIFS('P&L Data'!$P:$P,'P&L Data'!$B:$B,$D39,'P&L Data'!$C:$C,$CC$4) -> 3687.5565 | CE39: =SUMIFS('P&L Data'!$T:$T,'P&L Data'!$B:$B,$D39,'P&L Data'!$C:$C,$CC$4) -> 1935.1912 | CF39: =CC39-CD39 -> -1305.6824 | CG39: =CC39-CE39 -> 446.68284 | CH39: =IFERROR((CC39-CD39)/ABS(CD39),0) -> -0.35407794 | CI39: =IFERROR((CC39-CE39)/ABS(CE39),0) -> 0.23082103 | CK39: =SUMIFS('P&L Data'!$N:$N,'P&L Data'!$B:$B,$D39,'P&L Data'!$C:$C,$CK$4) -> -795.98283 | CL39: =SUMIFS('P&L Data'!$P:$P,'P&L Data'!$B:$B,$D39,'P&L Data'!$C:$C,$CK$4) -> -774.10019 | CM39: =SUMIFS('P&L Data'!$T:$T,'P&L Data'!$B:$B,$D39,'P&L Data'!$C:$C,$CK$4) -> -572.33367 | CN39: =CK39-CL39 -> -21.88264 | CO39: =CK39-CM39 -> -223.64916 | CP39: =IFERROR((CK39-CL39)/ABS(CL39),0) -> -0.028268486 | CQ39: =IFERROR((CK39-CM39)/ABS(CM39),0) -> -0.39076709 | CS39: =SUMIFS('P&L Data'!$N:$N,'P&L Data'!$B:$B,$D39,'P&L Data'!$C:$C,$CS$4) -> 1585.8912 | CT39: =SUMIFS('P&L Data'!$P:$P,'P&L Data'!$B:$B,$D39,'P&L Data'!$C:$C,$CS$4) -> 2913.4563 | CU39: =SUMIFS('P&L Data'!$T:$T,'P&L Data'!$B:$B,$D39,'P&L Data'!$C:$C,$CS$4) -> 1362.8576 | CV39: =CS39-CT39 -> -1327.5651 | CW39: =CS39-CU39 -> 223.03368 | CX39: =IFERROR((CS39-CT39)/ABS(CT39),0) -> -0.45566671 | CY39: =IFERROR((CS39-CU39)/ABS(CU39),0) -> 0.16365149
B40: West | C40: Western - South Total | I40: =SUBTOTAL(9,I38:I39) -> 73571.434 | J40: =SUBTOTAL(9,J38:J39) -> 76200.378 | K40: =SUBTOTAL(9,K38:K39) -> 76762.546 | L40: =I40-J40 -> -2628.9441 | M40: =I40-K40 -> -3191.1117 | N40: =IFERROR((I40-J40)/ABS(J40),0) -> -0.034500407 | O40: =IFERROR((I40-K40)/ABS(K40),0) -> -0.041571207 | Q40: =SUBTOTAL(9,Q38:Q39) -> -615.29974 | R40: =SUBTOTAL(9,R38:R39) -> 1753.5886 | S40: =SUBTOTAL(9,S38:S39) -> -541.60548 | T40: =Q40-R40 -> -2368.8883 | U40: =Q40-S40 -> -73.69426 | V40: =IFERROR((Q40-R40)/ABS(R40),0) -> -1.3508803 | W40: =IFERROR((Q40-S40)/ABS(S40),0) -> -0.13606631 | Y40: =SUBTOTAL(9,Y38:Y39) -> 14696.174 | Z40: =SUBTOTAL(9,Z38:Z39) -> 17061.08 | AA40: =SUBTOTAL(9,AA38:AA39) -> 14032.626 | AB40: =Y40-Z40 -> -2364.9059 | AC40: =Y40-AA40 -> 663.54792 | AD40: =IFERROR((Y40-Z40)/ABS(Z40),0) -> -0.13861408 | AE40: =IFERROR((Y40-AA40)/ABS(AA40),0) -> 0.047286083 | AG40: =SUBTOTAL(9,AG38:AG39) -> -171.37904 | AH40: =SUBTOTAL(9,AH38:AH39) -> -508.43553 | AI40: =SUBTOTAL(9,AI38:AI39) -> -221.61676 | AJ40: =AG40-AH40 -> 337.05649 | AK40: =AG40-AI40 -> 50.23772 | AL40: =IFERROR((AG40-AH40)/ABS(AH40),0) -> 0.66292867 | AM40: =IFERROR((AG40-AI40)/ABS(AI40),0) -> 0.22668737 | AO40: =SUBTOTAL(9,AO38:AO39) -> -1292.9246 | AP40: =SUBTOTAL(9,AP38:AP39) -> -1385.9662 | AQ40: =SUBTOTAL(9,AQ38:AQ39) -> -1279.9377 | AR40: =AO40-AP40 -> 93.04158 | AS40: =AO40-AQ40 -> -12.986872 | AT40: =IFERROR((AO40-AP40)/ABS(AP40),0) -> 0.067131206 | AU40: =IFERROR((AO40-AQ40)/ABS(AQ40),0) -> -0.010146488 | AW40: =SUBTOTAL(9,AW38:AW39) -> 13231.871 | AX40: =SUBTOTAL(9,AX38:AX39) -> 15166.678 | AY40: =SUBTOTAL(9,AY38:AY39) -> 12531.072 | AZ40: =AW40-AX40 -> -1934.8079 | BA40: =AW40-AY40 -> 700.79877 | BB40: =IFERROR((AW40-AX40)/ABS(AX40),0) -> -0.12756965 | BC40: =IFERROR((AW40-AY40)/ABS(AY40),0) -> 0.055924887 | BE40: =SUBTOTAL(9,BE38:BE39) -> -4487.7696 | BF40: =SUBTOTAL(9,BF38:BF39) -> -4645.8148 | BG40: =SUBTOTAL(9,BG38:BG39) -> -4613.5261 | BH40: =BE40-BF40 -> 158.04519 | BI40: =BE40-BG40 -> 125.75654 | BJ40: =IFERROR((BE40-BF40)/ABS(BF40),0) -> 0.034018832 | BK40: =IFERROR((BE40-BG40)/ABS(BG40),0) -> 0.027258227 | BM40: =SUBTOTAL(9,BM38:BM39) -> -1517.3839 | BN40: =SUBTOTAL(9,BN38:BN39) -> -1513.4275 | BO40: =SUBTOTAL(9,BO38:BO39) -> -1535.6493 | BP40: =BM40-BN40 -> -3.95649 | BQ40: =BM40-BO40 -> 18.2654 | BR40: =IFERROR((BM40-BN40)/ABS(BN40),0) -> -0.0026142581 | BS40: =IFERROR((BM40-BO40)/ABS(BO40),0) -> 0.011894252 | BU40: =SUBTOTAL(9,BU38:BU39) -> -1361.4493 | BV40: =SUBTOTAL(9,BV38:BV39) -> -1313.7602 | BW40: =SUBTOTAL(9,BW38:BW39) -> -1313.7602 | BX40: =BU40-BV40 -> -47.68907 | BY40: =BU40-BW40 -> -47.68907 | BZ40: =IFERROR((BU40-BV40)/ABS(BV40),0) -> -0.036299675 | CA40: =IFERROR((BU40-BW40)/ABS(BW40),0) -> -0.036299675 | CC40: =SUBTOTAL(9,CC38:CC39) -> 5865.2677 | CD40: =SUBTOTAL(9,CD38:CD39) -> 7693.6759 | CE40: =SUBTOTAL(9,CE38:CE39) -> 5068.1361 | CF40: =CC40-CD40 -> -1828.4082 | CG40: =CC40-CE40 -> 797.13164 | CH40: =IFERROR((CC40-CD40)/ABS(CD40),0) -> -0.2376508 | CI40: =IFERROR((CC40-CE40)/ABS(CE40),0) -> 0.157283 | CK40: =SUBTOTAL(9,CK38:CK39) -> -1753.7162 | CL40: =SUBTOTAL(9,CL38:CL39) -> -1644.6017 | CM40: =SUBTOTAL(9,CM38:CM39) -> -1488.2976 | CN40: =CK40-CL40 -> -109.1145 | CO40: =CK40-CM40 -> -265.41857 | CP40: =IFERROR((CK40-CL40)/ABS(CL40),0) -> -0.066347067 | CQ40: =IFERROR((CK40-CM40)/ABS(CM40),0) -> -0.17833702 | CS40: =SUBTOTAL(9,CS38:CS39) -> 4111.5515 | CT40: =SUBTOTAL(9,CT38:CT39) -> 6049.0742 | CU40: =SUBTOTAL(9,CU38:CU39) -> 3579.8384 | CV40: =SUBTOTAL(9,CV38:CV39) -> -1937.5227 | CW40: =SUBTOTAL(9,CW38:CW39) -> 531.71307 | CX40: =IFERROR((CS40-CT40)/ABS(CT40),0) -> -0.3203007 | CY40: =IFERROR((CS40-CU40)/ABS(CU40),0) -> 0.14852991
B41: West Total | I41: =SUBTOTAL(9,I32:I40) -> 224157.44 | J41: =SUBTOTAL(9,J32:J40) -> 239406.68 | K41: =SUBTOTAL(9,K32:K40) -> 252576.18 | L41: =I41-J41 -> -15249.243 | M41: =I41-K41 -> -28418.739 | N41: =IFERROR((I41-J41)/ABS(J41),0) -> -0.063695977 | O41: =IFERROR((I41-K41)/ABS(K41),0) -> -0.11251552 | Q41: =SUBTOTAL(9,Q32:Q40) -> 6415.6269 | R41: =SUBTOTAL(9,R32:R40) -> 11038.552 | S41: =SUBTOTAL(9,S32:S40) -> 10032.928 | T41: =Q41-R41 -> -4622.9252 | U41: =Q41-S41 -> -3617.3013 | V41: =IFERROR((Q41-R41)/ABS(R41),0) -> -0.41879815 | W41: =IFERROR((Q41-S41)/ABS(S41),0) -> -0.36054293 | Y41: =SUBTOTAL(9,Y32:Y40) -> 51294.894 | Z41: =SUBTOTAL(9,Z32:Z40) -> 57314.284 | AA41: =SUBTOTAL(9,AA32:AA40) -> 55774.253 | AB41: =Y41-Z41 -> -6019.3895 | AC41: =Y41-AA41 -> -4479.3584 | AD41: =IFERROR((Y41-Z41)/ABS(Z41),0) -> -0.10502425 | AE41: =IFERROR((Y41-AA41)/ABS(AA41),0) -> -0.080312298 | AG41: =SUBTOTAL(9,AG32:AG40) -> -742.99829 | AH41: =SUBTOTAL(9,AH32:AH40) -> -1448.5901 | AI41: =SUBTOTAL(9,AI32:AI40) -> -1042.6852 | AJ41: =AG41-AH41 -> 705.59179 | AK41: =AG41-AI41 -> 299.68687 | AL41: =IFERROR((AG41-AH41)/ABS(AH41),0) -> 0.48708865 | AM41: =IFERROR((AG41-AI41)/ABS(AI41),0) -> 0.28741837 | AO41: =SUBTOTAL(9,AO32:AO40) -> -3908.8573 | AP41: =SUBTOTAL(9,AP32:AP40) -> -4403.9833 | AQ41: =SUBTOTAL(9,AQ32:AQ40) -> -4121.5665 | AR41: =AO41-AP41 -> 495.12595 | AS41: =AO41-AQ41 -> 212.70923 | AT41: =IFERROR((AO41-AP41)/ABS(AP41),0) -> 0.11242685 | AU41: =IFERROR((AO41-AQ41)/ABS(AQ41),0) -> 0.05160883 | AW41: =SUBTOTAL(9,AW32:AW40) -> 46643.039 | AX41: =SUBTOTAL(9,AX32:AX40) -> 51461.711 | AY41: =SUBTOTAL(9,AY32:AY40) -> 50610.001 | AZ41: =AW41-AX41 -> -4818.6717 | BA41: =AW41-AY41 -> -3966.9623 | BB41: =IFERROR((AW41-AX41)/ABS(AX41),0) -> -0.093636058 | BC41: =IFERROR((AW41-AY41)/ABS(AY41),0) -> -0.078382972 | BE41: =SUBTOTAL(9,BE32:BE40) -> -15811.977 | BF41: =SUBTOTAL(9,BF32:BF40) -> -16003.496 | BG41: =SUBTOTAL(9,BG32:BG40) -> -16195.707 | BH41: =BE41-BF41 -> 191.51898 | BI41: =BE41-BG41 -> 383.7308 | BJ41: =IFERROR((BE41-BF41)/ABS(BF41),0) -> 0.011967322 | BK41: =IFERROR((BE41-BG41)/ABS(BG41),0) -> 0.023693365 | BM41: =SUBTOTAL(9,BM32:BM40) -> -5625.9663 | BN41: =SUBTOTAL(9,BN32:BN40) -> -5799.7911 | BO41: =SUBTOTAL(9,BO32:BO40) -> -6338.7466 | BP41: =BM41-BN41 -> 173.82487 | BQ41: =BM41-BO41 -> 712.7803 | BR41: =IFERROR((BM41-BN41)/ABS(BN41),0) -> 0.029970884 | BS41: =IFERROR((BM41-BO41)/ABS(BO41),0) -> 0.11244815 | BU41: =SUBTOTAL(9,BU32:BU40) -> -8471.4813 | BV41: =SUBTOTAL(9,BV32:BV40) -> -8423.7922 | BW41: =SUBTOTAL(9,BW32:BW40) -> -8423.7922 | BX41: =BU41-BV41 -> -47.68907 | BY41: =BU41-BW41 -> -47.68907 | BZ41: =IFERROR((BU41-BV41)/ABS(BV41),0) -> -0.0056612353 | CA41: =IFERROR((BU41-BW41)/ABS(BW41),0) -> -0.0056612353 | CC41: =SUBTOTAL(9,CC32:CC40) -> 16733.615 | CD41: =SUBTOTAL(9,CD32:CD40) -> 21234.632 | CE41: =SUBTOTAL(9,CE32:CE40) -> 19651.755 | CF41: =CC41-CD41 -> -4501.017 | CG41: =CC41-CE41 -> -2918.1403 | CH41: =IFERROR((CC41-CD41)/ABS(CD41),0) -> -0.21196586 | CI41: =IFERROR((CC41-CE41)/ABS(CE41),0) -> -0.1484926 | CK41: =SUBTOTAL(9,CK32:CK40) -> -5136.6112 | CL41: =SUBTOTAL(9,CL32:CL40) -> -5259.8437 | CM41: =SUBTOTAL(9,CM32:CM40) -> -4450.7778 | CN41: =CK41-CL41 -> 123.23245 | CO41: =CK41-CM41 -> -685.83344 | CP41: =IFERROR((CK41-CL41)/ABS(CL41),0) -> 0.023428919 | CQ41: =IFERROR((CK41-CM41)/ABS(CM41),0) -> -0.15409294 | CS41: =SUBTOTAL(9,CS32:CS40) -> 11597.003 | CT41: =SUBTOTAL(9,CT32:CT40) -> 15974.788 | CU41: =SUBTOTAL(9,CU32:CU40) -> 15200.977 | CV41: =CS41-CT41 -> -4377.7845 | CW41: =CS41-CU41 -> -3603.9737 | CX41: =IFERROR((CS41-CT41)/ABS(CT41),0) -> -0.27404336 | CY41: =IFERROR((CS41-CU41)/ABS(CU41),0) -> -0.23708829
B42: North | C42: North | D42: 501 | E42: King Abdulaziz Road, Tabuk | F42: Super | G42: LFL | I42: =SUMIFS('P&L Data'!$N:$N,'P&L Data'!$B:$B,$D42,'P&L Data'!$C:$C,$I$4) -> 23340.933 | J42: =SUMIFS('P&L Data'!$P:$P,'P&L Data'!$B:$B,$D42,'P&L Data'!$C:$C,$I$4) -> 20939.725 | K42: =SUMIFS('P&L Data'!$T:$T,'P&L Data'!$B:$B,$D42,'P&L Data'!$C:$C,$I$4) -> 20319.704 | L42: =I42-J42 -> 2401.2076 | M42: =I42-K42 -> 3021.2286 | N42: =IFERROR((I42-J42)/ABS(J42),0) -> 0.11467235 | O42: =IFERROR((I42-K42)/ABS(K42),0) -> 0.14868467 | Q42: =SUMIFS('P&L Data'!$N:$N,'P&L Data'!$B:$B,$D42,'P&L Data'!$C:$C,$Q$4) -> 304.98234 | R42: =SUMIFS('P&L Data'!$P:$P,'P&L Data'!$B:$B,$D42,'P&L Data'!$C:$C,$Q$4) -> 857.91122 | S42: =SUMIFS('P&L Data'!$T:$T,'P&L Data'!$B:$B,$D42,'P&L Data'!$C:$C,$Q$4) -> 504.43523 | T42: =Q42-R42 -> -552.92888 | U42: =Q42-S42 -> -199.45289 | V42: =IFERROR((Q42-R42)/ABS(R42),0) -> -0.64450594 | W42: =IFERROR((Q42-S42)/ABS(S42),0) -> -0.39539841 | Y42: =SUMIFS('P&L Data'!$N:$N,'P&L Data'!$B:$B,$D42,'P&L Data'!$C:$C,$Y$4) -> 5162.1799 | Z42: =SUMIFS('P&L Data'!$P:$P,'P&L Data'!$B:$B,$D42,'P&L Data'!$C:$C,$Y$4) -> 4952.0237 | AA42: =SUMIFS('P&L Data'!$T:$T,'P&L Data'!$B:$B,$D42,'P&L Data'!$C:$C,$Y$4) -> 4267.0561 | AB42: =Y42-Z42 -> 210.15627 | AC42: =Y42-AA42 -> 895.12383 | AD42: =IFERROR((Y42-Z42)/ABS(Z42),0) -> 0.042438462 | AE42: =IFERROR((Y42-AA42)/ABS(AA42),0) -> 0.2097755 | AG42: =SUMIFS('P&L Data'!$N:$N,'P&L Data'!$B:$B,$D42,'P&L Data'!$C:$C,$AG$4) -> -88.61656 | AH42: =SUMIFS('P&L Data'!$P:$P,'P&L Data'!$B:$B,$D42,'P&L Data'!$C:$C,$AG$4) -> -138.14498 | AI42: =SUMIFS('P&L Data'!$T:$T,'P&L Data'!$B:$B,$D42,'P&L Data'!$C:$C,$AG$4) -> -70.41776 | AJ42: =AG42-AH42 -> 49.52842 | AK42: =AG42-AI42 -> -18.1988 | AL42: =IFERROR((AG42-AH42)/ABS(AH42),0) -> 0.35852494 | AM42: =IFERROR((AG42-AI42)/ABS(AI42),0) -> -0.25844048 | AO42: =SUMIFS('P&L Data'!$N:$N,'P&L Data'!$B:$B,$D42,'P&L Data'!$C:$C,$AO$4) -> -384.80231 | AP42: =SUMIFS('P&L Data'!$P:$P,'P&L Data'!$B:$B,$D42,'P&L Data'!$C:$C,$AO$4) -> -380.77743 | AQ42: =SUMIFS('P&L Data'!$T:$T,'P&L Data'!$B:$B,$D42,'P&L Data'!$C:$C,$AO$4) -> -327.03028 | AR42: =AO42-AP42 -> -4.02488 | AS42: =AO42-AQ42 -> -57.77203 | AT42: =IFERROR((AO42-AP42)/ABS(AP42),0) -> -0.010570164 | AU42: =IFERROR((AO42-AQ42)/ABS(AQ42),0) -> -0.17665652 | AW42: =SUMIFS('P&L Data'!$N:$N,'P&L Data'!$B:$B,$D42,'P&L Data'!$C:$C,$AW$4) -> 4688.7611 | AX42: =SUMIFS('P&L Data'!$P:$P,'P&L Data'!$B:$B,$D42,'P&L Data'!$C:$C,$AW$4) -> 4433.1013 | AY42: =SUMIFS('P&L Data'!$T:$T,'P&L Data'!$B:$B,$D42,'P&L Data'!$C:$C,$AW$4) -> 3869.6081 | AZ42: =AW42-AX42 -> 255.65981 | BA42: =AW42-AY42 -> 819.153 | BB42: =IFERROR((AW42-AX42)/ABS(AX42),0) -> 0.057670645 | BC42: =IFERROR((AW42-AY42)/ABS(AY42),0) -> 0.21168888 | BE42: =SUMIFS('P&L Data'!$N:$N,'P&L Data'!$B:$B,$D42,'P&L Data'!$C:$C,$BE$4) -> -1295.2409 | BF42: =SUMIFS('P&L Data'!$P:$P,'P&L Data'!$B:$B,$D42,'P&L Data'!$C:$C,$BE$4) -> -1310.5516 | BG42: =SUMIFS('P&L Data'!$T:$T,'P&L Data'!$B:$B,$D42,'P&L Data'!$C:$C,$BE$4) -> -1223.4205 | BH42: =BE42-BF42 -> 15.31073 | BI42: =BE42-BG42 -> -71.82043 | BJ42: =IFERROR((BE42-BF42)/ABS(BF42),0) -> 0.011682661 | BK42: =IFERROR((BE42-BG42)/ABS(BG42),0) -> -0.058704617 | BM42: =SUMIFS('P&L Data'!$N:$N,'P&L Data'!$B:$B,$D42,'P&L Data'!$C:$C,$BM$4) -> -106.36413 | BN42: =SUMIFS('P&L Data'!$P:$P,'P&L Data'!$B:$B,$D42,'P&L Data'!$C:$C,$BM$4) -> -60.94483 | BO42: =SUMIFS('P&L Data'!$T:$T,'P&L Data'!$B:$B,$D42,'P&L Data'!$C:$C,$BM$4) -> -130.8013 | BP42: =BM42-BN42 -> -45.4193 | BQ42: =BM42-BO42 -> 24.43717 | BR42: =IFERROR((BM42-BN42)/ABS(BN42),0) -> -0.74525271 | BS42: =IFERROR((BM42-BO42)/ABS(BO42),0) -> 0.18682666 | BU42: =SUMIFS('P&L Data'!$N:$N,'P&L Data'!$B:$B,$D42,'P&L Data'!$C:$C,$BU$4) -> -1203.5197 | BV42: =SUMIFS('P&L Data'!$P:$P,'P&L Data'!$B:$B,$D42,'P&L Data'!$C:$C,$BU$4) -> -1050.206 | BW42: =SUMIFS('P&L Data'!$T:$T,'P&L Data'!$B:$B,$D42,'P&L Data'!$C:$C,$BU$4) -> -1018.1201 | BX42: =BU42-BV42 -> -153.31372 | BY42: =BU42-BW42 -> -185.39959 | BZ42: =IFERROR((BU42-BV42)/ABS(BV42),0) -> -0.14598443 | CA42: =IFERROR((BU42-BW42)/ABS(BW42),0) -> -0.18209992 | CC42: =SUMIFS('P&L Data'!$N:$N,'P&L Data'!$B:$B,$D42,'P&L Data'!$C:$C,$CC$4) -> 2083.6363 | CD42: =SUMIFS('P&L Data'!$P:$P,'P&L Data'!$B:$B,$D42,'P&L Data'!$C:$C,$CC$4) -> 2011.3988 | CE42: =SUMIFS('P&L Data'!$T:$T,'P&L Data'!$B:$B,$D42,'P&L Data'!$C:$C,$CC$4) -> 1497.2662 | CF42: =CC42-CD42 -> 72.23752 | CG42: =CC42-CE42 -> 586.37015 | CH42: =IFERROR((CC42-CD42)/ABS(CD42),0) -> 0.035914071 | CI42: =IFERROR((CC42-CE42)/ABS(CE42),0) -> 0.39162719 | CK42: =SUMIFS('P&L Data'!$N:$N,'P&L Data'!$B:$B,$D42,'P&L Data'!$C:$C,$CK$4) -> -965.68597 | CL42: =SUMIFS('P&L Data'!$P:$P,'P&L Data'!$B:$B,$D42,'P&L Data'!$C:$C,$CK$4) -> -486.06832 | CM42: =SUMIFS('P&L Data'!$T:$T,'P&L Data'!$B:$B,$D42,'P&L Data'!$C:$C,$CK$4) -> -698.51518 | CN42: =CK42-CL42 -> -479.61765 | CO42: =CK42-CM42 -> -267.17079 | CP42: =IFERROR((CK42-CL42)/ABS(CL42),0) -> -0.98672888 | CQ42: =IFERROR((CK42-CM42)/ABS(CM42),0) -> -0.38248387 | CS42: =SUMIFS('P&L Data'!$N:$N,'P&L Data'!$B:$B,$D42,'P&L Data'!$C:$C,$CS$4) -> 1117.9504 | CT42: =SUMIFS('P&L Data'!$P:$P,'P&L Data'!$B:$B,$D42,'P&L Data'!$C:$C,$CS$4) -> 1525.3305 | CU42: =SUMIFS('P&L Data'!$T:$T,'P&L Data'!$B:$B,$D42,'P&L Data'!$C:$C,$CS$4) -> 798.75102 | CV42: =CS42-CT42 -> -407.38013 | CW42: =CS42-CU42 -> 319.19936 | CX42: =IFERROR((CS42-CT42)/ABS(CT42),0) -> -0.26707663 | CY42: =IFERROR((CS42-CU42)/ABS(CU42),0) -> 0.3996231
B43: North | C43: North | D43: 50001 | E43: Aliat Al Madina | F43: Hyper | G43: LFL | I43: =SUMIFS('P&L Data'!$N:$N,'P&L Data'!$B:$B,$D43,'P&L Data'!$C:$C,$I$4) -> 49786.106 | J43: =SUMIFS('P&L Data'!$P:$P,'P&L Data'!$B:$B,$D43,'P&L Data'!$C:$C,$I$4) -> 49015.604 | K43: =SUMIFS('P&L Data'!$T:$T,'P&L Data'!$B:$B,$D43,'P&L Data'!$C:$C,$I$4) -> 48564.772 | L43: =I43-J43 -> 770.50115 | M43: =I43-K43 -> 1221.3334 | N43: =IFERROR((I43-J43)/ABS(J43),0) -> 0.015719507 | O43: =IFERROR((I43-K43)/ABS(K43),0) -> 0.025148547 | Q43: =SUMIFS('P&L Data'!$N:$N,'P&L Data'!$B:$B,$D43,'P&L Data'!$C:$C,$Q$4) -> 1304.2209 | R43: =SUMIFS('P&L Data'!$P:$P,'P&L Data'!$B:$B,$D43,'P&L Data'!$C:$C,$Q$4) -> 1755.1074 | S43: =SUMIFS('P&L Data'!$T:$T,'P&L Data'!$B:$B,$D43,'P&L Data'!$C:$C,$Q$4) -> 1522.1882 | T43: =Q43-R43 -> -450.88649 | U43: =Q43-S43 -> -217.96723 | V43: =IFERROR((Q43-R43)/ABS(R43),0) -> -0.25689965 | W43: =IFERROR((Q43-S43)/ABS(S43),0) -> -0.14319335 | Y43: =SUMIFS('P&L Data'!$N:$N,'P&L Data'!$B:$B,$D43,'P&L Data'!$C:$C,$Y$4) -> 11873.795 | Z43: =SUMIFS('P&L Data'!$P:$P,'P&L Data'!$B:$B,$D43,'P&L Data'!$C:$C,$Y$4) -> 11841.086 | AA43: =SUMIFS('P&L Data'!$T:$T,'P&L Data'!$B:$B,$D43,'P&L Data'!$C:$C,$Y$4) -> 10990.809 | AB43: =Y43-Z43 -> 32.70978 | AC43: =Y43-AA43 -> 882.98669 | AD43: =IFERROR((Y43-Z43)/ABS(Z43),0) -> 0.0027623971 | AE43: =IFERROR((Y43-AA43)/ABS(AA43),0) -> 0.080338646 | AG43: =SUMIFS('P&L Data'!$N:$N,'P&L Data'!$B:$B,$D43,'P&L Data'!$C:$C,$AG$4) -> -148.15268 | AH43: =SUMIFS('P&L Data'!$P:$P,'P&L Data'!$B:$B,$D43,'P&L Data'!$C:$C,$AG$4) -> -324.37 | AI43: =SUMIFS('P&L Data'!$T:$T,'P&L Data'!$B:$B,$D43,'P&L Data'!$C:$C,$AG$4) -> -195.80557 | AJ43: =AG43-AH43 -> 176.21732 | AK43: =AG43-AI43 -> 47.65289 | AL43: =IFERROR((AG43-AH43)/ABS(AH43),0) -> 0.54326023 | AM43: =IFERROR((AG43-AI43)/ABS(AI43),0) -> 0.24336841 | AO43: =SUMIFS('P&L Data'!$N:$N,'P&L Data'!$B:$B,$D43,'P&L Data'!$C:$C,$AO$4) -> -861.64697 | AP43: =SUMIFS('P&L Data'!$P:$P,'P&L Data'!$B:$B,$D43,'P&L Data'!$C:$C,$AO$4) -> -923.82521 | AQ43: =SUMIFS('P&L Data'!$T:$T,'P&L Data'!$B:$B,$D43,'P&L Data'!$C:$C,$AO$4) -> -823.65049 | AR43: =AO43-AP43 -> 62.17824 | AS43: =AO43-AQ43 -> -37.996475 | AT43: =IFERROR((AO43-AP43)/ABS(AP43),0) -> 0.067305199 | AU43: =IFERROR((AO43-AQ43)/ABS(AQ43),0) -> -0.046131795 | AW43: =SUMIFS('P&L Data'!$N:$N,'P&L Data'!$B:$B,$D43,'P&L Data'!$C:$C,$AW$4) -> 10863.996 | AX43: =SUMIFS('P&L Data'!$P:$P,'P&L Data'!$B:$B,$D43,'P&L Data'!$C:$C,$AW$4) -> 10592.89 | AY43: =SUMIFS('P&L Data'!$T:$T,'P&L Data'!$B:$B,$D43,'P&L Data'!$C:$C,$AW$4) -> 9971.3526 | AZ43: =AW43-AX43 -> 271.10534 | BA43: =AW43-AY43 -> 892.64311 | BB43: =IFERROR((AW43-AX43)/ABS(AX43),0) -> 0.025593141 | BC43: =IFERROR((AW43-AY43)/ABS(AY43),0) -> 0.089520764 | BE43: =SUMIFS('P&L Data'!$N:$N,'P&L Data'!$B:$B,$D43,'P&L Data'!$C:$C,$BE$4) -> -2934.2887 | BF43: =SUMIFS('P&L Data'!$P:$P,'P&L Data'!$B:$B,$D43,'P&L Data'!$C:$C,$BE$4) -> -3490.0444 | BG43: =SUMIFS('P&L Data'!$T:$T,'P&L Data'!$B:$B,$D43,'P&L Data'!$C:$C,$BE$4) -> -3183.2015 | BH43: =BE43-BF43 -> 555.75564 | BI43: =BE43-BG43 -> 248.9128 | BJ43: =IFERROR((BE43-BF43)/ABS(BF43),0) -> 0.15924028 | BK43: =IFERROR((BE43-BG43)/ABS(BG43),0) -> 0.07819574 | BM43: =SUMIFS('P&L Data'!$N:$N,'P&L Data'!$B:$B,$D43,'P&L Data'!$C:$C,$BM$4) -> -1075.0468 | BN43: =SUMIFS('P&L Data'!$P:$P,'P&L Data'!$B:$B,$D43,'P&L Data'!$C:$C,$BM$4) -> -1116.0882 | BO43: =SUMIFS('P&L Data'!$T:$T,'P&L Data'!$B:$B,$D43,'P&L Data'!$C:$C,$BM$4) -> -1056.35 | BP43: =BM43-BN43 -> 41.04132 | BQ43: =BM43-BO43 -> -18.69686 | BR43: =IFERROR((BM43-BN43)/ABS(BN43),0) -> 0.036772472 | BS43: =IFERROR((BM43-BO43)/ABS(BO43),0) -> -0.017699494 | BU43: =SUMIFS('P&L Data'!$N:$N,'P&L Data'!$B:$B,$D43,'P&L Data'!$C:$C,$BU$4) -> -1358.191 | BV43: =SUMIFS('P&L Data'!$P:$P,'P&L Data'!$B:$B,$D43,'P&L Data'!$C:$C,$BU$4) -> -1370.8812 | BW43: =SUMIFS('P&L Data'!$T:$T,'P&L Data'!$B:$B,$D43,'P&L Data'!$C:$C,$BU$4) -> -1215.729 | BX43: =BU43-BV43 -> 12.69022 | BY43: =BU43-BW43 -> -142.46203 | BZ43: =IFERROR((BU43-BV43)/ABS(BV43),0) -> 0.0092569801 | CA43: =IFERROR((BU43-BW43)/ABS(BW43),0) -> -0.11718239 | CC43: =SUMIFS('P&L Data'!$N:$N,'P&L Data'!$B:$B,$D43,'P&L Data'!$C:$C,$CC$4) -> 5496.4692 | CD43: =SUMIFS('P&L Data'!$P:$P,'P&L Data'!$B:$B,$D43,'P&L Data'!$C:$C,$CC$4) -> 4615.8767 | CE43: =SUMIFS('P&L Data'!$T:$T,'P&L Data'!$B:$B,$D43,'P&L Data'!$C:$C,$CC$4) -> 4516.0722 | CF43: =CC43-CD43 -> 880.59252 | CG43: =CC43-CE43 -> 980.39702 | CH43: =IFERROR((CC43-CD43)/ABS(CD43),0) -> 0.19077471 | CI43: =IFERROR((CC43-CE43)/ABS(CE43),0) -> 0.21709064 | CK43: =SUMIFS('P&L Data'!$N:$N,'P&L Data'!$B:$B,$D43,'P&L Data'!$C:$C,$CK$4) -> -2354.2206 | CL43: =SUMIFS('P&L Data'!$P:$P,'P&L Data'!$B:$B,$D43,'P&L Data'!$C:$C,$CK$4) -> -1080.0708 | CM43: =SUMIFS('P&L Data'!$T:$T,'P&L Data'!$B:$B,$D43,'P&L Data'!$C:$C,$CK$4) -> -980.34647 | CN43: =CK43-CL43 -> -1274.1498 | CO43: =CK43-CM43 -> -1373.8741 | CP43: =IFERROR((CK43-CL43)/ABS(CL43),0) -> -1.1796909 | CQ43: =IFERROR((CK43-CM43)/ABS(CM43),0) -> -1.4014169 | CS43: =SUMIFS('P&L Data'!$N:$N,'P&L Data'!$B:$B,$D43,'P&L Data'!$C:$C,$CS$4) -> 3142.2486 | CT43: =SUMIFS('P&L Data'!$P:$P,'P&L Data'!$B:$B,$D43,'P&L Data'!$C:$C,$CS$4) -> 3535.8058 | CU43: =SUMIFS('P&L Data'!$T:$T,'P&L Data'!$B:$B,$D43,'P&L Data'!$C:$C,$CS$4) -> 3535.7257 | CV43: =CS43-CT43 -> -393.55724 | CW43: =CS43-CU43 -> -393.47709 | CX43: =IFERROR((CS43-CT43)/ABS(CT43),0) -> -0.11130624 | CY43: =IFERROR((CS43-CU43)/ABS(CU43),0) -> -0.11128609
B44: North | C44: North Total | I44: =SUBTOTAL(9,I42:I43) -> 73127.038 | J44: =SUBTOTAL(9,J42:J43) -> 69955.33 | K44: =SUBTOTAL(9,K42:K43) -> 68884.476 | L44: =SUBTOTAL(9,L42:L43) -> 3171.7087 | M44: =SUBTOTAL(9,M42:M43) -> 4242.562 | N44: =IFERROR((I44-J44)/ABS(J44),0) -> 0.045339058 | O44: =IFERROR((I44-K44)/ABS(K44),0) -> 0.061589523 | Q44: =SUBTOTAL(9,Q42:Q43) -> 1609.2033 | R44: =SUBTOTAL(9,R42:R43) -> 2613.0187 | S44: =SUBTOTAL(9,S42:S43) -> 2026.6234 | T44: =SUBTOTAL(9,T42:T43) -> -1003.8154 | U44: =SUBTOTAL(9,U42:U43) -> -417.42012 | V44: =IFERROR((Q44-R44)/ABS(R44),0) -> -0.38415928 | W44: =IFERROR((Q44-S44)/ABS(S44),0) -> -0.20596827 | Y44: =SUBTOTAL(9,Y42:Y43) -> 17035.975 | Z44: =SUBTOTAL(9,Z42:Z43) -> 16793.109 | AA44: =SUBTOTAL(9,AA42:AA43) -> 15257.865 | AB44: =SUBTOTAL(9,AB42:AB43) -> 242.86605 | AC44: =SUBTOTAL(9,AC42:AC43) -> 1778.1105 | AD44: =IFERROR((Y44-Z44)/ABS(Z44),0) -> 0.014462244 | AE44: =IFERROR((Y44-AA44)/ABS(AA44),0) -> 0.11653731 | AG44: =SUBTOTAL(9,AG42:AG43) -> -236.76924 | AH44: =SUBTOTAL(9,AH42:AH43) -> -462.51498 | AI44: =SUBTOTAL(9,AI42:AI43) -> -266.22333 | AJ44: =SUBTOTAL(9,AJ42:AJ43) -> 225.74574 | AK44: =SUBTOTAL(9,AK42:AK43) -> 29.45409 | AL44: =IFERROR((AG44-AH44)/ABS(AH44),0) -> 0.48808309 | AM44: =IFERROR((AG44-AI44)/ABS(AI44),0) -> 0.11063677 | AO44: =SUBTOTAL(9,AO42:AO43) -> -1246.4493 | AP44: =SUBTOTAL(9,AP42:AP43) -> -1304.6026 | AQ44: =SUBTOTAL(9,AQ42:AQ43) -> -1150.6808 | AR44: =SUBTOTAL(9,AR42:AR43) -> 58.15336 | AS44: =SUBTOTAL(9,AS42:AS43) -> -95.768505 | AT44: =IFERROR((AO44-AP44)/ABS(AP44),0) -> 0.044575535 | AU44: =IFERROR((AO44-AQ44)/ABS(AQ44),0) -> -0.083227692 | AW44: =SUBTOTAL(9,AW42:AW43) -> 15552.757 | AX44: =SUBTOTAL(9,AX42:AX43) -> 15025.992 | AY44: =SUBTOTAL(9,AY42:AY43) -> 13840.961 | AZ44: =SUBTOTAL(9,AZ42:AZ43) -> 526.76515 | BA44: =SUBTOTAL(9,BA42:BA43) -> 1711.7961 | BB44: =IFERROR((AW44-AX44)/ABS(AX44),0) -> 0.035056931 | BC44: =IFERROR((AW44-AY44)/ABS(AY44),0) -> 0.1236761 | BE44: =SUBTOTAL(9,BE42:BE43) -> -4229.5296 | BF44: =SUBTOTAL(9,BF42:BF43) -> -4800.596 | BG44: =SUBTOTAL(9,BG42:BG43) -> -4406.622 | BH44: =SUBTOTAL(9,BH42:BH43) -> 571.06637 | BI44: =SUBTOTAL(9,BI42:BI43) -> 177.09237 | BJ44: =IFERROR((BE44-BF44)/ABS(BF44),0) -> 0.11895739 | BK44: =IFERROR((BE44-BG44)/ABS(BG44),0) -> 0.040187783 | BM44: =SUBTOTAL(9,BM42:BM43) -> -1181.411 | BN44: =SUBTOTAL(9,BN42:BN43) -> -1177.033 | BO44: =SUBTOTAL(9,BO42:BO43) -> -1187.1513 | BP44: =SUBTOTAL(9,BP42:BP43) -> -4.37798 | BQ44: =SUBTOTAL(9,BQ42:BQ43) -> 5.74031 | BR44: =IFERROR((BM44-BN44)/ABS(BN44),0) -> -0.003719505 | BS44: =IFERROR((BM44-BO44)/ABS(BO44),0) -> 0.0048353653 | BU44: =SUBTOTAL(9,BU42:BU43) -> -2561.7107 | BV44: =SUBTOTAL(9,BV42:BV43) -> -2421.0872 | BW44: =SUBTOTAL(9,BW42:BW43) -> -2233.8491 | BX44: =SUBTOTAL(9,BX42:BX43) -> -140.6235 | BY44: =SUBTOTAL(9,BY42:BY43) -> -327.86162 | BZ44: =IFERROR((BU44-BV44)/ABS(BV44),0) -> -0.058082791 | CA44: =IFERROR((BU44-BW44)/ABS(BW44),0) -> -0.14676982 | CC44: =SUBTOTAL(9,CC42:CC43) -> 7580.1055 | CD44: =SUBTOTAL(9,CD42:CD43) -> 6627.2755 | CE44: =SUBTOTAL(9,CE42:CE43) -> 6013.3384 | CF44: =SUBTOTAL(9,CF42:CF43) -> 952.83004 | CG44: =SUBTOTAL(9,CG42:CG43) -> 1566.7672 | CH44: =IFERROR((CC44-CD44)/ABS(CD44),0) -> 0.14377402 | CI44: =IFERROR((CC44-CE44)/ABS(CE44),0) -> 0.26054865 | CK44: =SUBTOTAL(9,CK42:CK43) -> -3319.9066 | CL44: =SUBTOTAL(9,CL42:CL43) -> -1566.1391 | CM44: =SUBTOTAL(9,CM42:CM43) -> -1678.8617 | CN44: =SUBTOTAL(9,CN42:CN43) -> -1753.7674 | CO44: =SUBTOTAL(9,CO42:CO43) -> -1641.0449 | CP44: =IFERROR((CK44-CL44)/ABS(CL44),0) -> -1.1198031 | CQ44: =IFERROR((CK44-CM44)/ABS(CM44),0) -> -0.97747477 | CS44: =SUBTOTAL(9,CS42:CS43) -> 4260.199 | CT44: =SUBTOTAL(9,CT42:CT43) -> 5061.1364 | CU44: =SUBTOTAL(9,CU42:CU43) -> 4334.4767 | CV44: =SUBTOTAL(9,CV42:CV43) -> -800.93737 | CW44: =SUBTOTAL(9,CW42:CW43) -> -74.277734 | CX44: =IFERROR((CS44-CT44)/ABS(CT44),0) -> -0.15825248 | CY44: =IFERROR((CS44-CU44)/ABS(CU44),0) -> -0.017136494
B45: North Total | I45: =SUBTOTAL(9,I42:I44) -> 73127.038 | J45: =SUBTOTAL(9,J42:J44) -> 69955.33 | K45: =SUBTOTAL(9,K42:K44) -> 68884.476 | L45: =I45-J45 -> 3171.7087 | M45: =I45-K45 -> 4242.562 | N45: =IFERROR((I45-J45)/ABS(J45),0) -> 0.045339058 | O45: =IFERROR((I45-K45)/ABS(K45),0) -> 0.061589523 | Q45: =SUBTOTAL(9,Q42:Q44) -> 1609.2033 | R45: =SUBTOTAL(9,R42:R44) -> 2613.0187 | S45: =SUBTOTAL(9,S42:S44) -> 2026.6234 | T45: =Q45-R45 -> -1003.8154 | U45: =Q45-S45 -> -417.42012 | V45: =IFERROR((Q45-R45)/ABS(R45),0) -> -0.38415928 | W45: =IFERROR((Q45-S45)/ABS(S45),0) -> -0.20596827 | Y45: =SUBTOTAL(9,Y42:Y44) -> 17035.975 | Z45: =SUBTOTAL(9,Z42:Z44) -> 16793.109 | AA45: =SUBTOTAL(9,AA42:AA44) -> 15257.865 | AB45: =Y45-Z45 -> 242.86605 | AC45: =Y45-AA45 -> 1778.1105 | AD45: =IFERROR((Y45-Z45)/ABS(Z45),0) -> 0.014462244 | AE45: =IFERROR((Y45-AA45)/ABS(AA45),0) -> 0.11653731 | AG45: =SUBTOTAL(9,AG42:AG44) -> -236.76924 | AH45: =SUBTOTAL(9,AH42:AH44) -> -462.51498 | AI45: =SUBTOTAL(9,AI42:AI44) -> -266.22333 | AJ45: =AG45-AH45 -> 225.74574 | AK45: =AG45-AI45 -> 29.45409 | AL45: =IFERROR((AG45-AH45)/ABS(AH45),0) -> 0.48808309 | AM45: =IFERROR((AG45-AI45)/ABS(AI45),0) -> 0.11063677 | AO45: =SUBTOTAL(9,AO42:AO44) -> -1246.4493 | AP45: =SUBTOTAL(9,AP42:AP44) -> -1304.6026 | AQ45: =SUBTOTAL(9,AQ42:AQ44) -> -1150.6808 | AR45: =AO45-AP45 -> 58.15336 | AS45: =AO45-AQ45 -> -95.768505 | AT45: =IFERROR((AO45-AP45)/ABS(AP45),0) -> 0.044575535 | AU45: =IFERROR((AO45-AQ45)/ABS(AQ45),0) -> -0.083227692 | AW45: =SUBTOTAL(9,AW42:AW44) -> 15552.757 | AX45: =SUBTOTAL(9,AX42:AX44) -> 15025.992 | AY45: =SUBTOTAL(9,AY42:AY44) -> 13840.961 | AZ45: =AW45-AX45 -> 526.76515 | BA45: =AW45-AY45 -> 1711.7961 | BB45: =IFERROR((AW45-AX45)/ABS(AX45),0) -> 0.035056931 | BC45: =IFERROR((AW45-AY45)/ABS(AY45),0) -> 0.1236761 | BE45: =SUBTOTAL(9,BE42:BE44) -> -4229.5296 | BF45: =SUBTOTAL(9,BF42:BF44) -> -4800.596 | BG45: =SUBTOTAL(9,BG42:BG44) -> -4406.622 | BH45: =BE45-BF45 -> 571.06637 | BI45: =BE45-BG45 -> 177.09237 | BJ45: =IFERROR((BE45-BF45)/ABS(BF45),0) -> 0.11895739 | BK45: =IFERROR((BE45-BG45)/ABS(BG45),0) -> 0.040187783 | BM45: =SUBTOTAL(9,BM42:BM44) -> -1181.411 | BN45: =SUBTOTAL(9,BN42:BN44) -> -1177.033 | BO45: =SUBTOTAL(9,BO42:BO44) -> -1187.1513 | BP45: =BM45-BN45 -> -4.37798 | BQ45: =BM45-BO45 -> 5.74031 | BR45: =IFERROR((BM45-BN45)/ABS(BN45),0) -> -0.003719505 | BS45: =IFERROR((BM45-BO45)/ABS(BO45),0) -> 0.0048353653 | BU45: =SUBTOTAL(9,BU42:BU44) -> -2561.7107 | BV45: =SUBTOTAL(9,BV42:BV44) -> -2421.0872 | BW45: =SUBTOTAL(9,BW42:BW44) -> -2233.8491 | BX45: =BU45-BV45 -> -140.6235 | BY45: =BU45-BW45 -> -327.86162 | BZ45: =IFERROR((BU45-BV45)/ABS(BV45),0) -> -0.058082791 | CA45: =IFERROR((BU45-BW45)/ABS(BW45),0) -> -0.14676982 | CC45: =SUBTOTAL(9,CC42:CC44) -> 7580.1055 | CD45: =SUBTOTAL(9,CD42:CD44) -> 6627.2755 | CE45: =SUBTOTAL(9,CE42:CE44) -> 6013.3384 | CF45: =CC45-CD45 -> 952.83004 | CG45: =CC45-CE45 -> 1566.7672 | CH45: =IFERROR((CC45-CD45)/ABS(CD45),0) -> 0.14377402 | CI45: =IFERROR((CC45-CE45)/ABS(CE45),0) -> 0.26054865 | CK45: =SUBTOTAL(9,CK42:CK44) -> -3319.9066 | CL45: =SUBTOTAL(9,CL42:CL44) -> -1566.1391 | CM45: =SUBTOTAL(9,CM42:CM44) -> -1678.8617 | CN45: =CK45-CL45 -> -1753.7674 | CO45: =CK45-CM45 -> -1641.0449 | CP45: =IFERROR((CK45-CL45)/ABS(CL45),0) -> -1.1198031 | CQ45: =IFERROR((CK45-CM45)/ABS(CM45),0) -> -0.97747477 | CS45: =SUBTOTAL(9,CS42:CS44) -> 4260.199 | CT45: =SUBTOTAL(9,CT42:CT44) -> 5061.1364 | CU45: =SUBTOTAL(9,CU42:CU44) -> 4334.4767 | CV45: =CS45-CT45 -> -800.93737 | CW45: =CS45-CU45 -> -74.277734 | CX45: =IFERROR((CS45-CT45)/ABS(CT45),0) -> -0.15825248 | CY45: =IFERROR((CS45-CU45)/ABS(CU45),0) -> -0.017136494
B46: Grand Total | I46: =SUBTOTAL(9,I6:I45) -> 664953.09 | J46: =SUBTOTAL(9,J6:J45) -> 675599.34 | K46: =SUBTOTAL(9,K6:K45) -> 676186.75 | L46: =I46-J46 -> -10646.251 | M46: =I46-K46 -> -11233.658 | N46: =IFERROR((I46-J46)/ABS(J46),0) -> -0.015758231 | O46: =IFERROR((I46-K46)/ABS(K46),0) -> -0.016613248 | Q46: =SUBTOTAL(9,Q6:Q45) -> 25267.827 | R46: =SUBTOTAL(9,R6:R45) -> 34557.18 | S46: =SUBTOTAL(9,S6:S45) -> 34161.963 | T46: =Q46-R46 -> -9289.353 | U46: =Q46-S46 -> -8894.1357 | V46: =IFERROR((Q46-R46)/ABS(R46),0) -> -0.26881108 | W46: =IFERROR((Q46-S46)/ABS(S46),0) -> -0.26035201 | Y46: =SUBTOTAL(9,Y6:Y45) -> 158749.97 | Z46: =SUBTOTAL(9,Z6:Z45) -> 165454.98 | AA46: =SUBTOTAL(9,AA6:AA45) -> 157464.02 | AB46: =Y46-Z46 -> -6705.009 | AC46: =Y46-AA46 -> 1285.9455 | AD46: =IFERROR((Y46-Z46)/ABS(Z46),0) -> -0.040524674 | AE46: =IFERROR((Y46-AA46)/ABS(AA46),0) -> 0.0081665987 | AG46: =SUBTOTAL(9,AG6:AG45) -> -2235.3481 | AH46: =SUBTOTAL(9,AH6:AH45) -> -4168.7274 | AI46: =SUBTOTAL(9,AI6:AI45) -> -3218.6299 | AJ46: =AG46-AH46 -> 1933.3792 | AK46: =AG46-AI46 -> 983.28174 | AL46: =IFERROR((AG46-AH46)/ABS(AH46),0) -> 0.46378164 | AM46: =IFERROR((AG46-AI46)/ABS(AI46),0) -> 0.30549699 | AO46: =SUBTOTAL(9,AO6:AO45) -> -11395.906 | AP46: =SUBTOTAL(9,AP6:AP45) -> -12527.007 | AQ46: =SUBTOTAL(9,AQ6:AQ45) -> -10988.856 | AR46: =AO46-AP46 -> 1131.1003 | AS46: =AO46-AQ46 -> -407.04998 | AT46: =IFERROR((AO46-AP46)/ABS(AP46),0) -> 0.090292941 | AU46: =IFERROR((AO46-AQ46)/ABS(AQ46),0) -> -0.03704207 | AW46: =SUBTOTAL(9,AW6:AW45) -> 145118.71 | AX46: =SUBTOTAL(9,AX6:AX45) -> 148759.24 | AY46: =SUBTOTAL(9,AY6:AY45) -> 143256.54 | AZ46: =AW46-AX46 -> -3640.5295 | BA46: =AW46-AY46 -> 1862.1772 | BB46: =IFERROR((AW46-AX46)/ABS(AX46),0) -> -0.024472627 | BC46: =IFERROR((AW46-AY46)/ABS(AY46),0) -> 0.012998899 | BE46: =SUBTOTAL(9,BE6:BE45) -> -45899.262 | BF46: =SUBTOTAL(9,BF6:BF45) -> -46209.787 | BG46: =SUBTOTAL(9,BG6:BG45) -> -45900.513 | BH46: =BE46-BF46 -> 310.5249 | BI46: =BE46-BG46 -> 1.25121 | BJ46: =IFERROR((BE46-BF46)/ABS(BF46),0) -> 0.0067198947 | BK46: =IFERROR((BE46-BG46)/ABS(BG46),0) -> 2.7259172e-05 | BM46: =SUBTOTAL(9,BM6:BM45) -> -16420.034 | BN46: =SUBTOTAL(9,BN6:BN45) -> -17105.669 | BO46: =SUBTOTAL(9,BO6:BO45) -> -17785.389 | BP46: =BM46-BN46 -> 685.63499 | BQ46: =BM46-BO46 -> 1365.3548 | BR46: =IFERROR((BM46-BN46)/ABS(BN46),0) -> 0.040082326 | BS46: =IFERROR((BM46-BO46)/ABS(BO46),0) -> 0.076768344 | BU46: =SUBTOTAL(9,BU6:BU45) -> -27506.979 | BV46: =SUBTOTAL(9,BV6:BV45) -> -26669.181 | BW46: =SUBTOTAL(9,BW6:BW45) -> -26593.737 | BX46: =BU46-BV46 -> -837.79842 | BY46: =BU46-BW46 -> -913.24243 | BZ46: =IFERROR((BU46-BV46)/ABS(BV46),0) -> -0.031414479 | CA46: =IFERROR((BU46-BW46)/ABS(BW46),0) -> -0.034340508 | CC46: =SUBTOTAL(9,CC6:CC45) -> 55292.439 | CD46: =SUBTOTAL(9,CD6:CD45) -> 58774.607 | CE46: =SUBTOTAL(9,CE6:CE45) -> 52976.898 | CF46: =CC46-CD46 -> -3482.168 | CG46: =CC46-CE46 -> 2315.5409 | CH46: =IFERROR((CC46-CD46)/ABS(CD46),0) -> -0.05924613 | CI46: =IFERROR((CC46-CE46)/ABS(CE46),0) -> 0.043708502 | CK46: =SUBTOTAL(9,CK6:CK45) -> -17957.093 | CL46: =SUBTOTAL(9,CL6:CL45) -> -15539.098 | CM46: =SUBTOTAL(9,CM6:CM45) -> -14047.16 | CN46: =CK46-CL46 -> -2417.9943 | CO46: =CK46-CM46 -> -3909.9323 | CP46: =IFERROR((CK46-CL46)/ABS(CL46),0) -> -0.15560712 | CQ46: =IFERROR((CK46-CM46)/ABS(CM46),0) -> -0.27834326 | CS46: =SUBTOTAL(9,CS6:CS45) -> 37335.347 | CT46: =SUBTOTAL(9,CT6:CT45) -> 43235.509 | CU46: =SUBTOTAL(9,CU6:CU45) -> 38929.738 | CV46: =SUBTOTAL(9,CV6:CV44) -> -10327.366 | CW46: =SUBTOTAL(9,CW6:CW44) -> -4893.6581 | CX46: =IFERROR((CS46-CT46)/ABS(CT46),0) -> -0.13646566 | CY46: =IFERROR((CS46-CU46)/ABS(CU46),0) -> -0.040955618

Sheet Store P&L Y2025B & Y2024A
B2: Stores P&L - Y2025B & Y2024A
B3: (SAR'000')
I4: Sales | L4: Product Margin | O4: Commercial Margin | R4: Stock Loss | U4: Supply Chain Expenses | X4: Gross Profit | AA4: Staff Expense | AD4: Operating Expenses | AG4: Rent Expense | AJ4: EBITDA | AM4: Depreciation & Interest | AP4: Net Income / (Loss)
B5: Region | C5: District | D5: Location | E5: Loc Name | F5: Format | G5: Status | I5: Y2025B | J5: Y2024A | L5: Y2025B | M5: Y2024A | O5: Y2025B | P5: Y2024A | R5: Y2025B | S5: Y2024A | U5: Y2025B | V5: Y2024A | X5: Y2025B | Y5: Y2024A | AA5: Y2025B | AB5: Y2024A | AD5: Y2025B | AE5: Y2024A | AG5: Y2025B | AH5: Y2024A | AJ5: Y2025B | AK5: Y2024A | AM5: Y2025B | AN5: Y2024A | AP5: Y2025B | AQ5: Y2024A
B6: Central | C6: Riyadh - Crescent | D6: 110 | E6: Al Quds-Re Opened | F6: Super | G6: LFL | I6: =SUMIFS('Y2025B & Y2024A'!$D:$D,'Y2025B & Y2024A'!$B:$B,$D6,'Y2025B & Y2024A'!$C:$C,$I$4) -> 74279.883 | J6: =SUMIFS('Y2025B & Y2024A'!$F:$F,'Y2025B & Y2024A'!$B:$B,$D6,'Y2025B & Y2024A'!$C:$C,$I$4) -> 72771.665 | L6: =SUMIFS('Y2025B & Y2024A'!$D:$D,'Y2025B & Y2024A'!$B:$B,$D6,'Y2025B & Y2024A'!$C:$C,$L$4) -> 7450.6475 | M6: =SUMIFS('Y2025B & Y2024A'!$F:$F,'Y2025B & Y2024A'!$B:$B,$D6,'Y2025B & Y2024A'!$C:$C,$L$4) -> 7812.0152 | O6: =SUMIFS('Y2025B & Y2024A'!$D:$D,'Y2025B & Y2024A'!$B:$B,$D6,'Y2025B & Y2024A'!$C:$C,$O$4) -> 21497.114 | P6: =SUMIFS('Y2025B & Y2024A'!$F:$F,'Y2025B & Y2024A'!$B:$B,$D6,'Y2025B & Y2024A'!$C:$C,$O$4) -> 21139.972 | R6: =SUMIFS('Y2025B & Y2024A'!$D:$D,'Y2025B & Y2024A'!$B:$B,$D6,'Y2025B & Y2024A'!$C:$C,$R$4) -> -398.49456 | S6: =SUMIFS('Y2025B & Y2024A'!$F:$F,'Y2025B & Y2024A'!$B:$B,$D6,'Y2025B & Y2024A'!$C:$C,$R$4) -> -352.47011 | U6: =SUMIFS('Y2025B & Y2024A'!$D:$D,'Y2025B & Y2024A'!$B:$B,$D6,'Y2025B & Y2024A'!$C:$C,$U$4) -> -1377.399 | V6: =SUMIFS('Y2025B & Y2024A'!$F:$F,'Y2025B & Y2024A'!$B:$B,$D6,'Y2025B & Y2024A'!$C:$C,$U$4) -> -1234.985 | X6: =SUMIFS('Y2025B & Y2024A'!$D:$D,'Y2025B & Y2024A'!$B:$B,$D6,'Y2025B & Y2024A'!$C:$C,$X$4) -> 19721.221 | Y6: =SUMIFS('Y2025B & Y2024A'!$F:$F,'Y2025B & Y2024A'!$B:$B,$D6,'Y2025B & Y2024A'!$C:$C,$X$4) -> 19552.517 | AA6: =SUMIFS('Y2025B & Y2024A'!$D:$D,'Y2025B & Y2024A'!$B:$B,$D6,'Y2025B & Y2024A'!$C:$C,$AA$4) -> -5261.5625 | AB6: =SUMIFS('Y2025B & Y2024A'!$F:$F,'Y2025B & Y2024A'!$B:$B,$D6,'Y2025B & Y2024A'!$C:$C,$AA$4) -> -5050.1943 | AD6: =SUMIFS('Y2025B & Y2024A'!$D:$D,'Y2025B & Y2024A'!$B:$B,$D6,'Y2025B & Y2024A'!$C:$C,$AD$4) -> -2071.1289 | AE6: =SUMIFS('Y2025B & Y2024A'!$F:$F,'Y2025B & Y2024A'!$B:$B,$D6,'Y2025B & Y2024A'!$C:$C,$AD$4) -> -2117.4765 | AG6: =SUMIFS('Y2025B & Y2024A'!$D:$D,'Y2025B & Y2024A'!$B:$B,$D6,'Y2025B & Y2024A'!$C:$C,$AG$4) -> -2707.4657 | AH6: =SUMIFS('Y2025B & Y2024A'!$F:$F,'Y2025B & Y2024A'!$B:$B,$D6,'Y2025B & Y2024A'!$C:$C,$AG$4) -> -2707.4657 | AJ6: =SUMIFS('Y2025B & Y2024A'!$D:$D,'Y2025B & Y2024A'!$B:$B,$D6,'Y2025B & Y2024A'!$C:$C,$AJ$4) -> 9681.0637 | AK6: =SUMIFS('Y2025B & Y2024A'!$F:$F,'Y2025B & Y2024A'!$B:$B,$D6,'Y2025B & Y2024A'!$C:$C,$AJ$4) -> 9677.3803 | AM6: =SUMIFS('Y2025B & Y2024A'!$D:$D,'Y2025B & Y2024A'!$B:$B,$D6,'Y2025B & Y2024A'!$C:$C,$AM$4) -> -1726.142 | AN6: =SUMIFS('Y2025B & Y2024A'!$F:$F,'Y2025B & Y2024A'!$B:$B,$D6,'Y2025B & Y2024A'!$C:$C,$AM$4) -> -2593.8084 | AP6: =SUMIFS('Y2025B & Y2024A'!$D:$D,'Y2025B & Y2024A'!$B:$B,$D6,'Y2025B & Y2024A'!$C:$C,$AP$4) -> 7954.9217 | AQ6: =SUMIFS('Y2025B & Y2024A'!$F:$F,'Y2025B & Y2024A'!$B:$B,$D6,'Y2025B & Y2024A'!$C:$C,$AP$4) -> 7083.5718
